Workbook

Sheet Dashboard
A1: FW26 — MERCHANDISE PLAN DASHBOARD
A2: Auto-populated. Do not edit.
A4: OTB SUMMARY
A5: Metric | B5: Value
A6: Collection | B6: ='OTB Budget'!B4 -> FW26
A7: Total OTB Budget | B7: ='OTB Budget'!B5 -> 500000
A8: Total Planned Retail | B8: ='FW26 Styles'!Q505 -> 0
A9: Total Planned Cost | B9: ='FW26 Styles'!P505 -> 0
A10: Blended Margin % | B10: ='FW26 Styles'!M505 -> 0
A11: Total Units | B11: ='FW26 Styles'!O505 -> 0
A12: Budget Remaining | B12: ='OTB Budget'!B5-'FW26 Styles'!Q505 -> 500000
A13: Last Season Revenue | B13: ='Last Season Data'!N562 -> 3495803.6 | C13: 1 week of sales
A14: Last Season Units | B14: ='Last Season Data'!M562 -> 75457
A16: BY DROP
A17: Drop | B17: OTB ($) | C17: Planned Retail ($) | D17: Planned Cost ($) | E17: Margin % | F17: Units | G17: Remaining ($)
A18: Drop 1 - Sep | B18: ='OTB Budget'!C10 -> 0 | C18: =SUMIFS('FW26 Styles'!Q5:Q574,'FW26 Styles'!I5:I574,A18) -> 0 | D18: =SUMIFS('FW26 Styles'!P5:P574,'FW26 Styles'!I5:I574,A18) -> 0 | E18: =IF(C18=0,"",1-(D18/C18)) | F18: =SUMIFS('FW26 Styles'!O5:O574,'FW26 Styles'!I5:I574,A18) -> 0 | G18: =B18-C18 -> 0
A19: Drop 2 - Oct | B19: ='OTB Budget'!C11 -> 0 | C19: =SUMIFS('FW26 Styles'!Q5:Q574,'FW26 Styles'!I5:I574,A19) -> 0 | D19: =SUMIFS('FW26 Styles'!P5:P574,'FW26 Styles'!I5:I574,A19) -> 0 | E19: =IF(C19=0,"",1-(D19/C19)) | F19: =SUMIFS('FW26 Styles'!O5:O574,'FW26 Styles'!I5:I574,A19) -> 0 | G19: =B19-C19 -> 0
A20: Drop 3 - Nov | B20: ='OTB Budget'!C12 -> 0 | C20: =SUMIFS('FW26 Styles'!Q5:Q574,'FW26 Styles'!I5:I574,A20) -> 0 | D20: =SUMIFS('FW26 Styles'!P5:P574,'FW26 Styles'!I5:I574,A20) -> 0 | E20: =IF(C20=0,"",1-(D20/C20)) | F20: =SUMIFS('FW26 Styles'!O5:O574,'FW26 Styles'!I5:I574,A20) -> 0 | G20: =B20-C20 -> 0
A21: TOTAL | B21: =SUM(B18:B20) -> 0 | C21: =SUM(C18:C20) -> 0 | D21: =SUM(D18:D20) -> 0 | E21: =IF(C21=0,"",1-(D21/C21)) | F21: =SUM(F18:F20) -> 0 | G21: =SUM(G18:G20) -> 0
A23: BY TIER
A24: Tier | B24: Planned Retail ($) | C24: Planned Cost ($) | D24: Margin % | E24: Units | F24: # Styles | G24: % of Total
A25: Trend | B25: =SUMIFS('FW26 Styles'!Q5:Q574,'FW26 Styles'!J5:J574,A25) -> 0 | C25: =SUMIFS('FW26 Styles'!P5:P574,'FW26 Styles'!J5:J574,A25) -> 0 | D25: =IF(B25=0,"",1-(C25/B25)) | E25: =SUMIFS('FW26 Styles'!O5:O574,'FW26 Styles'!J5:J574,A25) -> 0 | F25: =COUNTIF('FW26 Styles'!J5:J574,A25) -> 15 | G25: =IF('FW26 Styles'!Q505=0,"",B25/'FW26 Styles'!Q505) | H25: What is the margin banding for each tier based on the buy contribution
A26: Commercial | B26: =SUMIFS('FW26 Styles'!Q5:Q574,'FW26 Styles'!J5:J574,A26) -> 0 | C26: =SUMIFS('FW26 Styles'!P5:P574,'FW26 Styles'!J5:J574,A26) -> 0 | D26: =IF(B26=0,"",1-(C26/B26)) | E26: =SUMIFS('FW26 Styles'!O5:O574,'FW26 Styles'!J5:J574,A26) -> 0 | F26: =COUNTIF('FW26 Styles'!J5:J574,A26) -> 32 | G26: =IF('FW26 Styles'!Q505=0,"",B26/'FW26 Styles'!Q505) | H26: Price band analysis
A27: Volume | B27: =SUMIFS('FW26 Styles'!Q5:Q574,'FW26 Styles'!J5:J574,A27) -> 0 | C27: =SUMIFS('FW26 Styles'!P5:P574,'FW26 Styles'!J5:J574,A27) -> 0 | D27: =IF(B27=0,"",1-(C27/B27)) | E27: =SUMIFS('FW26 Styles'!O5:O574,'FW26 Styles'!J5:J574,A27) -> 0 | F27: =COUNTIF('FW26 Styles'!J5:J574,A27) -> 0 | G27: =IF('FW26 Styles'!Q505=0,"",B27/'FW26 Styles'!Q505) | H27: Sub 70% margin - Ask the why
A28: TOTAL | B28: =SUM(B25:B27) -> 0 | C28: =SUM(C25:C27) -> 0 | D28: =IF(B28=0,"",1-(C28/B28)) | E28: =SUM(E25:E27) -> 0 | F28: =SUM(F25:F27) -> 47
A30: CATEGORY ROLLUP — PROPOSED vs LAST SEASON
A31: Main Category | B31: Category | C31: Sub Category | D31: Proposed Retail ($) | E31: Proposed Cost ($) | F31: Margin % | G31: Proposed Units | H31: LS Revenue ($) | I31: LS Units | J31: Rev vs LS ($) | K31: Rev vs LS (%) | L31: Units vs LS
A32: Headwear | B32: Scarves | C32: Premium | D32: =SUMIFS('FW26 Styles'!Q5:Q574,'FW26 Styles'!A5:A574,A32,'FW26 Styles'!B5:B574,B32,'FW26 Styles'!C5:C574,C32) -> 0 | E32: =SUMIFS('FW26 Styles'!P5:P574,'FW26 Styles'!A5:A574,A32,'FW26 Styles'!B5:B574,B32,'FW26 Styles'!C5:C574,C32) -> 0 | F32: =IF(D32=0,"",1-(E32/D32)) | G32: =SUMIFS('FW26 Styles'!O5:O574,'FW26 Styles'!A5:A574,A32,'FW26 Styles'!B5:B574,B32,'FW26 Styles'!C5:C574,C32) -> 0 | H32: =SUMIFS('Last Season Data'!N5:N561,'Last Season Data'!B5:B561,A32,'Last Season Data'!C5:C561,B32,'Last Season Data'!D5:D561,C32) -> 566134.71 | I32: =SUMIFS('Last Season Data'!M5:M561,'Last Season Data'!B5:B561,A32,'Last Season Data'!C5:C561,B32,'Last Season Data'!D5:D561,C32) -> 23758 | J32: =D32-H32 -> -566134.71 | K32: =IF(H32=0,"",(D32-H32)/H32) -> -1 | L32: =G32-I32 -> -23758
A33: Headwear | B33: Scarves | C33: Bamboo | D33: =SUMIFS('FW26 Styles'!Q5:Q574,'FW26 Styles'!A5:A574,A33,'FW26 Styles'!B5:B574,B33,'FW26 Styles'!C5:C574,C33) -> 0 | E33: =SUMIFS('FW26 Styles'!P5:P574,'FW26 Styles'!A5:A574,A33,'FW26 Styles'!B5:B574,B33,'FW26 Styles'!C5:C574,C33) -> 0 | F33: =IF(D33=0,"",1-(E33/D33)) | G33: =SUMIFS('FW26 Styles'!O5:O574,'FW26 Styles'!A5:A574,A33,'FW26 Styles'!B5:B574,B33,'FW26 Styles'!C5:C574,C33) -> 0 | H33: =SUMIFS('Last Season Data'!N6:N562,'Last Season Data'!B6:B562,A33,'Last Season Data'!C6:C562,B33,'Last Season Data'!D6:D562,C33) -> 171288.54 | I33: =SUMIFS('Last Season Data'!M5:M561,'Last Season Data'!B5:B561,A33,'Last Season Data'!C5:C561,B33,'Last Season Data'!D5:D561,C33) -> 5230 | J33: =D33-H33 -> -171288.54 | K33: =IF(H33=0,"",(D33-H33)/H33) -> -1 | L33: =G33-I33 -> -5230
A34: Headwear | B34: Scarves | C34: Breathable | D34: =SUMIFS('FW26 Styles'!Q5:Q574,'FW26 Styles'!A5:A574,A34,'FW26 Styles'!B5:B574,B34,'FW26 Styles'!C5:C574,C34) -> 0 | E34: =SUMIFS('FW26 Styles'!P5:P574,'FW26 Styles'!A5:A574,A34,'FW26 Styles'!B5:B574,B34,'FW26 Styles'!C5:C574,C34) -> 0 | F34: =IF(D34=0,"",1-(E34/D34)) | G34: =SUMIFS('FW26 Styles'!O5:O574,'FW26 Styles'!A5:A574,A34,'FW26 Styles'!B5:B574,B34,'FW26 Styles'!C5:C574,C34) -> 0 | H34: =SUMIFS('Last Season Data'!N7:N563,'Last Season Data'!B7:B563,A34,'Last Season Data'!C7:C563,B34,'Last Season Data'!D7:D563,C34) -> 102172.52 | I34: =SUMIFS('Last Season Data'!M5:M561,'Last Season Data'!B5:B561,A34,'Last Season Data'!C5:C561,B34,'Last Season Data'!D5:D561,C34) -> 2723 | J34: =D34-H34 -> -102172.52 | K34: =IF(H34=0,"",(D34-H34)/H34) -> -1 | L34: =G34-I34 -> -2723
A35: Headwear | B35: Scarves | C35: Liquid | D35: =SUMIFS('FW26 Styles'!Q5:Q574,'FW26 Styles'!A5:A574,A35,'FW26 Styles'!B5:B574,B35,'FW26 Styles'!C5:C574,C35) -> 0 | E35: =SUMIFS('FW26 Styles'!P5:P574,'FW26 Styles'!A5:A574,A35,'FW26 Styles'!B5:B574,B35,'FW26 Styles'!C5:C574,C35) -> 0 | F35: =IF(D35=0,"",1-(E35/D35)) | G35: =SUMIFS('FW26 Styles'!O5:O574,'FW26 Styles'!A5:A574,A35,'FW26 Styles'!B5:B574,B35,'FW26 Styles'!C5:C574,C35) -> 0 | H35: =SUMIFS('Last Season Data'!N8:N564,'Last Season Data'!B8:B564,A35,'Last Season Data'!C8:C564,B35,'Last Season Data'!D8:D564,C35) -> 280896.89 | I35: =SUMIFS('Last Season Data'!M5:M561,'Last Season Data'!B5:B561,A35,'Last Season Data'!C5:C561,B35,'Last Season Data'!D5:D561,C35) -> 11742 | J35: =D35-H35 -> -280896.89 | K35: =IF(H35=0,"",(D35-H35)/H35) -> -1 | L35: =G35-I35 -> -11742
A36: Headwear | B36: Scarves | C36: Decorative | D36: =SUMIFS('FW26 Styles'!Q5:Q574,'FW26 Styles'!A5:A574,A36,'FW26 Styles'!B5:B574,B36,'FW26 Styles'!C5:C574,C36) -> 0 | E36: =SUMIFS('FW26 Styles'!P5:P574,'FW26 Styles'!A5:A574,A36,'FW26 Styles'!B5:B574,B36,'FW26 Styles'!C5:C574,C36) -> 0 | F36: =IF(D36=0,"",1-(E36/D36)) | G36: =SUMIFS('FW26 Styles'!O5:O574,'FW26 Styles'!A5:A574,A36,'FW26 Styles'!B5:B574,B36,'FW26 Styles'!C5:C574,C36) -> 0 | H36: =SUMIFS('Last Season Data'!N9:N565,'Last Season Data'!B9:B565,A36,'Last Season Data'!C9:C565,B36,'Last Season Data'!D9:D565,C36) -> 293247.3 | I36: =SUMIFS('Last Season Data'!M5:M561,'Last Season Data'!B5:B561,A36,'Last Season Data'!C5:C561,B36,'Last Season Data'!D5:D561,C36) -> 6195 | J36: =D36-H36 -> -293247.3 | K36: =IF(H36=0,"",(D36-H36)/H36) -> -1 | L36: =G36-I36 -> -6195
A37: Headwear | B37: Scarves | C37: New 1 | D37: =SUMIFS('FW26 Styles'!Q5:Q574,'FW26 Styles'!A5:A574,A37,'FW26 Styles'!B5:B574,B37,'FW26 Styles'!C5:C574,C37) -> 0 | E37: =SUMIFS('FW26 Styles'!P5:P574,'FW26 Styles'!A5:A574,A37,'FW26 Styles'!B5:B574,B37,'FW26 Styles'!C5:C574,C37) -> 0 | F37: =IF(D37=0,"",1-(E37/D37)) | G37: =SUMIFS('FW26 Styles'!O5:O574,'FW26 Styles'!A5:A574,A37,'FW26 Styles'!B5:B574,B37,'FW26 Styles'!C5:C574,C37) -> 0 | H37: =SUMIFS('Last Season Data'!N10:N566,'Last Season Data'!B10:B566,A37,'Last Season Data'!C10:C566,B37,'Last Season Data'!D10:D566,C37) -> 0 | I37: =SUMIFS('Last Season Data'!M5:M561,'Last Season Data'!B5:B561,A37,'Last Season Data'!C5:C561,B37,'Last Season Data'!D5:D561,C37) -> 0 | J37: =D37-H37 -> 0 | K37: =IF(H37=0,"",(D37-H37)/H37) | L37: =G37-I37 -> 0
A38: Headwear | B38: Scarves | C38: New 2 | D38: =SUMIFS('FW26 Styles'!Q5:Q574,'FW26 Styles'!A5:A574,A38,'FW26 Styles'!B5:B574,B38,'FW26 Styles'!C5:C574,C38) -> 0 | E38: =SUMIFS('FW26 Styles'!P5:P574,'FW26 Styles'!A5:A574,A38,'FW26 Styles'!B5:B574,B38,'FW26 Styles'!C5:C574,C38) -> 0 | F38: =IF(D38=0,"",1-(E38/D38)) | G38: =SUMIFS('FW26 Styles'!O5:O574,'FW26 Styles'!A5:A574,A38,'FW26 Styles'!B5:B574,B38,'FW26 Styles'!C5:C574,C38) -> 0 | H38: =SUMIFS('Last Season Data'!N11:N567,'Last Season Data'!B11:B567,A38,'Last Season Data'!C11:C567,B38,'Last Season Data'!D11:D567,C38) -> 0 | I38: =SUMIFS('Last Season Data'!M5:M561,'Last Season Data'!B5:B561,A38,'Last Season Data'!C5:C561,B38,'Last Season Data'!D5:D561,C38) -> 0 | J38: =D38-H38 -> 0 | K38: =IF(H38=0,"",(D38-H38)/H38) | L38: =G38-I38 -> 0
A39: Headwear | B39: Scarves | C39: New 3 | D39: =SUMIFS('FW26 Styles'!Q5:Q574,'FW26 Styles'!A5:A574,A39,'FW26 Styles'!B5:B574,B39,'FW26 Styles'!C5:C574,C39) -> 0 | E39: =SUMIFS('FW26 Styles'!P5:P574,'FW26 Styles'!A5:A574,A39,'FW26 Styles'!B5:B574,B39,'FW26 Styles'!C5:C574,C39) -> 0 | F39: =IF(D39=0,"",1-(E39/D39)) | G39: =SUMIFS('FW26 Styles'!O5:O574,'FW26 Styles'!A5:A574,A39,'FW26 Styles'!B5:B574,B39,'FW26 Styles'!C5:C574,C39) -> 0 | H39: =SUMIFS('Last Season Data'!N12:N568,'Last Season Data'!B12:B568,A39,'Last Season Data'!C12:C568,B39,'Last Season Data'!D12:D568,C39) -> 0 | I39: =SUMIFS('Last Season Data'!M5:M561,'Last Season Data'!B5:B561,A39,'Last Season Data'!C5:C561,B39,'Last Season Data'!D5:D561,C39) -> 0 | J39: =D39-H39 -> 0 | K39: =IF(H39=0,"",(D39-H39)/H39) | L39: =G39-I39 -> 0
B40: Scarves Subtotal | D40: =SUM(D32:D39) -> 0 | E40: =SUM(E32:E39) -> 0 | F40: =IF(D40=0,"",1-(E40/D40)) | G40: =SUM(G32:G39) -> 0 | H40: =SUM(H32:H39) -> 1413740 | I40: =SUM(I32:I39) -> 49648 | J40: =SUM(J32:J39) -> -1413740 | K40: =IF(H40=0,"",(D40-H40)/H40) -> -1 | L40: =SUM(L32:L39) -> -49648
A41: Headwear | B41: Hijab | C41: Premium | D41: =SUMIFS('FW26 Styles'!Q5:Q574,'FW26 Styles'!A5:A574,A41,'FW26 Styles'!B5:B574,B41,'FW26 Styles'!C5:C574,C41) -> 0 | E41: =SUMIFS('FW26 Styles'!P5:P574,'FW26 Styles'!A5:A574,A41,'FW26 Styles'!B5:B574,B41,'FW26 Styles'!C5:C574,C41) -> 0 | F41: =IF(D41=0,"",1-(E41/D41)) | G41: =SUMIFS('FW26 Styles'!O5:O574,'FW26 Styles'!A5:A574,A41,'FW26 Styles'!B5:B574,B41,'FW26 Styles'!C5:C574,C41) -> 0 | H41: =SUMIFS('Last Season Data'!N5:N561,'Last Season Data'!B5:B561,A41,'Last Season Data'!C5:C561,B41,'Last Season Data'!D5:D561,C41) -> 0 | I41: =SUMIFS('Last Season Data'!M5:M561,'Last Season Data'!B5:B561,A41,'Last Season Data'!C5:C561,B41,'Last Season Data'!D5:D561,C41) -> 0 | J41: =D41-H41 -> 0 | K41: =IF(H41=0,"",(D41-H41)/H41) | L41: =G41-I41 -> 0
A42: Headwear | B42: Hijab | C42: Bamboo | D42: =SUMIFS('FW26 Styles'!Q5:Q574,'FW26 Styles'!A5:A574,A42,'FW26 Styles'!B5:B574,B42,'FW26 Styles'!C5:C574,C42) -> 0 | E42: =SUMIFS('FW26 Styles'!P5:P574,'FW26 Styles'!A5:A574,A42,'FW26 Styles'!B5:B574,B42,'FW26 Styles'!C5:C574,C42) -> 0 | F42: =IF(D42=0,"",1-(E42/D42)) | G42: =SUMIFS('FW26 Styles'!O5:O574,'FW26 Styles'!A5:A574,A42,'FW26 Styles'!B5:B574,B42,'FW26 Styles'!C5:C574,C42) -> 0 | H42: =SUMIFS('Last Season Data'!N5:N561,'Last Season Data'!B5:B561,A42,'Last Season Data'!C5:C561,B42,'Last Season Data'!D5:D561,C42) -> 0 | I42: =SUMIFS('Last Season Data'!M5:M561,'Last Season Data'!B5:B561,A42,'Last Season Data'!C5:C561,B42,'Last Season Data'!D5:D561,C42) -> 0 | J42: =D42-H42 -> 0 | K42: =IF(H42=0,"",(D42-H42)/H42) | L42: =G42-I42 -> 0
A43: Headwear | B43: Hijab | C43: Breathable | D43: =SUMIFS('FW26 Styles'!Q5:Q574,'FW26 Styles'!A5:A574,A43,'FW26 Styles'!B5:B574,B43,'FW26 Styles'!C5:C574,C43) -> 0 | E43: =SUMIFS('FW26 Styles'!P5:P574,'FW26 Styles'!A5:A574,A43,'FW26 Styles'!B5:B574,B43,'FW26 Styles'!C5:C574,C43) -> 0 | F43: =IF(D43=0,"",1-(E43/D43)) | G43: =SUMIFS('FW26 Styles'!O5:O574,'FW26 Styles'!A5:A574,A43,'FW26 Styles'!B5:B574,B43,'FW26 Styles'!C5:C574,C43) -> 0 | H43: =SUMIFS('Last Season Data'!N5:N561,'Last Season Data'!B5:B561,A43,'Last Season Data'!C5:C561,B43,'Last Season Data'!D5:D561,C43) -> 0 | I43: =SUMIFS('Last Season Data'!M5:M561,'Last Season Data'!B5:B561,A43,'Last Season Data'!C5:C561,B43,'Last Season Data'!D5:D561,C43) -> 0 | J43: =D43-H43 -> 0 | K43: =IF(H43=0,"",(D43-H43)/H43) | L43: =G43-I43 -> 0
A44: Headwear | B44: Underscarf | C44: Underscarf | D44: =SUMIFS('FW26 Styles'!Q5:Q574,'FW26 Styles'!A5:A574,A44,'FW26 Styles'!B5:B574,B44,'FW26 Styles'!C5:C574,C44) -> 0 | E44: =SUMIFS('FW26 Styles'!P5:P574,'FW26 Styles'!A5:A574,A44,'FW26 Styles'!B5:B574,B44,'FW26 Styles'!C5:C574,C44) -> 0 | F44: =IF(D44=0,"",1-(E44/D44)) | G44: =SUMIFS('FW26 Styles'!O5:O574,'FW26 Styles'!A5:A574,A44,'FW26 Styles'!B5:B574,B44,'FW26 Styles'!C5:C574,C44) -> 0 | H44: =SUMIFS('Last Season Data'!N5:N561,'Last Season Data'!B5:B561,A44,'Last Season Data'!C5:C561,B44,'Last Season Data'!D5:D561,C44) -> 18224.45 | I44: =SUMIFS('Last Season Data'!M5:M561,'Last Season Data'!B5:B561,A44,'Last Season Data'!C5:C561,B44,'Last Season Data'!D5:D561,C44) -> 997 | J44: =D44-H44 -> -18224.45 | K44: =IF(H44=0,"",(D44-H44)/H44) -> -1 | L44: =G44-I44 -> -997
A45: Headwear | B45: Hijab | C45: New 2 | D45: =SUMIFS('FW26 Styles'!Q5:Q574,'FW26 Styles'!A5:A574,A45,'FW26 Styles'!B5:B574,B45,'FW26 Styles'!C5:C574,C45) -> 0 | E45: =SUMIFS('FW26 Styles'!P5:P574,'FW26 Styles'!A5:A574,A45,'FW26 Styles'!B5:B574,B45,'FW26 Styles'!C5:C574,C45) -> 0 | F45: =IF(D45=0,"",1-(E45/D45)) | G45: =SUMIFS('FW26 Styles'!O5:O574,'FW26 Styles'!A5:A574,A45,'FW26 Styles'!B5:B574,B45,'FW26 Styles'!C5:C574,C45) -> 0 | H45: =SUMIFS('Last Season Data'!N5:N561,'Last Season Data'!B5:B561,A45,'Last Season Data'!C5:C561,B45,'Last Season Data'!D5:D561,C45) -> 0 | I45: =SUMIFS('Last Season Data'!M5:M561,'Last Season Data'!B5:B561,A45,'Last Season Data'!C5:C561,B45,'Last Season Data'!D5:D561,C45) -> 0 | J45: =D45-H45 -> 0 | K45: =IF(H45=0,"",(D45-H45)/H45) | L45: =G45-I45 -> 0
A46: Headwear | B46: Hijab | C46: New 3 | D46: =SUMIFS('FW26 Styles'!Q5:Q574,'FW26 Styles'!A5:A574,A46,'FW26 Styles'!B5:B574,B46,'FW26 Styles'!C5:C574,C46) -> 0 | E46: =SUMIFS('FW26 Styles'!P5:P574,'FW26 Styles'!A5:A574,A46,'FW26 Styles'!B5:B574,B46,'FW26 Styles'!C5:C574,C46) -> 0 | F46: =IF(D46=0,"",1-(E46/D46)) | G46: =SUMIFS('FW26 Styles'!O5:O574,'FW26 Styles'!A5:A574,A46,'FW26 Styles'!B5:B574,B46,'FW26 Styles'!C5:C574,C46) -> 0 | H46: =SUMIFS('Last Season Data'!N5:N561,'Last Season Data'!B5:B561,A46,'Last Season Data'!C5:C561,B46,'Last Season Data'!D5:D561,C46) -> 0 | I46: =SUMIFS('Last Season Data'!M5:M561,'Last Season Data'!B5:B561,A46,'Last Season Data'!C5:C561,B46,'Last Season Data'!D5:D561,C46) -> 0 | J46: =D46-H46 -> 0 | K46: =IF(H46=0,"",(D46-H46)/H46) | L46: =G46-I46 -> 0
B47: Hijab Subtotal | D47: =SUM(D41:D46) -> 0 | E47: =SUM(E41:E46) -> 0 | F47: =IF(D47=0,"",1-(E47/D47)) | G47: =SUM(G41:G46) -> 0 | H47: =SUM(H41:H46) -> 18224.45 | I47: =SUM(I41:I46) -> 997 | J47: =SUM(J41:J46) -> -18224.45 | K47: =IF(H47=0,"",(D47-H47)/H47) -> -1 | L47: =SUM(L41:L46) -> -997
A48: Headwear | B48: Khimaar | C48: Premium | D48: =SUMIFS('FW26 Styles'!Q5:Q574,'FW26 Styles'!A5:A574,A48,'FW26 Styles'!B5:B574,B48,'FW26 Styles'!C5:C574,C48) -> 0 | E48: =SUMIFS('FW26 Styles'!P5:P574,'FW26 Styles'!A5:A574,A48,'FW26 Styles'!B5:B574,B48,'FW26 Styles'!C5:C574,C48) -> 0 | F48: =IF(D48=0,"",1-(E48/D48)) | G48: =SUMIFS('FW26 Styles'!O5:O574,'FW26 Styles'!A5:A574,A48,'FW26 Styles'!B5:B574,B48,'FW26 Styles'!C5:C574,C48) -> 0 | H48: =SUMIFS('Last Season Data'!N5:N561,'Last Season Data'!B5:B561,A48,'Last Season Data'!C5:C561,B48,'Last Season Data'!D5:D561,C48) -> 0 | I48: =SUMIFS('Last Season Data'!M5:M561,'Last Season Data'!B5:B561,A48,'Last Season Data'!C5:C561,B48,'Last Season Data'!D5:D561,C48) -> 0 | J48: =D48-H48 -> 0 | K48: =IF(H48=0,"",(D48-H48)/H48) | L48: =G48-I48 -> 0
A49: Headwear | B49: Khimaar | C49: Bamboo | D49: =SUMIFS('FW26 Styles'!Q5:Q574,'FW26 Styles'!A5:A574,A49,'FW26 Styles'!B5:B574,B49,'FW26 Styles'!C5:C574,C49) -> 0 | E49: =SUMIFS('FW26 Styles'!P5:P574,'FW26 Styles'!A5:A574,A49,'FW26 Styles'!B5:B574,B49,'FW26 Styles'!C5:C574,C49) -> 0 | F49: =IF(D49=0,"",1-(E49/D49)) | G49: =SUMIFS('FW26 Styles'!O5:O574,'FW26 Styles'!A5:A574,A49,'FW26 Styles'!B5:B574,B49,'FW26 Styles'!C5:C574,C49) -> 0 | H49: =SUMIFS('Last Season Data'!N5:N561,'Last Season Data'!B5:B561,A49,'Last Season Data'!C5:C561,B49,'Last Season Data'!D5:D561,C49) -> 0 | I49: =SUMIFS('Last Season Data'!M5:M561,'Last Season Data'!B5:B561,A49,'Last Season Data'!C5:C561,B49,'Last Season Data'!D5:D561,C49) -> 0 | J49: =D49-H49 -> 0 | K49: =IF(H49=0,"",(D49-H49)/H49) | L49: =G49-I49 -> 0
A50: Headwear | B50: Khimaar | C50: Breathable | D50: =SUMIFS('FW26 Styles'!Q5:Q574,'FW26 Styles'!A5:A574,A50,'FW26 Styles'!B5:B574,B50,'FW26 Styles'!C5:C574,C50) -> 0 | E50: =SUMIFS('FW26 Styles'!P5:P574,'FW26 Styles'!A5:A574,A50,'FW26 Styles'!B5:B574,B50,'FW26 Styles'!C5:C574,C50) -> 0 | F50: =IF(D50=0,"",1-(E50/D50)) | G50: =SUMIFS('FW26 Styles'!O5:O574,'FW26 Styles'!A5:A574,A50,'FW26 Styles'!B5:B574,B50,'FW26 Styles'!C5:C574,C50) -> 0 | H50: =SUMIFS('Last Season Data'!N5:N561,'Last Season Data'!B5:B561,A50,'Last Season Data'!C5:C561,B50,'Last Season Data'!D5:D561,C50) -> 0 | I50: =SUMIFS('Last Season Data'!M5:M561,'Last Season Data'!B5:B561,A50,'Last Season Data'!C5:C561,B50,'Last Season Data'!D5:D561,C50) -> 0 | J50: =D50-H50 -> 0 | K50: =IF(H50=0,"",(D50-H50)/H50) | L50: =G50-I50 -> 0
A51: Headwear | B51: Khimaar | C51: New 1 | D51: =SUMIFS('FW26 Styles'!Q5:Q574,'FW26 Styles'!A5:A574,A51,'FW26 Styles'!B5:B574,B51,'FW26 Styles'!C5:C574,C51) -> 0 | E51: =SUMIFS('FW26 Styles'!P5:P574,'FW26 Styles'!A5:A574,A51,'FW26 Styles'!B5:B574,B51,'FW26 Styles'!C5:C574,C51) -> 0 | F51: =IF(D51=0,"",1-(E51/D51)) | G51: =SUMIFS('FW26 Styles'!O5:O574,'FW26 Styles'!A5:A574,A51,'FW26 Styles'!B5:B574,B51,'FW26 Styles'!C5:C574,C51) -> 0 | H51: =SUMIFS('Last Season Data'!N5:N561,'Last Season Data'!B5:B561,A51,'Last Season Data'!C5:C561,B51,'Last Season Data'!D5:D561,C51) -> 0 | I51: =SUMIFS('Last Season Data'!M5:M561,'Last Season Data'!B5:B561,A51,'Last Season Data'!C5:C561,B51,'Last Season Data'!D5:D561,C51) -> 0 | J51: =D51-H51 -> 0 | K51: =IF(H51=0,"",(D51-H51)/H51) | L51: =G51-I51 -> 0
A52: Headwear | B52: Khimaar | C52: New 2 | D52: =SUMIFS('FW26 Styles'!Q5:Q574,'FW26 Styles'!A5:A574,A52,'FW26 Styles'!B5:B574,B52,'FW26 Styles'!C5:C574,C52) -> 0 | E52: =SUMIFS('FW26 Styles'!P5:P574,'FW26 Styles'!A5:A574,A52,'FW26 Styles'!B5:B574,B52,'FW26 Styles'!C5:C574,C52) -> 0 | F52: =IF(D52=0,"",1-(E52/D52)) | G52: =SUMIFS('FW26 Styles'!O5:O574,'FW26 Styles'!A5:A574,A52,'FW26 Styles'!B5:B574,B52,'FW26 Styles'!C5:C574,C52) -> 0 | H52: =SUMIFS('Last Season Data'!N5:N561,'Last Season Data'!B5:B561,A52,'Last Season Data'!C5:C561,B52,'Last Season Data'!D5:D561,C52) -> 0 | I52: =SUMIFS('Last Season Data'!M5:M561,'Last Season Data'!B5:B561,A52,'Last Season Data'!C5:C561,B52,'Last Season Data'!D5:D561,C52) -> 0 | J52: =D52-H52 -> 0 | K52: =IF(H52=0,"",(D52-H52)/H52) | L52: =G52-I52 -> 0
A53: Headwear | B53: Khimaar | C53: New 3 | D53: =SUMIFS('FW26 Styles'!Q5:Q574,'FW26 Styles'!A5:A574,A53,'FW26 Styles'!B5:B574,B53,'FW26 Styles'!C5:C574,C53) -> 0 | E53: =SUMIFS('FW26 Styles'!P5:P574,'FW26 Styles'!A5:A574,A53,'FW26 Styles'!B5:B574,B53,'FW26 Styles'!C5:C574,C53) -> 0 | F53: =IF(D53=0,"",1-(E53/D53)) | G53: =SUMIFS('FW26 Styles'!O5:O574,'FW26 Styles'!A5:A574,A53,'FW26 Styles'!B5:B574,B53,'FW26 Styles'!C5:C574,C53) -> 0 | H53: =SUMIFS('Last Season Data'!N5:N561,'Last Season Data'!B5:B561,A53,'Last Season Data'!C5:C561,B53,'Last Season Data'!D5:D561,C53) -> 0 | I53: =SUMIFS('Last Season Data'!M5:M561,'Last Season Data'!B5:B561,A53,'Last Season Data'!C5:C561,B53,'Last Season Data'!D5:D561,C53) -> 0 | J53: =D53-H53 -> 0 | K53: =IF(H53=0,"",(D53-H53)/H53) | L53: =G53-I53 -> 0
B54: Khimaar Subtotal | D54: =SUM(D48:D53) -> 0 | E54: =SUM(E48:E53) -> 0 | F54: =IF(D54=0,"",1-(E54/D54)) | G54: =SUM(G48:G53) -> 0 | H54: =SUM(H48:H53) -> 0 | I54: =SUM(I48:I53) -> 0 | J54: =SUM(J48:J53) -> 0 | K54: =IF(H54=0,"",(D54-H54)/H54) | L54: =SUM(L48:L53) -> 0
A55: Headwear TOTAL | D55: =SUMIFS(D32:D54,A32:A54,"Headwear") -> 0 | E55: =SUMIFS(E32:E54,A32:A54,"Headwear") -> 0 | F55: =IF(D55=0,"",1-(E55/D55)) | G55: =SUMIFS(G32:G54,A32:A54,"Headwear") -> 0 | H55: =SUMIFS(H32:H54,A32:A54,"Headwear") -> 1431964.4 | I55: =SUMIFS(I32:I54,A32:A54,"Headwear") -> 50645 | J55: =SUMIFS(J32:J54,A32:A54,"Headwear") -> -1431964.4 | K55: =IF(H55=0,"",(D55-H55)/H55) -> -1 | L55: =SUMIFS(L32:L54,A32:A54,"Headwear") -> -50645
A56: Clothing | B56: Dresses | C56: Casual | D56: =SUMIFS('FW26 Styles'!Q5:Q574,'FW26 Styles'!A5:A574,A56,'FW26 Styles'!B5:B574,B56,'FW26 Styles'!C5:C574,C56) -> 0 | E56: =SUMIFS('FW26 Styles'!P5:P574,'FW26 Styles'!A5:A574,A56,'FW26 Styles'!B5:B574,B56,'FW26 Styles'!C5:C574,C56) -> 0 | F56: =IF(D56=0,"",1-(E56/D56)) | G56: =SUMIFS('FW26 Styles'!O5:O574,'FW26 Styles'!A5:A574,A56,'FW26 Styles'!B5:B574,B56,'FW26 Styles'!C5:C574,C56) -> 0 | H56: =SUMIFS('Last Season Data'!N5:N561,'Last Season Data'!B5:B561,A56,'Last Season Data'!C5:C561,B56,'Last Season Data'!D5:D561,C56) -> 353219.3 | I56: =SUMIFS('Last Season Data'!M5:M561,'Last Season Data'!B5:B561,A56,'Last Season Data'!C5:C561,B56,'Last Season Data'!D5:D561,C56) -> 3424 | J56: =D56-H56 -> -353219.3 | K56: =IF(H56=0,"",(D56-H56)/H56) -> -1 | L56: =G56-I56 -> -3424
A57: Clothing | B57: Dresses | C57: Occasion | D57: =SUMIFS('FW26 Styles'!Q5:Q574,'FW26 Styles'!A5:A574,A57,'FW26 Styles'!B5:B574,B57,'FW26 Styles'!C5:C574,C57) -> 0 | E57: =SUMIFS('FW26 Styles'!P5:P574,'FW26 Styles'!A5:A574,A57,'FW26 Styles'!B5:B574,B57,'FW26 Styles'!C5:C574,C57) -> 0 | F57: =IF(D57=0,"",1-(E57/D57)) | G57: =SUMIFS('FW26 Styles'!O5:O574,'FW26 Styles'!A5:A574,A57,'FW26 Styles'!B5:B574,B57,'FW26 Styles'!C5:C574,C57) -> 0 | H57: =SUMIFS('Last Season Data'!N5:N561,'Last Season Data'!B5:B561,A57,'Last Season Data'!C5:C561,B57,'Last Season Data'!D5:D561,C57) -> 30277.18 | I57: =SUMIFS('Last Season Data'!M5:M561,'Last Season Data'!B5:B561,A57,'Last Season Data'!C5:C561,B57,'Last Season Data'!D5:D561,C57) -> 254 | J57: =D57-H57 -> -30277.18 | K57: =IF(H57=0,"",(D57-H57)/H57) -> -1 | L57: =G57-I57 -> -254
A58: Clothing | B58: Dresses | C58: Essential | D58: =SUMIFS('FW26 Styles'!Q5:Q574,'FW26 Styles'!A5:A574,A58,'FW26 Styles'!B5:B574,B58,'FW26 Styles'!C5:C574,C58) -> 0 | E58: =SUMIFS('FW26 Styles'!P5:P574,'FW26 Styles'!A5:A574,A58,'FW26 Styles'!B5:B574,B58,'FW26 Styles'!C5:C574,C58) -> 0 | F58: =IF(D58=0,"",1-(E58/D58)) | G58: =SUMIFS('FW26 Styles'!O5:O574,'FW26 Styles'!A5:A574,A58,'FW26 Styles'!B5:B574,B58,'FW26 Styles'!C5:C574,C58) -> 0 | H58: =SUMIFS('Last Season Data'!N5:N561,'Last Season Data'!B5:B561,A58,'Last Season Data'!C5:C561,B58,'Last Season Data'!D5:D561,C58) -> 128725.15 | I58: =SUMIFS('Last Season Data'!M5:M561,'Last Season Data'!B5:B561,A58,'Last Season Data'!C5:C561,B58,'Last Season Data'!D5:D561,C58) -> 1452 | J58: =D58-H58 -> -128725.15 | K58: =IF(H58=0,"",(D58-H58)/H58) -> -1 | L58: =G58-I58 -> -1452
A59: Clothing | B59: Dresses | C59: New 1 | D59: =SUMIFS('FW26 Styles'!Q5:Q574,'FW26 Styles'!A5:A574,A59,'FW26 Styles'!B5:B574,B59,'FW26 Styles'!C5:C574,C59) -> 0 | E59: =SUMIFS('FW26 Styles'!P5:P574,'FW26 Styles'!A5:A574,A59,'FW26 Styles'!B5:B574,B59,'FW26 Styles'!C5:C574,C59) -> 0 | F59: =IF(D59=0,"",1-(E59/D59)) | G59: =SUMIFS('FW26 Styles'!O5:O574,'FW26 Styles'!A5:A574,A59,'FW26 Styles'!B5:B574,B59,'FW26 Styles'!C5:C574,C59) -> 0 | H59: =SUMIFS('Last Season Data'!N5:N561,'Last Season Data'!B5:B561,A59,'Last Season Data'!C5:C561,B59,'Last Season Data'!D5:D561,C59) -> 0 | I59: =SUMIFS('Last Season Data'!M5:M561,'Last Season Data'!B5:B561,A59,'Last Season Data'!C5:C561,B59,'Last Season Data'!D5:D561,C59) -> 0 | J59: =D59-H59 -> 0 | K59: =IF(H59=0,"",(D59-H59)/H59) | L59: =G59-I59 -> 0
A60: Clothing | B60: Dresses | C60: New 2 | D60: =SUMIFS('FW26 Styles'!Q5:Q574,'FW26 Styles'!A5:A574,A60,'FW26 Styles'!B5:B574,B60,'FW26 Styles'!C5:C574,C60) -> 0 | E60: =SUMIFS('FW26 Styles'!P5:P574,'FW26 Styles'!A5:A574,A60,'FW26 Styles'!B5:B574,B60,'FW26 Styles'!C5:C574,C60) -> 0 | F60: =IF(D60=0,"",1-(E60/D60)) | G60: =SUMIFS('FW26 Styles'!O5:O574,'FW26 Styles'!A5:A574,A60,'FW26 Styles'!B5:B574,B60,'FW26 Styles'!C5:C574,C60) -> 0 | H60: =SUMIFS('Last Season Data'!N5:N561,'Last Season Data'!B5:B561,A60,'Last Season Data'!C5:C561,B60,'Last Season Data'!D5:D561,C60) -> 0 | I60: =SUMIFS('Last Season Data'!M5:M561,'Last Season Data'!B5:B561,A60,'Last Season Data'!C5:C561,B60,'Last Season Data'!D5:D561,C60) -> 0 | J60: =D60-H60 -> 0 | K60: =IF(H60=0,"",(D60-H60)/H60) | L60: =G60-I60 -> 0
A61: Clothing | B61: Dresses | C61: New 3 | D61: =SUMIFS('FW26 Styles'!Q5:Q574,'FW26 Styles'!A5:A574,A61,'FW26 Styles'!B5:B574,B61,'FW26 Styles'!C5:C574,C61) -> 0 | E61: =SUMIFS('FW26 Styles'!P5:P574,'FW26 Styles'!A5:A574,A61,'FW26 Styles'!B5:B574,B61,'FW26 Styles'!C5:C574,C61) -> 0 | F61: =IF(D61=0,"",1-(E61/D61)) | G61: =SUMIFS('FW26 Styles'!O5:O574,'FW26 Styles'!A5:A574,A61,'FW26 Styles'!B5:B574,B61,'FW26 Styles'!C5:C574,C61) -> 0 | H61: =SUMIFS('Last Season Data'!N5:N561,'Last Season Data'!B5:B561,A61,'Last Season Data'!C5:C561,B61,'Last Season Data'!D5:D561,C61) -> 0 | I61: =SUMIFS('Last Season Data'!M5:M561,'Last Season Data'!B5:B561,A61,'Last Season Data'!C5:C561,B61,'Last Season Data'!D5:D561,C61) -> 0 | J61: =D61-H61 -> 0 | K61: =IF(H61=0,"",(D61-H61)/H61) | L61: =G61-I61 -> 0
B62: Dresses Subtotal | D62: =SUM(D56:D61) -> 0 | E62: =SUM(E56:E61) -> 0 | F62: =IF(D62=0,"",1-(E62/D62)) | G62: =SUM(G56:G61) -> 0 | H62: =SUM(H56:H61) -> 512221.63 | I62: =SUM(I56:I61) -> 5130 | J62: =SUM(J56:J61) -> -512221.63 | K62: =IF(H62=0,"",(D62-H62)/H62) -> -1 | L62: =SUM(L56:L61) -> -5130
A63: Clothing | B63: Tops | C63: Sweater | D63: =SUMIFS('FW26 Styles'!Q5:Q574,'FW26 Styles'!A5:A574,A63,'FW26 Styles'!B5:B574,B63,'FW26 Styles'!C5:C574,C63) -> 0 | E63: =SUMIFS('FW26 Styles'!P5:P574,'FW26 Styles'!A5:A574,A63,'FW26 Styles'!B5:B574,B63,'FW26 Styles'!C5:C574,C63) -> 0 | F63: =IF(D63=0,"",1-(E63/D63)) | G63: =SUMIFS('FW26 Styles'!O5:O574,'FW26 Styles'!A5:A574,A63,'FW26 Styles'!B5:B574,B63,'FW26 Styles'!C5:C574,C63) -> 0 | H63: =SUMIFS('Last Season Data'!N5:N561,'Last Season Data'!B5:B561,A63,'Last Season Data'!C5:C561,B63,'Last Season Data'!D5:D561,C63) -> 217169.61 | I63: =SUMIFS('Last Season Data'!M5:M561,'Last Season Data'!B5:B561,A63,'Last Season Data'!C5:C561,B63,'Last Season Data'!D5:D561,C63) -> 2606 | J63: =D63-H63 -> -217169.61 | K63: =IF(H63=0,"",(D63-H63)/H63) -> -1 | L63: =G63-I63 -> -2606
A64: Clothing | B64: Tops | C64: LS Top | D64: =SUMIFS('FW26 Styles'!Q5:Q574,'FW26 Styles'!A5:A574,A64,'FW26 Styles'!B5:B574,B64,'FW26 Styles'!C5:C574,C64) -> 0 | E64: =SUMIFS('FW26 Styles'!P5:P574,'FW26 Styles'!A5:A574,A64,'FW26 Styles'!B5:B574,B64,'FW26 Styles'!C5:C574,C64) -> 0 | F64: =IF(D64=0,"",1-(E64/D64)) | G64: =SUMIFS('FW26 Styles'!O5:O574,'FW26 Styles'!A5:A574,A64,'FW26 Styles'!B5:B574,B64,'FW26 Styles'!C5:C574,C64) -> 0 | H64: =SUMIFS('Last Season Data'!N5:N561,'Last Season Data'!B5:B561,A64,'Last Season Data'!C5:C561,B64,'Last Season Data'!D5:D561,C64) -> 123510.22 | I64: =SUMIFS('Last Season Data'!M5:M561,'Last Season Data'!B5:B561,A64,'Last Season Data'!C5:C561,B64,'Last Season Data'!D5:D561,C64) -> 2116 | J64: =D64-H64 -> -123510.22 | K64: =IF(H64=0,"",(D64-H64)/H64) -> -1 | L64: =G64-I64 -> -2116
A65: Clothing | B65: Tops | C65: Shirt | D65: =SUMIFS('FW26 Styles'!Q5:Q574,'FW26 Styles'!A5:A574,A65,'FW26 Styles'!B5:B574,B65,'FW26 Styles'!C5:C574,C65) -> 0 | E65: =SUMIFS('FW26 Styles'!P5:P574,'FW26 Styles'!A5:A574,A65,'FW26 Styles'!B5:B574,B65,'FW26 Styles'!C5:C574,C65) -> 0 | F65: =IF(D65=0,"",1-(E65/D65)) | G65: =SUMIFS('FW26 Styles'!O5:O574,'FW26 Styles'!A5:A574,A65,'FW26 Styles'!B5:B574,B65,'FW26 Styles'!C5:C574,C65) -> 0 | H65: =SUMIFS('Last Season Data'!N5:N561,'Last Season Data'!B5:B561,A65,'Last Season Data'!C5:C561,B65,'Last Season Data'!D5:D561,C65) -> 39192.49 | I65: =SUMIFS('Last Season Data'!M5:M561,'Last Season Data'!B5:B561,A65,'Last Season Data'!C5:C561,B65,'Last Season Data'!D5:D561,C65) -> 473 | J65: =D65-H65 -> -39192.49 | K65: =IF(H65=0,"",(D65-H65)/H65) -> -1 | L65: =G65-I65 -> -473
A66: Clothing | B66: Tops | C66: Cardigan | D66: =SUMIFS('FW26 Styles'!Q5:Q574,'FW26 Styles'!A5:A574,A66,'FW26 Styles'!B5:B574,B66,'FW26 Styles'!C5:C574,C66) -> 0 | E66: =SUMIFS('FW26 Styles'!P5:P574,'FW26 Styles'!A5:A574,A66,'FW26 Styles'!B5:B574,B66,'FW26 Styles'!C5:C574,C66) -> 0 | F66: =IF(D66=0,"",1-(E66/D66)) | G66: =SUMIFS('FW26 Styles'!O5:O574,'FW26 Styles'!A5:A574,A66,'FW26 Styles'!B5:B574,B66,'FW26 Styles'!C5:C574,C66) -> 0 | H66: =SUMIFS('Last Season Data'!N5:N561,'Last Season Data'!B5:B561,A66,'Last Season Data'!C5:C561,B66,'Last Season Data'!D5:D561,C66) -> 48982.45 | I66: =SUMIFS('Last Season Data'!M5:M561,'Last Season Data'!B5:B561,A66,'Last Season Data'!C5:C561,B66,'Last Season Data'!D5:D561,C66) -> 552 | J66: =D66-H66 -> -48982.45 | K66: =IF(H66=0,"",(D66-H66)/H66) -> -1 | L66: =G66-I66 -> -552
A67: Clothing | B67: Tops | C67: New 1 | D67: =SUMIFS('FW26 Styles'!Q5:Q574,'FW26 Styles'!A5:A574,A67,'FW26 Styles'!B5:B574,B67,'FW26 Styles'!C5:C574,C67) -> 0 | E67: =SUMIFS('FW26 Styles'!P5:P574,'FW26 Styles'!A5:A574,A67,'FW26 Styles'!B5:B574,B67,'FW26 Styles'!C5:C574,C67) -> 0 | F67: =IF(D67=0,"",1-(E67/D67)) | G67: =SUMIFS('FW26 Styles'!O5:O574,'FW26 Styles'!A5:A574,A67,'FW26 Styles'!B5:B574,B67,'FW26 Styles'!C5:C574,C67) -> 0 | H67: =SUMIFS('Last Season Data'!N5:N561,'Last Season Data'!B5:B561,A67,'Last Season Data'!C5:C561,B67,'Last Season Data'!D5:D561,C67) -> 0 | I67: =SUMIFS('Last Season Data'!M5:M561,'Last Season Data'!B5:B561,A67,'Last Season Data'!C5:C561,B67,'Last Season Data'!D5:D561,C67) -> 0 | J67: =D67-H67 -> 0 | K67: =IF(H67=0,"",(D67-H67)/H67) | L67: =G67-I67 -> 0
A68: Clothing | B68: Tops | C68: New 2 | D68: =SUMIFS('FW26 Styles'!Q5:Q574,'FW26 Styles'!A5:A574,A68,'FW26 Styles'!B5:B574,B68,'FW26 Styles'!C5:C574,C68) -> 0 | E68: =SUMIFS('FW26 Styles'!P5:P574,'FW26 Styles'!A5:A574,A68,'FW26 Styles'!B5:B574,B68,'FW26 Styles'!C5:C574,C68) -> 0 | F68: =IF(D68=0,"",1-(E68/D68)) | G68: =SUMIFS('FW26 Styles'!O5:O574,'FW26 Styles'!A5:A574,A68,'FW26 Styles'!B5:B574,B68,'FW26 Styles'!C5:C574,C68) -> 0 | H68: =SUMIFS('Last Season Data'!N5:N561,'Last Season Data'!B5:B561,A68,'Last Season Data'!C5:C561,B68,'Last Season Data'!D5:D561,C68) -> 0 | I68: =SUMIFS('Last Season Data'!M5:M561,'Last Season Data'!B5:B561,A68,'Last Season Data'!C5:C561,B68,'Last Season Data'!D5:D561,C68) -> 0 | J68: =D68-H68 -> 0 | K68: =IF(H68=0,"",(D68-H68)/H68) | L68: =G68-I68 -> 0
A69: Clothing | B69: Tops | C69: New 3 | D69: =SUMIFS('FW26 Styles'!Q5:Q574,'FW26 Styles'!A5:A574,A69,'FW26 Styles'!B5:B574,B69,'FW26 Styles'!C5:C574,C69) -> 0 | E69: =SUMIFS('FW26 Styles'!P5:P574,'FW26 Styles'!A5:A574,A69,'FW26 Styles'!B5:B574,B69,'FW26 Styles'!C5:C574,C69) -> 0 | F69: =IF(D69=0,"",1-(E69/D69)) | G69: =SUMIFS('FW26 Styles'!O5:O574,'FW26 Styles'!A5:A574,A69,'FW26 Styles'!B5:B574,B69,'FW26 Styles'!C5:C574,C69) -> 0 | H69: =SUMIFS('Last Season Data'!N5:N561,'Last Season Data'!B5:B561,A69,'Last Season Data'!C5:C561,B69,'Last Season Data'!D5:D561,C69) -> 0 | I69: =SUMIFS('Last Season Data'!M5:M561,'Last Season Data'!B5:B561,A69,'Last Season Data'!C5:C561,B69,'Last Season Data'!D5:D561,C69) -> 0 | J69: =D69-H69 -> 0 | K69: =IF(H69=0,"",(D69-H69)/H69) | L69: =G69-I69 -> 0
A70: Clothing | B70: Tops | C70: New 4 | D70: =SUMIFS('FW26 Styles'!Q5:Q574,'FW26 Styles'!A5:A574,A70,'FW26 Styles'!B5:B574,B70,'FW26 Styles'!C5:C574,C70) -> 0 | E70: =SUMIFS('FW26 Styles'!P5:P574,'FW26 Styles'!A5:A574,A70,'FW26 Styles'!B5:B574,B70,'FW26 Styles'!C5:C574,C70) -> 0 | F70: =IF(D70=0,"",1-(E70/D70)) | G70: =SUMIFS('FW26 Styles'!O5:O574,'FW26 Styles'!A5:A574,A70,'FW26 Styles'!B5:B574,B70,'FW26 Styles'!C5:C574,C70) -> 0 | H70: =SUMIFS('Last Season Data'!N5:N561,'Last Season Data'!B5:B561,A70,'Last Season Data'!C5:C561,B70,'Last Season Data'!D5:D561,C70) -> 0 | I70: =SUMIFS('Last Season Data'!M5:M561,'Last Season Data'!B5:B561,A70,'Last Season Data'!C5:C561,B70,'Last Season Data'!D5:D561,C70) -> 0 | J70: =D70-H70 -> 0 | K70: =IF(H70=0,"",(D70-H70)/H70) | L70: =G70-I70 -> 0
A71: Clothing | B71: Tops | C71: New 5 | D71: =SUMIFS('FW26 Styles'!Q5:Q574,'FW26 Styles'!A5:A574,A71,'FW26 Styles'!B5:B574,B71,'FW26 Styles'!C5:C574,C71) -> 0 | E71: =SUMIFS('FW26 Styles'!P5:P574,'FW26 Styles'!A5:A574,A71,'FW26 Styles'!B5:B574,B71,'FW26 Styles'!C5:C574,C71) -> 0 | F71: =IF(D71=0,"",1-(E71/D71)) | G71: =SUMIFS('FW26 Styles'!O5:O574,'FW26 Styles'!A5:A574,A71,'FW26 Styles'!B5:B574,B71,'FW26 Styles'!C5:C574,C71) -> 0 | H71: =SUMIFS('Last Season Data'!N5:N561,'Last Season Data'!B5:B561,A71,'Last Season Data'!C5:C561,B71,'Last Season Data'!D5:D561,C71) -> 0 | I71: =SUMIFS('Last Season Data'!M5:M561,'Last Season Data'!B5:B561,A71,'Last Season Data'!C5:C561,B71,'Last Season Data'!D5:D561,C71) -> 0 | J71: =D71-H71 -> 0 | K71: =IF(H71=0,"",(D71-H71)/H71) | L71: =G71-I71 -> 0
A72: Clothing | B72: Tops | C72: New 6 | D72: =SUMIFS('FW26 Styles'!Q5:Q574,'FW26 Styles'!A5:A574,A72,'FW26 Styles'!B5:B574,B72,'FW26 Styles'!C5:C574,C72) -> 0 | E72: =SUMIFS('FW26 Styles'!P5:P574,'FW26 Styles'!A5:A574,A72,'FW26 Styles'!B5:B574,B72,'FW26 Styles'!C5:C574,C72) -> 0 | F72: =IF(D72=0,"",1-(E72/D72)) | G72: =SUMIFS('FW26 Styles'!O5:O574,'FW26 Styles'!A5:A574,A72,'FW26 Styles'!B5:B574,B72,'FW26 Styles'!C5:C574,C72) -> 0 | H72: =SUMIFS('Last Season Data'!N5:N561,'Last Season Data'!B5:B561,A72,'Last Season Data'!C5:C561,B72,'Last Season Data'!D5:D561,C72) -> 0 | I72: =SUMIFS('Last Season Data'!M5:M561,'Last Season Data'!B5:B561,A72,'Last Season Data'!C5:C561,B72,'Last Season Data'!D5:D561,C72) -> 0 | J72: =D72-H72 -> 0 | K72: =IF(H72=0,"",(D72-H72)/H72) | L72: =G72-I72 -> 0
B73: Tops Subtotal | D73: =SUM(D63:D72) -> 0 | E73: =SUM(E63:E72) -> 0 | F73: =IF(D73=0,"",1-(E73/D73)) | G73: =SUM(G63:G72) -> 0 | H73: =SUM(H63:H72) -> 428854.77 | I73: =SUM(I63:I72) -> 5747 | J73: =SUM(J63:J72) -> -428854.77 | K73: =IF(H73=0,"",(D73-H73)/H73) -> -1 | L73: =SUM(L63:L72) -> -5747
A74: Clothing | B74: Bottoms | C74: Pants | D74: =SUMIFS('FW26 Styles'!Q5:Q574,'FW26 Styles'!A5:A574,A74,'FW26 Styles'!B5:B574,B74,'FW26 Styles'!C5:C574,C74) -> 0 | E74: =SUMIFS('FW26 Styles'!P5:P574,'FW26 Styles'!A5:A574,A74,'FW26 Styles'!B5:B574,B74,'FW26 Styles'!C5:C574,C74) -> 0 | F74: =IF(D74=0,"",1-(E74/D74)) | G74: =SUMIFS('FW26 Styles'!O5:O574,'FW26 Styles'!A5:A574,A74,'FW26 Styles'!B5:B574,B74,'FW26 Styles'!C5:C574,C74) -> 0 | H74: =SUMIFS('Last Season Data'!N5:N561,'Last Season Data'!B5:B561,A74,'Last Season Data'!C5:C561,B74,'Last Season Data'!D5:D561,C74) -> 209084.69 | I74: =SUMIFS('Last Season Data'!M5:M561,'Last Season Data'!B5:B561,A74,'Last Season Data'!C5:C561,B74,'Last Season Data'!D5:D561,C74) -> 2739 | J74: =D74-H74 -> -209084.69 | K74: =IF(H74=0,"",(D74-H74)/H74) -> -1 | L74: =G74-I74 -> -2739
A75: Clothing | B75: Bottoms | C75: Skirts | D75: =SUMIFS('FW26 Styles'!Q5:Q574,'FW26 Styles'!A5:A574,A75,'FW26 Styles'!B5:B574,B75,'FW26 Styles'!C5:C574,C75) -> 0 | E75: =SUMIFS('FW26 Styles'!P5:P574,'FW26 Styles'!A5:A574,A75,'FW26 Styles'!B5:B574,B75,'FW26 Styles'!C5:C574,C75) -> 0 | F75: =IF(D75=0,"",1-(E75/D75)) | G75: =SUMIFS('FW26 Styles'!O5:O574,'FW26 Styles'!A5:A574,A75,'FW26 Styles'!B5:B574,B75,'FW26 Styles'!C5:C574,C75) -> 0 | H75: =SUMIFS('Last Season Data'!N5:N561,'Last Season Data'!B5:B561,A75,'Last Season Data'!C5:C561,B75,'Last Season Data'!D5:D561,C75) -> 84427.79 | I75: =SUMIFS('Last Season Data'!M5:M561,'Last Season Data'!B5:B561,A75,'Last Season Data'!C5:C561,B75,'Last Season Data'!D5:D561,C75) -> 1042 | J75: =D75-H75 -> -84427.79 | K75: =IF(H75=0,"",(D75-H75)/H75) -> -1 | L75: =G75-I75 -> -1042
A76: Clothing | B76: Bottoms | C76: Legging | D76: =SUMIFS('FW26 Styles'!Q5:Q574,'FW26 Styles'!A5:A574,A76,'FW26 Styles'!B5:B574,B76,'FW26 Styles'!C5:C574,C76) -> 0 | E76: =SUMIFS('FW26 Styles'!P5:P574,'FW26 Styles'!A5:A574,A76,'FW26 Styles'!B5:B574,B76,'FW26 Styles'!C5:C574,C76) -> 0 | F76: =IF(D76=0,"",1-(E76/D76)) | G76: =SUMIFS('FW26 Styles'!O5:O574,'FW26 Styles'!A5:A574,A76,'FW26 Styles'!B5:B574,B76,'FW26 Styles'!C5:C574,C76) -> 0 | H76: =SUMIFS('Last Season Data'!N5:N561,'Last Season Data'!B5:B561,A76,'Last Season Data'!C5:C561,B76,'Last Season Data'!D5:D561,C76) -> 0 | I76: =SUMIFS('Last Season Data'!M5:M561,'Last Season Data'!B5:B561,A76,'Last Season Data'!C5:C561,B76,'Last Season Data'!D5:D561,C76) -> 0 | J76: =D76-H76 -> 0 | K76: =IF(H76=0,"",(D76-H76)/H76) | L76: =G76-I76 -> 0
A77: Clothing | B77: Bottoms | C77: New 1 | D77: =SUMIFS('FW26 Styles'!Q5:Q574,'FW26 Styles'!A5:A574,A77,'FW26 Styles'!B5:B574,B77,'FW26 Styles'!C5:C574,C77) -> 0 | E77: =SUMIFS('FW26 Styles'!P5:P574,'FW26 Styles'!A5:A574,A77,'FW26 Styles'!B5:B574,B77,'FW26 Styles'!C5:C574,C77) -> 0 | F77: =IF(D77=0,"",1-(E77/D77)) | G77: =SUMIFS('FW26 Styles'!O5:O574,'FW26 Styles'!A5:A574,A77,'FW26 Styles'!B5:B574,B77,'FW26 Styles'!C5:C574,C77) -> 0 | H77: =SUMIFS('Last Season Data'!N5:N561,'Last Season Data'!B5:B561,A77,'Last Season Data'!C5:C561,B77,'Last Season Data'!D5:D561,C77) -> 0 | I77: =SUMIFS('Last Season Data'!M5:M561,'Last Season Data'!B5:B561,A77,'Last Season Data'!C5:C561,B77,'Last Season Data'!D5:D561,C77) -> 0 | J77: =D77-H77 -> 0 | K77: =IF(H77=0,"",(D77-H77)/H77) | L77: =G77-I77 -> 0
A78: Clothing | B78: Bottoms | C78: New 2 | D78: =SUMIFS('FW26 Styles'!Q5:Q574,'FW26 Styles'!A5:A574,A78,'FW26 Styles'!B5:B574,B78,'FW26 Styles'!C5:C574,C78) -> 0 | E78: =SUMIFS('FW26 Styles'!P5:P574,'FW26 Styles'!A5:A574,A78,'FW26 Styles'!B5:B574,B78,'FW26 Styles'!C5:C574,C78) -> 0 | F78: =IF(D78=0,"",1-(E78/D78)) | G78: =SUMIFS('FW26 Styles'!O5:O574,'FW26 Styles'!A5:A574,A78,'FW26 Styles'!B5:B574,B78,'FW26 Styles'!C5:C574,C78) -> 0 | H78: =SUMIFS('Last Season Data'!N5:N561,'Last Season Data'!B5:B561,A78,'Last Season Data'!C5:C561,B78,'Last Season Data'!D5:D561,C78) -> 0 | I78: =SUMIFS('Last Season Data'!M5:M561,'Last Season Data'!B5:B561,A78,'Last Season Data'!C5:C561,B78,'Last Season Data'!D5:D561,C78) -> 0 | J78: =D78-H78 -> 0 | K78: =IF(H78=0,"",(D78-H78)/H78) | L78: =G78-I78 -> 0
A79: Clothing | B79: Bottoms | C79: New 3 | D79: =SUMIFS('FW26 Styles'!Q5:Q574,'FW26 Styles'!A5:A574,A79,'FW26 Styles'!B5:B574,B79,'FW26 Styles'!C5:C574,C79) -> 0 | E79: =SUMIFS('FW26 Styles'!P5:P574,'FW26 Styles'!A5:A574,A79,'FW26 Styles'!B5:B574,B79,'FW26 Styles'!C5:C574,C79) -> 0 | F79: =IF(D79=0,"",1-(E79/D79)) | G79: =SUMIFS('FW26 Styles'!O5:O574,'FW26 Styles'!A5:A574,A79,'FW26 Styles'!B5:B574,B79,'FW26 Styles'!C5:C574,C79) -> 0 | H79: =SUMIFS('Last Season Data'!N5:N561,'Last Season Data'!B5:B561,A79,'Last Season Data'!C5:C561,B79,'Last Season Data'!D5:D561,C79) -> 0 | I79: =SUMIFS('Last Season Data'!M5:M561,'Last Season Data'!B5:B561,A79,'Last Season Data'!C5:C561,B79,'Last Season Data'!D5:D561,C79) -> 0 | J79: =D79-H79 -> 0 | K79: =IF(H79=0,"",(D79-H79)/H79) | L79: =G79-I79 -> 0
B80: Bottoms Subtotal | D80: =SUM(D74:D79) -> 0 | E80: =SUM(E74:E79) -> 0 | F80: =IF(D80=0,"",1-(E80/D80)) | G80: =SUM(G74:G79) -> 0 | H80: =SUM(H74:H79) -> 293512.48 | I80: =SUM(I74:I79) -> 3781 | J80: =SUM(J74:J79) -> -293512.48 | K80: =IF(H80=0,"",(D80-H80)/H80) -> -1 | L80: =SUM(L74:L79) -> -3781
A81: Clothing | B81: Outerwear | C81: Abaya | D81: =SUMIFS('FW26 Styles'!Q5:Q574,'FW26 Styles'!A5:A574,A81,'FW26 Styles'!B5:B574,B81,'FW26 Styles'!C5:C574,C81) -> 0 | E81: =SUMIFS('FW26 Styles'!P5:P574,'FW26 Styles'!A5:A574,A81,'FW26 Styles'!B5:B574,B81,'FW26 Styles'!C5:C574,C81) -> 0 | F81: =IF(D81=0,"",1-(E81/D81)) | G81: =SUMIFS('FW26 Styles'!O5:O574,'FW26 Styles'!A5:A574,A81,'FW26 Styles'!B5:B574,B81,'FW26 Styles'!C5:C574,C81) -> 0 | H81: =SUMIFS('Last Season Data'!N5:N561,'Last Season Data'!B5:B561,A81,'Last Season Data'!C5:C561,B81,'Last Season Data'!D5:D561,C81) -> 80161.29 | I81: =SUMIFS('Last Season Data'!M5:M561,'Last Season Data'!B5:B561,A81,'Last Season Data'!C5:C561,B81,'Last Season Data'!D5:D561,C81) -> 618 | J81: =D81-H81 -> -80161.29 | K81: =IF(H81=0,"",(D81-H81)/H81) -> -1 | L81: =G81-I81 -> -618
A82: Clothing | B82: Outerwear | C82: Jacket | D82: =SUMIFS('FW26 Styles'!Q5:Q574,'FW26 Styles'!A5:A574,A82,'FW26 Styles'!B5:B574,B82,'FW26 Styles'!C5:C574,C82) -> 0 | E82: =SUMIFS('FW26 Styles'!P5:P574,'FW26 Styles'!A5:A574,A82,'FW26 Styles'!B5:B574,B82,'FW26 Styles'!C5:C574,C82) -> 0 | F82: =IF(D82=0,"",1-(E82/D82)) | G82: =SUMIFS('FW26 Styles'!O5:O574,'FW26 Styles'!A5:A574,A82,'FW26 Styles'!B5:B574,B82,'FW26 Styles'!C5:C574,C82) -> 0 | H82: =SUMIFS('Last Season Data'!N5:N561,'Last Season Data'!B5:B561,A82,'Last Season Data'!C5:C561,B82,'Last Season Data'!D5:D561,C82) -> 53526.62 | I82: =SUMIFS('Last Season Data'!M5:M561,'Last Season Data'!B5:B561,A82,'Last Season Data'!C5:C561,B82,'Last Season Data'!D5:D561,C82) -> 570 | J82: =D82-H82 -> -53526.62 | K82: =IF(H82=0,"",(D82-H82)/H82) -> -1 | L82: =G82-I82 -> -570
A83: Clothing | B83: Outerwear | C83: Coat | D83: =SUMIFS('FW26 Styles'!Q5:Q574,'FW26 Styles'!A5:A574,A83,'FW26 Styles'!B5:B574,B83,'FW26 Styles'!C5:C574,C83) -> 0 | E83: =SUMIFS('FW26 Styles'!P5:P574,'FW26 Styles'!A5:A574,A83,'FW26 Styles'!B5:B574,B83,'FW26 Styles'!C5:C574,C83) -> 0 | F83: =IF(D83=0,"",1-(E83/D83)) | G83: =SUMIFS('FW26 Styles'!O5:O574,'FW26 Styles'!A5:A574,A83,'FW26 Styles'!B5:B574,B83,'FW26 Styles'!C5:C574,C83) -> 0 | H83: =SUMIFS('Last Season Data'!N5:N561,'Last Season Data'!B5:B561,A83,'Last Season Data'!C5:C561,B83,'Last Season Data'!D5:D561,C83) -> 240936.79 | I83: =SUMIFS('Last Season Data'!M5:M561,'Last Season Data'!B5:B561,A83,'Last Season Data'!C5:C561,B83,'Last Season Data'!D5:D561,C83) -> 1742 | J83: =D83-H83 -> -240936.79 | K83: =IF(H83=0,"",(D83-H83)/H83) -> -1 | L83: =G83-I83 -> -1742
A84: Clothing | B84: Outerwear | C84: Bomber | D84: =SUMIFS('FW26 Styles'!Q5:Q574,'FW26 Styles'!A5:A574,A84,'FW26 Styles'!B5:B574,B84,'FW26 Styles'!C5:C574,C84) -> 0 | E84: =SUMIFS('FW26 Styles'!P5:P574,'FW26 Styles'!A5:A574,A84,'FW26 Styles'!B5:B574,B84,'FW26 Styles'!C5:C574,C84) -> 0 | F84: =IF(D84=0,"",1-(E84/D84)) | G84: =SUMIFS('FW26 Styles'!O5:O574,'FW26 Styles'!A5:A574,A84,'FW26 Styles'!B5:B574,B84,'FW26 Styles'!C5:C574,C84) -> 0 | H84: =SUMIFS('Last Season Data'!N5:N561,'Last Season Data'!B5:B561,A84,'Last Season Data'!C5:C561,B84,'Last Season Data'!D5:D561,C84) -> 184962.19 | I84: =SUMIFS('Last Season Data'!M5:M561,'Last Season Data'!B5:B561,A84,'Last Season Data'!C5:C561,B84,'Last Season Data'!D5:D561,C84) -> 1766 | J84: =D84-H84 -> -184962.19 | K84: =IF(H84=0,"",(D84-H84)/H84) -> -1 | L84: =G84-I84 -> -1766
A85: Clothing | B85: Outerwear | C85: Poncho | D85: =SUMIFS('FW26 Styles'!Q5:Q574,'FW26 Styles'!A5:A574,A85,'FW26 Styles'!B5:B574,B85,'FW26 Styles'!C5:C574,C85) -> 0 | E85: =SUMIFS('FW26 Styles'!P5:P574,'FW26 Styles'!A5:A574,A85,'FW26 Styles'!B5:B574,B85,'FW26 Styles'!C5:C574,C85) -> 0 | F85: =IF(D85=0,"",1-(E85/D85)) | G85: =SUMIFS('FW26 Styles'!O5:O574,'FW26 Styles'!A5:A574,A85,'FW26 Styles'!B5:B574,B85,'FW26 Styles'!C5:C574,C85) -> 0 | H85: =SUMIFS('Last Season Data'!N5:N561,'Last Season Data'!B5:B561,A85,'Last Season Data'!C5:C561,B85,'Last Season Data'!D5:D561,C85) -> 12356.86 | I85: =SUMIFS('Last Season Data'!M5:M561,'Last Season Data'!B5:B561,A85,'Last Season Data'!C5:C561,B85,'Last Season Data'!D5:D561,C85) -> 198 | J85: =D85-H85 -> -12356.86 | K85: =IF(H85=0,"",(D85-H85)/H85) -> -1 | L85: =G85-I85 -> -198
A86: Clothing | B86: Outerwear | C86: Cape | D86: =SUMIFS('FW26 Styles'!Q5:Q574,'FW26 Styles'!A5:A574,A86,'FW26 Styles'!B5:B574,B86,'FW26 Styles'!C5:C574,C86) -> 0 | E86: =SUMIFS('FW26 Styles'!P5:P574,'FW26 Styles'!A5:A574,A86,'FW26 Styles'!B5:B574,B86,'FW26 Styles'!C5:C574,C86) -> 0 | F86: =IF(D86=0,"",1-(E86/D86)) | G86: =SUMIFS('FW26 Styles'!O5:O574,'FW26 Styles'!A5:A574,A86,'FW26 Styles'!B5:B574,B86,'FW26 Styles'!C5:C574,C86) -> 0 | H86: =SUMIFS('Last Season Data'!N5:N561,'Last Season Data'!B5:B561,A86,'Last Season Data'!C5:C561,B86,'Last Season Data'!D5:D561,C86) -> 19464.95 | I86: =SUMIFS('Last Season Data'!M5:M561,'Last Season Data'!B5:B561,A86,'Last Season Data'!C5:C561,B86,'Last Season Data'!D5:D561,C86) -> 507 | J86: =D86-H86 -> -19464.95 | K86: =IF(H86=0,"",(D86-H86)/H86) -> -1 | L86: =G86-I86 -> -507
A87: Clothing | B87: Outerwear | C87: Blazer | D87: =SUMIFS('FW26 Styles'!Q5:Q574,'FW26 Styles'!A5:A574,A87,'FW26 Styles'!B5:B574,B87,'FW26 Styles'!C5:C574,C87) -> 0 | E87: =SUMIFS('FW26 Styles'!P5:P574,'FW26 Styles'!A5:A574,A87,'FW26 Styles'!B5:B574,B87,'FW26 Styles'!C5:C574,C87) -> 0 | F87: =IF(D87=0,"",1-(E87/D87)) | G87: =SUMIFS('FW26 Styles'!O5:O574,'FW26 Styles'!A5:A574,A87,'FW26 Styles'!B5:B574,B87,'FW26 Styles'!C5:C574,C87) -> 0 | H87: =SUMIFS('Last Season Data'!N5:N561,'Last Season Data'!B5:B561,A87,'Last Season Data'!C5:C561,B87,'Last Season Data'!D5:D561,C87) -> 77868.15 | I87: =SUMIFS('Last Season Data'!M5:M561,'Last Season Data'!B5:B561,A87,'Last Season Data'!C5:C561,B87,'Last Season Data'!D5:D561,C87) -> 717 | J87: =D87-H87 -> -77868.15 | K87: =IF(H87=0,"",(D87-H87)/H87) -> -1 | L87: =G87-I87 -> -717
A88: Clothing | B88: Outerwear | C88: New 1 | D88: =SUMIFS('FW26 Styles'!Q5:Q574,'FW26 Styles'!A5:A574,A88,'FW26 Styles'!B5:B574,B88,'FW26 Styles'!C5:C574,C88) -> 0 | E88: =SUMIFS('FW26 Styles'!P5:P574,'FW26 Styles'!A5:A574,A88,'FW26 Styles'!B5:B574,B88,'FW26 Styles'!C5:C574,C88) -> 0 | F88: =IF(D88=0,"",1-(E88/D88)) | G88: =SUMIFS('FW26 Styles'!O5:O574,'FW26 Styles'!A5:A574,A88,'FW26 Styles'!B5:B574,B88,'FW26 Styles'!C5:C574,C88) -> 0 | H88: =SUMIFS('Last Season Data'!N5:N561,'Last Season Data'!B5:B561,A88,'Last Season Data'!C5:C561,B88,'Last Season Data'!D5:D561,C88) -> 0 | I88: =SUMIFS('Last Season Data'!M5:M561,'Last Season Data'!B5:B561,A88,'Last Season Data'!C5:C561,B88,'Last Season Data'!D5:D561,C88) -> 0 | J88: =D88-H88 -> 0 | K88: =IF(H88=0,"",(D88-H88)/H88) | L88: =G88-I88 -> 0
B89: Outerwear Subtotal | D89: =SUM(D81:D88) -> 0 | E89: =SUM(E81:E88) -> 0 | F89: =IF(D89=0,"",1-(E89/D89)) | G89: =SUM(G81:G88) -> 0 | H89: =SUM(H81:H88) -> 669276.85 | I89: =SUM(I81:I88) -> 6118 | J89: =SUM(J81:J88) -> -669276.85 | K89: =IF(H89=0,"",(D89-H89)/H89) -> -1 | L89: =SUM(L81:L88) -> -6118
A90: Clothing TOTAL | D90: =SUMIFS(D32:D89,A32:A89,"Clothing") -> 0 | E90: =SUMIFS(E32:E89,A32:A89,"Clothing") -> 0 | F90: =IF(D90=0,"",1-(E90/D90)) | G90: =SUMIFS(G32:G89,A32:A89,"Clothing") -> 0 | H90: =SUMIFS(H32:H89,A32:A89,"Clothing") -> 1903865.7 | I90: =SUMIFS(I32:I89,A32:A89,"Clothing") -> 20776 | J90: =SUMIFS(J32:J89,A32:A89,"Clothing") -> -1903865.7 | K90: =IF(H90=0,"",(D90-H90)/H90) -> -1 | L90: =SUMIFS(L32:L89,A32:A89,"Clothing") -> -20776
A91: Accessories | B91: Accessories | C91: Tote Bags | D91: =SUMIFS('FW26 Styles'!Q5:Q574,'FW26 Styles'!A5:A574,A91,'FW26 Styles'!B5:B574,B91,'FW26 Styles'!C5:C574,C91) -> 0 | E91: =SUMIFS('FW26 Styles'!P5:P574,'FW26 Styles'!A5:A574,A91,'FW26 Styles'!B5:B574,B91,'FW26 Styles'!C5:C574,C91) -> 0 | F91: =IF(D91=0,"",1-(E91/D91)) | G91: =SUMIFS('FW26 Styles'!O5:O574,'FW26 Styles'!A5:A574,A91,'FW26 Styles'!B5:B574,B91,'FW26 Styles'!C5:C574,C91) -> 0 | H91: =SUMIFS('Last Season Data'!N5:N561,'Last Season Data'!B5:B561,A91,'Last Season Data'!C5:C561,B91,'Last Season Data'!D5:D561,C91) -> 44310.47 | I91: =SUMIFS('Last Season Data'!M5:M561,'Last Season Data'!B5:B561,A91,'Last Season Data'!C5:C561,B91,'Last Season Data'!D5:D561,C91) -> 1409 | J91: =D91-H91 -> -44310.47 | K91: =IF(H91=0,"",(D91-H91)/H91) -> -1 | L91: =G91-I91 -> -1409
A92: Accessories | B92: Accessories | C92: Bags | D92: =SUMIFS('FW26 Styles'!Q5:Q574,'FW26 Styles'!A5:A574,A92,'FW26 Styles'!B5:B574,B92,'FW26 Styles'!C5:C574,C92) -> 0 | E92: =SUMIFS('FW26 Styles'!P5:P574,'FW26 Styles'!A5:A574,A92,'FW26 Styles'!B5:B574,B92,'FW26 Styles'!C5:C574,C92) -> 0 | F92: =IF(D92=0,"",1-(E92/D92)) | G92: =SUMIFS('FW26 Styles'!O5:O574,'FW26 Styles'!A5:A574,A92,'FW26 Styles'!B5:B574,B92,'FW26 Styles'!C5:C574,C92) -> 0 | H92: =SUMIFS('Last Season Data'!N5:N561,'Last Season Data'!B5:B561,A92,'Last Season Data'!C5:C561,B92,'Last Season Data'!D5:D561,C92) -> 17724.92 | I92: =SUMIFS('Last Season Data'!M5:M561,'Last Season Data'!B5:B561,A92,'Last Season Data'!C5:C561,B92,'Last Season Data'!D5:D561,C92) -> 264 | J92: =D92-H92 -> -17724.92 | K92: =IF(H92=0,"",(D92-H92)/H92) -> -1 | L92: =G92-I92 -> -264
A93: Accessories | B93: Accessories | C93: Scarf | D93: =SUMIFS('FW26 Styles'!Q5:Q574,'FW26 Styles'!A5:A574,A93,'FW26 Styles'!B5:B574,B93,'FW26 Styles'!C5:C574,C93) -> 0 | E93: =SUMIFS('FW26 Styles'!P5:P574,'FW26 Styles'!A5:A574,A93,'FW26 Styles'!B5:B574,B93,'FW26 Styles'!C5:C574,C93) -> 0 | F93: =IF(D93=0,"",1-(E93/D93)) | G93: =SUMIFS('FW26 Styles'!O5:O574,'FW26 Styles'!A5:A574,A93,'FW26 Styles'!B5:B574,B93,'FW26 Styles'!C5:C574,C93) -> 0 | H93: =SUMIFS('Last Season Data'!N5:N561,'Last Season Data'!B5:B561,A93,'Last Season Data'!C5:C561,B93,'Last Season Data'!D5:D561,C93) -> 39389.62 | I93: =SUMIFS('Last Season Data'!M5:M561,'Last Season Data'!B5:B561,A93,'Last Season Data'!C5:C561,B93,'Last Season Data'!D5:D561,C93) -> 691 | J93: =D93-H93 -> -39389.62 | K93: =IF(H93=0,"",(D93-H93)/H93) -> -1 | L93: =G93-I93 -> -691
A94: Accessories | B94: Accessories | C94: Gloves | D94: =SUMIFS('FW26 Styles'!Q5:Q574,'FW26 Styles'!A5:A574,A94,'FW26 Styles'!B5:B574,B94,'FW26 Styles'!C5:C574,C94) -> 0 | E94: =SUMIFS('FW26 Styles'!P5:P574,'FW26 Styles'!A5:A574,A94,'FW26 Styles'!B5:B574,B94,'FW26 Styles'!C5:C574,C94) -> 0 | F94: =IF(D94=0,"",1-(E94/D94)) | G94: =SUMIFS('FW26 Styles'!O5:O574,'FW26 Styles'!A5:A574,A94,'FW26 Styles'!B5:B574,B94,'FW26 Styles'!C5:C574,C94) -> 0 | H94: =SUMIFS('Last Season Data'!N5:N561,'Last Season Data'!B5:B561,A94,'Last Season Data'!C5:C561,B94,'Last Season Data'!D5:D561,C94) -> 6318 | I94: =SUMIFS('Last Season Data'!M5:M561,'Last Season Data'!B5:B561,A94,'Last Season Data'!C5:C561,B94,'Last Season Data'!D5:D561,C94) -> 167 | J94: =D94-H94 -> -6318 | K94: =IF(H94=0,"",(D94-H94)/H94) -> -1 | L94: =G94-I94 -> -167
A95: Accessories | B95: Accessories | C95: Balaclava | D95: =SUMIFS('FW26 Styles'!Q5:Q574,'FW26 Styles'!A5:A574,A95,'FW26 Styles'!B5:B574,B95,'FW26 Styles'!C5:C574,C95) -> 0 | E95: =SUMIFS('FW26 Styles'!P5:P574,'FW26 Styles'!A5:A574,A95,'FW26 Styles'!B5:B574,B95,'FW26 Styles'!C5:C574,C95) -> 0 | F95: =IF(D95=0,"",1-(E95/D95)) | G95: =SUMIFS('FW26 Styles'!O5:O574,'FW26 Styles'!A5:A574,A95,'FW26 Styles'!B5:B574,B95,'FW26 Styles'!C5:C574,C95) -> 0 | H95: =SUMIFS('Last Season Data'!N5:N561,'Last Season Data'!B5:B561,A95,'Last Season Data'!C5:C561,B95,'Last Season Data'!D5:D561,C95) -> 7984.41 | I95: =SUMIFS('Last Season Data'!M5:M561,'Last Season Data'!B5:B561,A95,'Last Season Data'!C5:C561,B95,'Last Season Data'!D5:D561,C95) -> 212 | J95: =D95-H95 -> -7984.41 | K95: =IF(H95=0,"",(D95-H95)/H95) -> -1 | L95: =G95-I95 -> -212
A96: Accessories | B96: Accessories | C96: Hijab Pins | D96: =SUMIFS('FW26 Styles'!Q5:Q574,'FW26 Styles'!A5:A574,A96,'FW26 Styles'!B5:B574,B96,'FW26 Styles'!C5:C574,C96) -> 0 | E96: =SUMIFS('FW26 Styles'!P5:P574,'FW26 Styles'!A5:A574,A96,'FW26 Styles'!B5:B574,B96,'FW26 Styles'!C5:C574,C96) -> 0 | F96: =IF(D96=0,"",1-(E96/D96)) | G96: =SUMIFS('FW26 Styles'!O5:O574,'FW26 Styles'!A5:A574,A96,'FW26 Styles'!B5:B574,B96,'FW26 Styles'!C5:C574,C96) -> 0 | H96: =SUMIFS('Last Season Data'!N5:N561,'Last Season Data'!B5:B561,A96,'Last Season Data'!C5:C561,B96,'Last Season Data'!D5:D561,C96) -> 6295.66 | I96: =SUMIFS('Last Season Data'!M5:M561,'Last Season Data'!B5:B561,A96,'Last Season Data'!C5:C561,B96,'Last Season Data'!D5:D561,C96) -> 345 | J96: =D96-H96 -> -6295.66 | K96: =IF(H96=0,"",(D96-H96)/H96) -> -1 | L96: =G96-I96 -> -345
A97: Accessories | B97: Accessories | C97: New | D97: =SUMIFS('FW26 Styles'!Q5:Q574,'FW26 Styles'!A5:A574,A97,'FW26 Styles'!B5:B574,B97,'FW26 Styles'!C5:C574,C97) -> 0 | E97: =SUMIFS('FW26 Styles'!P5:P574,'FW26 Styles'!A5:A574,A97,'FW26 Styles'!B5:B574,B97,'FW26 Styles'!C5:C574,C97) -> 0 | F97: =IF(D97=0,"",1-(E97/D97)) | G97: =SUMIFS('FW26 Styles'!O5:O574,'FW26 Styles'!A5:A574,A97,'FW26 Styles'!B5:B574,B97,'FW26 Styles'!C5:C574,C97) -> 0 | H97: =SUMIFS('Last Season Data'!N5:N561,'Last Season Data'!B5:B561,A97,'Last Season Data'!C5:C561,B97,'Last Season Data'!D5:D561,C97) -> 0 | I97: =SUMIFS('Last Season Data'!M5:M561,'Last Season Data'!B5:B561,A97,'Last Season Data'!C5:C561,B97,'Last Season Data'!D5:D561,C97) -> 0 | J97: =D97-H97 -> 0 | K97: =IF(H97=0,"",(D97-H97)/H97) | L97: =G97-I97 -> 0
A98: Accessories | B98: Accessories | C98: New | D98: =SUMIFS('FW26 Styles'!Q5:Q574,'FW26 Styles'!A5:A574,A98,'FW26 Styles'!B5:B574,B98,'FW26 Styles'!C5:C574,C98) -> 0 | E98: =SUMIFS('FW26 Styles'!P5:P574,'FW26 Styles'!A5:A574,A98,'FW26 Styles'!B5:B574,B98,'FW26 Styles'!C5:C574,C98) -> 0 | F98: =IF(D98=0,"",1-(E98/D98)) | G98: =SUMIFS('FW26 Styles'!O5:O574,'FW26 Styles'!A5:A574,A98,'FW26 Styles'!B5:B574,B98,'FW26 Styles'!C5:C574,C98) -> 0 | H98: =SUMIFS('Last Season Data'!N5:N561,'Last Season Data'!B5:B561,A98,'Last Season Data'!C5:C561,B98,'Last Season Data'!D5:D561,C98) -> 0 | I98: =SUMIFS('Last Season Data'!M5:M561,'Last Season Data'!B5:B561,A98,'Last Season Data'!C5:C561,B98,'Last Season Data'!D5:D561,C98) -> 0 | J98: =D98-H98 -> 0 | K98: =IF(H98=0,"",(D98-H98)/H98) | L98: =G98-I98 -> 0
A99: Accessories | B99: Accessories | C99: New 1 | D99: =SUMIFS('FW26 Styles'!Q5:Q574,'FW26 Styles'!A5:A574,A99,'FW26 Styles'!B5:B574,B99,'FW26 Styles'!C5:C574,C99) -> 0 | E99: =SUMIFS('FW26 Styles'!P5:P574,'FW26 Styles'!A5:A574,A99,'FW26 Styles'!B5:B574,B99,'FW26 Styles'!C5:C574,C99) -> 0 | F99: =IF(D99=0,"",1-(E99/D99)) | G99: =SUMIFS('FW26 Styles'!O5:O574,'FW26 Styles'!A5:A574,A99,'FW26 Styles'!B5:B574,B99,'FW26 Styles'!C5:C574,C99) -> 0 | H99: =SUMIFS('Last Season Data'!N5:N561,'Last Season Data'!B5:B561,A99,'Last Season Data'!C5:C561,B99,'Last Season Data'!D5:D561,C99) -> 0 | I99: =SUMIFS('Last Season Data'!M5:M561,'Last Season Data'!B5:B561,A99,'Last Season Data'!C5:C561,B99,'Last Season Data'!D5:D561,C99) -> 0 | J99: =D99-H99 -> 0 | K99: =IF(H99=0,"",(D99-H99)/H99) | L99: =G99-I99 -> 0
A100: Accessories | B100: Accessories | C100: New 2 | D100: =SUMIFS('FW26 Styles'!Q5:Q574,'FW26 Styles'!A5:A574,A100,'FW26 Styles'!B5:B574,B100,'FW26 Styles'!C5:C574,C100) -> 0 | E100: =SUMIFS('FW26 Styles'!P5:P574,'FW26 Styles'!A5:A574,A100,'FW26 Styles'!B5:B574,B100,'FW26 Styles'!C5:C574,C100) -> 0 | F100: =IF(D100=0,"",1-(E100/D100)) | G100: =SUMIFS('FW26 Styles'!O5:O574,'FW26 Styles'!A5:A574,A100,'FW26 Styles'!B5:B574,B100,'FW26 Styles'!C5:C574,C100) -> 0 | H100: =SUMIFS('Last Season Data'!N5:N561,'Last Season Data'!B5:B561,A100,'Last Season Data'!C5:C561,B100,'Last Season Data'!D5:D561,C100) -> 0 | I100: =SUMIFS('Last Season Data'!M5:M561,'Last Season Data'!B5:B561,A100,'Last Season Data'!C5:C561,B100,'Last Season Data'!D5:D561,C100) -> 0 | J100: =D100-H100 -> 0 | K100: =IF(H100=0,"",(D100-H100)/H100) | L100: =G100-I100 -> 0
A101: Accessories | B101: Accessories | C101: New 3 | D101: =SUMIFS('FW26 Styles'!Q5:Q574,'FW26 Styles'!A5:A574,A101,'FW26 Styles'!B5:B574,B101,'FW26 Styles'!C5:C574,C101) -> 0 | E101: =SUMIFS('FW26 Styles'!P5:P574,'FW26 Styles'!A5:A574,A101,'FW26 Styles'!B5:B574,B101,'FW26 Styles'!C5:C574,C101) -> 0 | F101: =IF(D101=0,"",1-(E101/D101)) | G101: =SUMIFS('FW26 Styles'!O5:O574,'FW26 Styles'!A5:A574,A101,'FW26 Styles'!B5:B574,B101,'FW26 Styles'!C5:C574,C101) -> 0 | H101: =SUMIFS('Last Season Data'!N5:N561,'Last Season Data'!B5:B561,A101,'Last Season Data'!C5:C561,B101,'Last Season Data'!D5:D561,C101) -> 0 | I101: =SUMIFS('Last Season Data'!M5:M561,'Last Season Data'!B5:B561,A101,'Last Season Data'!C5:C561,B101,'Last Season Data'!D5:D561,C101) -> 0 | J101: =D101-H101 -> 0 | K101: =IF(H101=0,"",(D101-H101)/H101) | L101: =G101-I101 -> 0
B102: Accessories Subtotal | D102: =SUM(D91:D101) -> 0 | E102: =SUM(E91:E101) -> 0 | F102: =IF(D102=0,"",1-(E102/D102)) | G102: =SUM(G91:G101) -> 0 | H102: =SUM(H91:H101) -> 122023.08 | I102: =SUM(I91:I101) -> 3088 | J102: =SUM(J91:J101) -> -122023.08 | K102: =IF(H102=0,"",(D102-H102)/H102) -> -1 | L102: =SUM(L91:L101) -> -3088
A103: Accessories TOTAL | D103: =SUMIFS(D32:D102,A32:A102,"Accessories") -> 0 | E103: =SUMIFS(E32:E102,A32:A102,"Accessories") -> 0 | F103: =IF(D103=0,"",1-(E103/D103)) | G103: =SUMIFS(G32:G102,A32:A102,"Accessories") -> 0 | H103: =SUMIFS(H32:H102,A32:A102,"Accessories") -> 122023.08 | I103: =SUMIFS(I32:I102,A32:A102,"Accessories") -> 3088 | J103: =SUMIFS(J32:J102,A32:A102,"Accessories") -> -122023.08 | K103: =IF(H103=0,"",(D103-H103)/H103) -> -1 | L103: =SUMIFS(L32:L102,A32:A102,"Accessories") -> -3088
A104: GRAND TOTAL | D104: ='FW26 Styles'!Q505 -> 0 | E104: ='FW26 Styles'!P505 -> 0 | F104: =IF(D104=0,"",1-(E104/D104)) | G104: ='FW26 Styles'!O505 -> 0 | H104: ='Last Season Data'!N497 -> 712 | I104: ='Last Season Data'!M497 -> 8 | J104: =D104-H104 -> -712 | K104: =IF(H104=0,"",(D104-H104)/H104) -> -1 | L104: =G104-I104 -> -8

Sheet OTB Budget
A1: FW26 — OTB BUDGET & SALES MIX
A2: Set overall OTB, allocate % per drop, then input expected sales mix. Yellow = input.
A4: Collection: | B4: FW26
A5: Total OTB Budget ($): | B5: 500000
A6: Target Margin %: | B6: 0.83
A8: DROP ALLOCATION
A9: Drop | B9: Allocation % | C9: Allocation ($)
A10: Drop 1 - Sep | C10: =B10*B$5 -> 0
A11: Drop 2 - Oct | C11: =B11*B$5 -> 0
A12: Drop 3 - Nov | C12: =B12*B$5 -> 0
A13: TOTAL | B13: =SUM(B10:B12) -> 0 | C13: =SUM(C10:C12) -> 0
A15: PLANNED vs OTB BY DROP
A16: Drop | B16: OTB ($) | C16: Planned Retail ($) | D16: Planned Cost ($) | E16: Planned Units | F16: Remaining ($)
A17: Drop 1 - Sep | B17: =C10 -> 0 | C17: =SUMIFS('FW26 Styles'!Q5:Q504,'FW26 Styles'!I5:I504,A17) -> 0 | D17: =SUMIFS('FW26 Styles'!P5:P504,'FW26 Styles'!I5:I504,A17) -> 0 | E17: =SUMIFS('FW26 Styles'!O5:O504,'FW26 Styles'!I5:I504,A17) -> 0 | F17: =B17-C17 -> 0
A18: Drop 2 - Oct | B18: =C11 -> 0 | C18: =SUMIFS('FW26 Styles'!Q5:Q504,'FW26 Styles'!I5:I504,A18) -> 0 | D18: =SUMIFS('FW26 Styles'!P5:P504,'FW26 Styles'!I5:I504,A18) -> 0 | E18: =SUMIFS('FW26 Styles'!O5:O504,'FW26 Styles'!I5:I504,A18) -> 0 | F18: =B18-C18 -> 0
A19: Drop 3 - Nov | B19: =C12 -> 0 | C19: =SUMIFS('FW26 Styles'!Q5:Q504,'FW26 Styles'!I5:I504,A19) -> 0 | D19: =SUMIFS('FW26 Styles'!P5:P504,'FW26 Styles'!I5:I504,A19) -> 0 | E19: =SUMIFS('FW26 Styles'!O5:O504,'FW26 Styles'!I5:I504,A19) -> 0 | F19: =B19-C19 -> 0
A20: TOTAL | B20: =SUM(B17:B19) -> 0 | C20: =SUM(C17:C19) -> 0 | D20: =SUM(D17:D19) -> 0 | E20: =SUM(E17:E19) -> 0 | F20: =SUM(F17:F19) -> 0
A22: SALES MIX — EXPECTED vs PROPOSED
A23: Main Category | B23: Category | C23: Sub Category | D23: Expected Sales Mix % | E23: Proposed Buy Mix % | F23: Variance (pp)
A24: Headwear | B24: Scarves | C24: Premium | D24: 0.18 | E24: =IF('FW26 Styles'!Q505=0,"",SUMIFS('FW26 Styles'!Q5:Q504,'FW26 Styles'!A5:A504,A24,'FW26 Styles'!B5:B504,B24,'FW26 Styles'!C5:C504,C24)/'FW26 Styles'!Q505) | F24: =IF(OR(D24="",E24=""),"",E24-D24)
A25: Headwear | B25: Scarves | C25: Bamboo | D25: 0.05 | E25: =IF('FW26 Styles'!Q505=0,"",SUMIFS('FW26 Styles'!Q5:Q504,'FW26 Styles'!A5:A504,A25,'FW26 Styles'!B5:B504,B25,'FW26 Styles'!C5:C504,C25)/'FW26 Styles'!Q505) | F25: =IF(OR(D25="",E25=""),"",E25-D25)
A26: Headwear | B26: Scarves | C26: Breathable | D26: 0.03 | E26: =IF('FW26 Styles'!Q505=0,"",SUMIFS('FW26 Styles'!Q5:Q504,'FW26 Styles'!A5:A504,A26,'FW26 Styles'!B5:B504,B26,'FW26 Styles'!C5:C504,C26)/'FW26 Styles'!Q505) | F26: =IF(OR(D26="",E26=""),"",E26-D26)
A27: Headwear | B27: Scarves | C27: Liquid | D27: 0.08 | E27: =IF('FW26 Styles'!Q505=0,"",SUMIFS('FW26 Styles'!Q5:Q504,'FW26 Styles'!A5:A504,A27,'FW26 Styles'!B5:B504,B27,'FW26 Styles'!C5:C504,C27)/'FW26 Styles'!Q505) | F27: =IF(OR(D27="",E27=""),"",E27-D27)
A28: Headwear | B28: Scarves | C28: Decorative | D28: 0.09 | E28: =IF('FW26 Styles'!Q505=0,"",SUMIFS('FW26 Styles'!Q5:Q504,'FW26 Styles'!A5:A504,A28,'FW26 Styles'!B5:B504,B28,'FW26 Styles'!C5:C504,C28)/'FW26 Styles'!Q505) | F28: =IF(OR(D28="",E28=""),"",E28-D28)
A29: Headwear | B29: Scarves | C29: Scarf Gift Box | D29: 0.03 | E29: =IF('FW26 Styles'!Q505=0,"",SUMIFS('FW26 Styles'!Q5:Q504,'FW26 Styles'!A5:A504,A29,'FW26 Styles'!B5:B504,B29,'FW26 Styles'!C5:C504,C29)/'FW26 Styles'!Q505) | F29: =IF(OR(D29="",E29=""),"",E29-D29)
A30: Headwear | B30: Scarves | C30: New 2 | E30: =IF('FW26 Styles'!Q505=0,"",SUMIFS('FW26 Styles'!Q5:Q504,'FW26 Styles'!A5:A504,A30,'FW26 Styles'!B5:B504,B30,'FW26 Styles'!C5:C504,C30)/'FW26 Styles'!Q505) | F30: =IF(OR(D30="",E30=""),"",E30-D30)
A31: Headwear | B31: Scarves | C31: New 3 | E31: =IF('FW26 Styles'!Q505=0,"",SUMIFS('FW26 Styles'!Q5:Q504,'FW26 Styles'!A5:A504,A31,'FW26 Styles'!B5:B504,B31,'FW26 Styles'!C5:C504,C31)/'FW26 Styles'!Q505) | F31: =IF(OR(D31="",E31=""),"",E31-D31)
B32: Scarves Subtotal | D32: =SUM(D24:D31) -> 0.46 | E32: =SUM(E24:E31) -> 0 | F32: =IF(OR(D32="",E32=""),"",E32-D32) -> -0.46
A33: Headwear | B33: Hijab | C33: Premium | E33: =IF('FW26 Styles'!Q505=0,"",SUMIFS('FW26 Styles'!Q5:Q504,'FW26 Styles'!A5:A504,A33,'FW26 Styles'!B5:B504,B33,'FW26 Styles'!C5:C504,C33)/'FW26 Styles'!Q505) | F33: =IF(OR(D33="",E33=""),"",E33-D33)
A34: Headwear | B34: Hijab | C34: Bamboo | E34: =IF('FW26 Styles'!Q505=0,"",SUMIFS('FW26 Styles'!Q5:Q504,'FW26 Styles'!A5:A504,A34,'FW26 Styles'!B5:B504,B34,'FW26 Styles'!C5:C504,C34)/'FW26 Styles'!Q505) | F34: =IF(OR(D34="",E34=""),"",E34-D34)
A35: Headwear | B35: Hijab | C35: Breathable | E35: =IF('FW26 Styles'!Q505=0,"",SUMIFS('FW26 Styles'!Q5:Q504,'FW26 Styles'!A5:A504,A35,'FW26 Styles'!B5:B504,B35,'FW26 Styles'!C5:C504,C35)/'FW26 Styles'!Q505) | F35: =IF(OR(D35="",E35=""),"",E35-D35)
A36: Headwear | B36: Hijab | C36: Underscarf | D36: 0.01 | E36: =IF('FW26 Styles'!Q505=0,"",SUMIFS('FW26 Styles'!Q5:Q504,'FW26 Styles'!A5:A504,A36,'FW26 Styles'!B5:B504,B36,'FW26 Styles'!C5:C504,C36)/'FW26 Styles'!Q505) | F36: =IF(OR(D36="",E36=""),"",E36-D36)
A37: Headwear | B37: Hijab | C37: New 2 | E37: =IF('FW26 Styles'!Q505=0,"",SUMIFS('FW26 Styles'!Q5:Q504,'FW26 Styles'!A5:A504,A37,'FW26 Styles'!B5:B504,B37,'FW26 Styles'!C5:C504,C37)/'FW26 Styles'!Q505) | F37: =IF(OR(D37="",E37=""),"",E37-D37)
A38: Headwear | B38: Hijab | C38: New 3 | E38: =IF('FW26 Styles'!Q505=0,"",SUMIFS('FW26 Styles'!Q5:Q504,'FW26 Styles'!A5:A504,A38,'FW26 Styles'!B5:B504,B38,'FW26 Styles'!C5:C504,C38)/'FW26 Styles'!Q505) | F38: =IF(OR(D38="",E38=""),"",E38-D38)
B39: Hijab Subtotal | D39: =SUM(D33:D38) -> 0.01 | E39: =SUM(E33:E38) -> 0 | F39: =IF(OR(D39="",E39=""),"",E39-D39) -> -0.01
A40: Headwear | B40: Khimaar | C40: Premium | D40: 0.05 | E40: =IF('FW26 Styles'!Q505=0,"",SUMIFS('FW26 Styles'!Q5:Q504,'FW26 Styles'!A5:A504,A40,'FW26 Styles'!B5:B504,B40,'FW26 Styles'!C5:C504,C40)/'FW26 Styles'!Q505) | F40: =IF(OR(D40="",E40=""),"",E40-D40)
A41: Headwear | B41: Khimaar | C41: Bamboo | E41: =IF('FW26 Styles'!Q505=0,"",SUMIFS('FW26 Styles'!Q5:Q504,'FW26 Styles'!A5:A504,A41,'FW26 Styles'!B5:B504,B41,'FW26 Styles'!C5:C504,C41)/'FW26 Styles'!Q505) | F41: =IF(OR(D41="",E41=""),"",E41-D41)
A42: Headwear | B42: Khimaar | C42: Breathable | E42: =IF('FW26 Styles'!Q505=0,"",SUMIFS('FW26 Styles'!Q5:Q504,'FW26 Styles'!A5:A504,A42,'FW26 Styles'!B5:B504,B42,'FW26 Styles'!C5:C504,C42)/'FW26 Styles'!Q505) | F42: =IF(OR(D42="",E42=""),"",E42-D42)
A43: Headwear | B43: Khimaar | C43: New 1 | E43: =IF('FW26 Styles'!Q505=0,"",SUMIFS('FW26 Styles'!Q5:Q504,'FW26 Styles'!A5:A504,A43,'FW26 Styles'!B5:B504,B43,'FW26 Styles'!C5:C504,C43)/'FW26 Styles'!Q505) | F43: =IF(OR(D43="",E43=""),"",E43-D43)
A44: Headwear | B44: Khimaar | C44: New 2 | E44: =IF('FW26 Styles'!Q505=0,"",SUMIFS('FW26 Styles'!Q5:Q504,'FW26 Styles'!A5:A504,A44,'FW26 Styles'!B5:B504,B44,'FW26 Styles'!C5:C504,C44)/'FW26 Styles'!Q505) | F44: =IF(OR(D44="",E44=""),"",E44-D44)
A45: Headwear | B45: Khimaar | C45: New 3 | E45: =IF('FW26 Styles'!Q505=0,"",SUMIFS('FW26 Styles'!Q5:Q504,'FW26 Styles'!A5:A504,A45,'FW26 Styles'!B5:B504,B45,'FW26 Styles'!C5:C504,C45)/'FW26 Styles'!Q505) | F45: =IF(OR(D45="",E45=""),"",E45-D45)
B46: Khimaar Subtotal | D46: =SUM(D40:D45) -> 0.05 | E46: =SUM(E40:E45) -> 0 | F46: =IF(OR(D46="",E46=""),"",E46-D46) -> -0.05
A47: Headwear TOTAL | D47: =D32+D39+D46 -> 0.52 | E47: =E32+E39+E46 -> 0 | F47: =IF(OR(D47="",E47=""),"",E47-D47) -> -0.52
A48: Clothing | B48: Dresses | C48: Casual | D48: 0.11 | E48: =IF('FW26 Styles'!Q505=0,"",SUMIFS('FW26 Styles'!Q5:Q504,'FW26 Styles'!A5:A504,A48,'FW26 Styles'!B5:B504,B48,'FW26 Styles'!C5:C504,C48)/'FW26 Styles'!Q505) | F48: =IF(OR(D48="",E48=""),"",E48-D48)
A49: Clothing | B49: Dresses | C49: Occasion | D49: 0.01 | E49: =IF('FW26 Styles'!Q505=0,"",SUMIFS('FW26 Styles'!Q5:Q504,'FW26 Styles'!A5:A504,A49,'FW26 Styles'!B5:B504,B49,'FW26 Styles'!C5:C504,C49)/'FW26 Styles'!Q505) | F49: =IF(OR(D49="",E49=""),"",E49-D49)
A50: Clothing | B50: Dresses | C50: Essential | D50: 0.04 | E50: =IF('FW26 Styles'!Q505=0,"",SUMIFS('FW26 Styles'!Q5:Q504,'FW26 Styles'!A5:A504,A50,'FW26 Styles'!B5:B504,B50,'FW26 Styles'!C5:C504,C50)/'FW26 Styles'!Q505) | F50: =IF(OR(D50="",E50=""),"",E50-D50)
A51: Clothing | B51: Dresses | C51: New 1 | E51: =IF('FW26 Styles'!Q505=0,"",SUMIFS('FW26 Styles'!Q5:Q504,'FW26 Styles'!A5:A504,A51,'FW26 Styles'!B5:B504,B51,'FW26 Styles'!C5:C504,C51)/'FW26 Styles'!Q505) | F51: =IF(OR(D51="",E51=""),"",E51-D51)
A52: Clothing | B52: Dresses | C52: New 2 | E52: =IF('FW26 Styles'!Q505=0,"",SUMIFS('FW26 Styles'!Q5:Q504,'FW26 Styles'!A5:A504,A52,'FW26 Styles'!B5:B504,B52,'FW26 Styles'!C5:C504,C52)/'FW26 Styles'!Q505) | F52: =IF(OR(D52="",E52=""),"",E52-D52)
A53: Clothing | B53: Dresses | C53: New 3 | E53: =IF('FW26 Styles'!Q505=0,"",SUMIFS('FW26 Styles'!Q5:Q504,'FW26 Styles'!A5:A504,A53,'FW26 Styles'!B5:B504,B53,'FW26 Styles'!C5:C504,C53)/'FW26 Styles'!Q505) | F53: =IF(OR(D53="",E53=""),"",E53-D53)
B54: Dresses Subtotal | D54: =SUM(D48:D53) -> 0.16 | E54: =SUM(E48:E53) -> 0 | F54: =IF(OR(D54="",E54=""),"",E54-D54) -> -0.16
A55: Clothing | B55: Tops | C55: Sweater | D55: 0.07 | E55: =IF('FW26 Styles'!Q505=0,"",SUMIFS('FW26 Styles'!Q5:Q504,'FW26 Styles'!A5:A504,A55,'FW26 Styles'!B5:B504,B55,'FW26 Styles'!C5:C504,C55)/'FW26 Styles'!Q505) | F55: =IF(OR(D55="",E55=""),"",E55-D55)
A56: Clothing | B56: Tops | C56: LS Top | D56: 0.04 | E56: =IF('FW26 Styles'!Q505=0,"",SUMIFS('FW26 Styles'!Q5:Q504,'FW26 Styles'!A5:A504,A56,'FW26 Styles'!B5:B504,B56,'FW26 Styles'!C5:C504,C56)/'FW26 Styles'!Q505) | F56: =IF(OR(D56="",E56=""),"",E56-D56)
A57: Clothing | B57: Tops | C57: Shirt | D57: 0.0115 | E57: =IF('FW26 Styles'!Q505=0,"",SUMIFS('FW26 Styles'!Q5:Q504,'FW26 Styles'!A5:A504,A57,'FW26 Styles'!B5:B504,B57,'FW26 Styles'!C5:C504,C57)/'FW26 Styles'!Q505) | F57: =IF(OR(D57="",E57=""),"",E57-D57)
A58: Clothing | B58: Tops | C58: Cardigan | D58: 0.02 | E58: =IF('FW26 Styles'!Q505=0,"",SUMIFS('FW26 Styles'!Q5:Q504,'FW26 Styles'!A5:A504,A58,'FW26 Styles'!B5:B504,B58,'FW26 Styles'!C5:C504,C58)/'FW26 Styles'!Q505) | F58: =IF(OR(D58="",E58=""),"",E58-D58)
A59: Clothing | B59: Tops | C59: Blouse | D59: 0.01 | E59: =IF('FW26 Styles'!Q505=0,"",SUMIFS('FW26 Styles'!Q5:Q504,'FW26 Styles'!A5:A504,A59,'FW26 Styles'!B5:B504,B59,'FW26 Styles'!C5:C504,C59)/'FW26 Styles'!Q505) | F59: =IF(OR(D59="",E59=""),"",E59-D59)
A60: Clothing | B60: Tops | C60: New 2 | E60: =IF('FW26 Styles'!Q505=0,"",SUMIFS('FW26 Styles'!Q5:Q504,'FW26 Styles'!A5:A504,A60,'FW26 Styles'!B5:B504,B60,'FW26 Styles'!C5:C504,C60)/'FW26 Styles'!Q505) | F60: =IF(OR(D60="",E60=""),"",E60-D60)
A61: Clothing | B61: Tops | C61: New 3 | E61: =IF('FW26 Styles'!Q505=0,"",SUMIFS('FW26 Styles'!Q5:Q504,'FW26 Styles'!A5:A504,A61,'FW26 Styles'!B5:B504,B61,'FW26 Styles'!C5:C504,C61)/'FW26 Styles'!Q505) | F61: =IF(OR(D61="",E61=""),"",E61-D61)
A62: Clothing | B62: Tops | C62: New 4 | E62: =IF('FW26 Styles'!Q505=0,"",SUMIFS('FW26 Styles'!Q5:Q504,'FW26 Styles'!A5:A504,A62,'FW26 Styles'!B5:B504,B62,'FW26 Styles'!C5:C504,C62)/'FW26 Styles'!Q505) | F62: =IF(OR(D62="",E62=""),"",E62-D62)
A63: Clothing | B63: Tops | C63: New 5 | E63: =IF('FW26 Styles'!Q505=0,"",SUMIFS('FW26 Styles'!Q5:Q504,'FW26 Styles'!A5:A504,A63,'FW26 Styles'!B5:B504,B63,'FW26 Styles'!C5:C504,C63)/'FW26 Styles'!Q505) | F63: =IF(OR(D63="",E63=""),"",E63-D63)
A64: Clothing | B64: Tops | C64: New 3 | E64: =IF('FW26 Styles'!Q505=0,"",SUMIFS('FW26 Styles'!Q5:Q504,'FW26 Styles'!A5:A504,A64,'FW26 Styles'!B5:B504,B64,'FW26 Styles'!C5:C504,C64)/'FW26 Styles'!Q505) | F64: =IF(OR(D64="",E64=""),"",E64-D64)
B65: Tops Subtotal | D65: =SUM(D55:D64) -> 0.1515 | E65: =SUM(E55:E64) -> 0 | F65: =IF(OR(D65="",E65=""),"",E65-D65) -> -0.1515
A66: Clothing | B66: Bottoms | C66: Pants | E66: =IF('FW26 Styles'!Q505=0,"",SUMIFS('FW26 Styles'!Q5:Q504,'FW26 Styles'!A5:A504,A66,'FW26 Styles'!B5:B504,B66,'FW26 Styles'!C5:C504,C66)/'FW26 Styles'!Q505) | F66: =IF(OR(D66="",E66=""),"",E66-D66)
A67: Clothing | B67: Bottoms | C67: Skirts | E67: =IF('FW26 Styles'!Q505=0,"",SUMIFS('FW26 Styles'!Q5:Q504,'FW26 Styles'!A5:A504,A67,'FW26 Styles'!B5:B504,B67,'FW26 Styles'!C5:C504,C67)/'FW26 Styles'!Q505) | F67: =IF(OR(D67="",E67=""),"",E67-D67)
A68: Clothing | B68: Bottoms | C68: Legging | E68: =IF('FW26 Styles'!Q505=0,"",SUMIFS('FW26 Styles'!Q5:Q504,'FW26 Styles'!A5:A504,A68,'FW26 Styles'!B5:B504,B68,'FW26 Styles'!C5:C504,C68)/'FW26 Styles'!Q505) | F68: =IF(OR(D68="",E68=""),"",E68-D68)
A69: Clothing | B69: Bottoms | C69: New 1 | E69: =IF('FW26 Styles'!Q505=0,"",SUMIFS('FW26 Styles'!Q5:Q504,'FW26 Styles'!A5:A504,A69,'FW26 Styles'!B5:B504,B69,'FW26 Styles'!C5:C504,C69)/'FW26 Styles'!Q505) | F69: =IF(OR(D69="",E69=""),"",E69-D69)
A70: Clothing | B70: Bottoms | C70: New 2 | E70: =IF('FW26 Styles'!Q505=0,"",SUMIFS('FW26 Styles'!Q5:Q504,'FW26 Styles'!A5:A504,A70,'FW26 Styles'!B5:B504,B70,'FW26 Styles'!C5:C504,C70)/'FW26 Styles'!Q505) | F70: =IF(OR(D70="",E70=""),"",E70-D70)
A71: Clothing | B71: Bottoms | C71: New 3 | E71: =IF('FW26 Styles'!Q505=0,"",SUMIFS('FW26 Styles'!Q5:Q504,'FW26 Styles'!A5:A504,A71,'FW26 Styles'!B5:B504,B71,'FW26 Styles'!C5:C504,C71)/'FW26 Styles'!Q505) | F71: =IF(OR(D71="",E71=""),"",E71-D71)
B72: Bottoms Subtotal | D72: =SUM(D66:D71) -> 0 | E72: =SUM(E66:E71) -> 0 | F72: =IF(OR(D72="",E72=""),"",E72-D72) -> 0
A73: Clothing | B73: Outerwear | C73: Abaya | E73: =IF('FW26 Styles'!Q505=0,"",SUMIFS('FW26 Styles'!Q5:Q504,'FW26 Styles'!A5:A504,A73,'FW26 Styles'!B5:B504,B73,'FW26 Styles'!C5:C504,C73)/'FW26 Styles'!Q505) | F73: =IF(OR(D73="",E73=""),"",E73-D73)
A74: Clothing | B74: Outerwear | C74: Jacket | E74: =IF('FW26 Styles'!Q505=0,"",SUMIFS('FW26 Styles'!Q5:Q504,'FW26 Styles'!A5:A504,A74,'FW26 Styles'!B5:B504,B74,'FW26 Styles'!C5:C504,C74)/'FW26 Styles'!Q505) | F74: =IF(OR(D74="",E74=""),"",E74-D74)
A75: Clothing | B75: Outerwear | C75: Coat | E75: =IF('FW26 Styles'!Q505=0,"",SUMIFS('FW26 Styles'!Q5:Q504,'FW26 Styles'!A5:A504,A75,'FW26 Styles'!B5:B504,B75,'FW26 Styles'!C5:C504,C75)/'FW26 Styles'!Q505) | F75: =IF(OR(D75="",E75=""),"",E75-D75)
A76: Clothing | B76: Outerwear | C76: Bomber | E76: =IF('FW26 Styles'!Q505=0,"",SUMIFS('FW26 Styles'!Q5:Q504,'FW26 Styles'!A5:A504,A76,'FW26 Styles'!B5:B504,B76,'FW26 Styles'!C5:C504,C76)/'FW26 Styles'!Q505) | F76: =IF(OR(D76="",E76=""),"",E76-D76)
A77: Clothing | B77: Outerwear | C77: Poncho | E77: =IF('FW26 Styles'!Q505=0,"",SUMIFS('FW26 Styles'!Q5:Q504,'FW26 Styles'!A5:A504,A77,'FW26 Styles'!B5:B504,B77,'FW26 Styles'!C5:C504,C77)/'FW26 Styles'!Q505) | F77: =IF(OR(D77="",E77=""),"",E77-D77)
A78: Clothing | B78: Outerwear | C78: New 1 | E78: =IF('FW26 Styles'!Q505=0,"",SUMIFS('FW26 Styles'!Q5:Q504,'FW26 Styles'!A5:A504,A78,'FW26 Styles'!B5:B504,B78,'FW26 Styles'!C5:C504,C78)/'FW26 Styles'!Q505) | F78: =IF(OR(D78="",E78=""),"",E78-D78)
A79: Clothing | B79: Outerwear | C79: New 2 | E79: =IF('FW26 Styles'!Q505=0,"",SUMIFS('FW26 Styles'!Q5:Q504,'FW26 Styles'!A5:A504,A79,'FW26 Styles'!B5:B504,B79,'FW26 Styles'!C5:C504,C79)/'FW26 Styles'!Q505) | F79: =IF(OR(D79="",E79=""),"",E79-D79)
A80: Clothing | B80: Outerwear | C80: New 3 | E80: =IF('FW26 Styles'!Q505=0,"",SUMIFS('FW26 Styles'!Q5:Q504,'FW26 Styles'!A5:A504,A80,'FW26 Styles'!B5:B504,B80,'FW26 Styles'!C5:C504,C80)/'FW26 Styles'!Q505) | F80: =IF(OR(D80="",E80=""),"",E80-D80)
B81: Outerwear Subtotal | D81: =SUM(D73:D80) -> 0 | E81: =SUM(E73:E80) -> 0 | F81: =IF(OR(D81="",E81=""),"",E81-D81) -> 0
A82: Clothing TOTAL | D82: =D54+D65+D72+D81 -> 0.3115 | E82: =E54+E65+E72+E81 -> 0 | F82: =IF(OR(D82="",E82=""),"",E82-D82) -> -0.3115
A83: Accessories | B83: Accessories | C83: Sunglasses | E83: =IF('FW26 Styles'!Q505=0,"",SUMIFS('FW26 Styles'!Q5:Q504,'FW26 Styles'!A5:A504,A83,'FW26 Styles'!B5:B504,B83,'FW26 Styles'!C5:C504,C83)/'FW26 Styles'!Q505) | F83: =IF(OR(D83="",E83=""),"",E83-D83)
A84: Accessories | B84: Accessories | C84: Bags | E84: =IF('FW26 Styles'!Q505=0,"",SUMIFS('FW26 Styles'!Q5:Q504,'FW26 Styles'!A5:A504,A84,'FW26 Styles'!B5:B504,B84,'FW26 Styles'!C5:C504,C84)/'FW26 Styles'!Q505) | F84: =IF(OR(D84="",E84=""),"",E84-D84)
A85: Accessories | B85: Accessories | C85: Tote Bags | E85: =IF('FW26 Styles'!Q505=0,"",SUMIFS('FW26 Styles'!Q5:Q504,'FW26 Styles'!A5:A504,A85,'FW26 Styles'!B5:B504,B85,'FW26 Styles'!C5:C504,C85)/'FW26 Styles'!Q505) | F85: =IF(OR(D85="",E85=""),"",E85-D85)
A86: Accessories | B86: Accessories | C86: Misc | E86: =IF('FW26 Styles'!Q505=0,"",SUMIFS('FW26 Styles'!Q5:Q504,'FW26 Styles'!A5:A504,A86,'FW26 Styles'!B5:B504,B86,'FW26 Styles'!C5:C504,C86)/'FW26 Styles'!Q505) | F86: =IF(OR(D86="",E86=""),"",E86-D86)
A87: Accessories | B87: Accessories | C87: Scarves | E87: =IF('FW26 Styles'!Q505=0,"",SUMIFS('FW26 Styles'!Q5:Q504,'FW26 Styles'!A5:A504,A87,'FW26 Styles'!B5:B504,B87,'FW26 Styles'!C5:C504,C87)/'FW26 Styles'!Q505) | F87: =IF(OR(D87="",E87=""),"",E87-D87)
A88: Accessories | B88: Accessories | C88: Gloves | E88: =IF('FW26 Styles'!Q505=0,"",SUMIFS('FW26 Styles'!Q5:Q504,'FW26 Styles'!A5:A504,A88,'FW26 Styles'!B5:B504,B88,'FW26 Styles'!C5:C504,C88)/'FW26 Styles'!Q505) | F88: =IF(OR(D88="",E88=""),"",E88-D88)
A89: Accessories | B89: Accessories | C89: Balaclava | E89: =IF('FW26 Styles'!Q505=0,"",SUMIFS('FW26 Styles'!Q5:Q504,'FW26 Styles'!A5:A504,A89,'FW26 Styles'!B5:B504,B89,'FW26 Styles'!C5:C504,C89)/'FW26 Styles'!Q505) | F89: =IF(OR(D89="",E89=""),"",E89-D89)
A90: Accessories | B90: Accessories | C90: Keyring | E90: =IF('FW26 Styles'!Q505=0,"",SUMIFS('FW26 Styles'!Q5:Q504,'FW26 Styles'!A5:A504,A90,'FW26 Styles'!B5:B504,B90,'FW26 Styles'!C5:C504,C90)/'FW26 Styles'!Q505) | F90: =IF(OR(D90="",E90=""),"",E90-D90)
A91: Accessories | B91: Accessories | C91: New 1 | E91: =IF('FW26 Styles'!Q505=0,"",SUMIFS('FW26 Styles'!Q5:Q504,'FW26 Styles'!A5:A504,A91,'FW26 Styles'!B5:B504,B91,'FW26 Styles'!C5:C504,C91)/'FW26 Styles'!Q505) | F91: =IF(OR(D91="",E91=""),"",E91-D91)
A92: Accessories | B92: Accessories | C92: New 2 | E92: =IF('FW26 Styles'!Q505=0,"",SUMIFS('FW26 Styles'!Q5:Q504,'FW26 Styles'!A5:A504,A92,'FW26 Styles'!B5:B504,B92,'FW26 Styles'!C5:C504,C92)/'FW26 Styles'!Q505) | F92: =IF(OR(D92="",E92=""),"",E92-D92)
A93: Accessories | B93: Accessories | C93: New 3 | E93: =IF('FW26 Styles'!Q505=0,"",SUMIFS('FW26 Styles'!Q5:Q504,'FW26 Styles'!A5:A504,A93,'FW26 Styles'!B5:B504,B93,'FW26 Styles'!C5:C504,C93)/'FW26 Styles'!Q505) | F93: =IF(OR(D93="",E93=""),"",E93-D93)
B94: Accessories Subtotal | D94: =SUM(D83:D93) -> 0 | E94: =SUM(E83:E93) -> 0 | F94: =IF(OR(D94="",E94=""),"",E94-D94) -> 0
A95: Accessories TOTAL | D95: =D94 -> 0 | E95: =E94 -> 0 | F95: =IF(OR(D95="",E95=""),"",E95-D95) -> 0
A96: GRAND TOTAL | D96: =D47+D82+D95 -> 0.8315 | E96: =E47+E82+E95 -> 0 | F96: =IF(OR(D96="",E96=""),"",E96-D96) -> -0.8315

Sheet FW26 Styles
A1: FW26 — PRODUCT NOMINATION
A2: One row per style/colour. Assign Drop and Tier. Yellow = input. Margin & totals auto-calculate.
A4: Main Category | B4: Category | C4: Sub Category | D4: Fabric Group | E4: SKU | F4: Style Name | G4: Colour Name | H4: Colour No | I4: Drop | J4: Tier | K4: Cost Price ($) | L4: Retail Price ($) | M4: Margin % | N4: Margin ($) | O4: Units | P4: Total Cost ($) | Q4: Total Retail ($) | R4: Notes
A5: Clothing | B5: Dresses | D5: Branded Knit | F5: High Neck Knit Dress | I5: Drop 1 - Sep | J5: Commercial | K5: 16.016 | L5: 104 | M5: =(L5-K5)/L5 -> 0.846 | N5: =IF(OR($L5="",$K5=""),"",$L5-$K5) -> 87.984 | P5: =IF(OR(O5="",K5=""),"",K5*O5) | Q5: =IF(OR(O5="",L5=""),"",L5*O5)
A6: Clothing | B6: Outerwear | C6: Abaya | D6: Branded Knit | F6: Knitted Abaya | I6: Drop 1 - Sep | J6: Commercial | K6: 18.655 | L6: 119 | M6: =(L6-K6)/L6 -> 0.84323529 | N6: =IF(OR($L6="",$K6=""),"",$L6-$K6) -> 100.345 | P6: =IF(OR(O6="",K6=""),"",K6*O6) | Q6: =IF(OR(O6="",L6=""),"",L6*O6)
A7: Clothing | B7: Tops | C7: Sweater | D7: Branded Knit | F7: Branded Turtle Neck Sweater | I7: Drop 1 - Sep | J7: Commercial | K7: 12.649 | L7: 89 | M7: =(L7-K7)/L7 -> 0.8578764 | N7: =IF(OR($L7="",$K7=""),"",$L7-$K7) -> 76.351 | P7: =IF(OR(O7="",K7=""),"",K7*O7) | Q7: =IF(OR(O7="",L7=""),"",L7*O7)
A8: Clothing | B8: Bottoms | C8: Pants | D8: Branded Knit | F8: Relaxed Fit Knitted Trousers | I8: Drop 1 - Sep | J8: Commercial | K8: 12.285 | L8: 74 | M8: =(L8-K8)/L8 -> 0.83398649 | N8: =IF(OR($L8="",$K8=""),"",$L8-$K8) -> 61.715 | P8: =IF(OR(O8="",K8=""),"",K8*O8) | Q8: =IF(OR(O8="",L8=""),"",L8*O8)
A9: Accessories | B9: Acessories | C9: Hijab | D9: Branded Knit | F9: Knitted Hijab | I9: Drop 1 - Sep | J9: Commercial | K9: 0 | L9: 39 | M9: =(L9-K9)/L9 -> 1 | N9: =IF(OR($L9="",$K9=""),"",$L9-$K9) -> 39 | P9: =IF(OR(O9="",K9=""),"",K9*O9) | Q9: =IF(OR(O9="",L9=""),"",L9*O9)
A10: Clothing | B10: Outerwear | C10: Coat | D10: Bolied Wool | F10: Cape Wrap Coat | I10: Drop 1 - Sep | J10: Commercial | K10: 28.665 | L10: 179 | M10: =(L10-K10)/L10 -> 0.83986034 | N10: =IF(OR($L10="",$K10=""),"",$L10-$K10) -> 150.335 | P10: =IF(OR(O10="",K10=""),"",K10*O10) | Q10: =IF(OR(O10="",L10=""),"",L10*O10)
A11: Clothing | B11: Outerwear | C11: Poncho | D11: Bolied Wool | F11: High Neck Asymmetric Poncho | I11: Drop 1 - Sep | J11: Commercial | K11: 22.295 | L11: 84 | M11: =(L11-K11)/L11 -> 0.73458333 | N11: =IF(OR($L11="",$K11=""),"",$L11-$K11) -> 61.705 | P11: =IF(OR(O11="",K11=""),"",K11*O11) | Q11: =IF(OR(O11="",L11=""),"",L11*O11)
A12: Clothing | B12: Outerwear | C12: Poncho | D12: Bolied Wool | F12: High Neck Poncho | I12: Drop 1 - Sep | J12: Commercial | K12: 22.568 | L12: 84 | M12: =(L12-K12)/L12 -> 0.73133333 | N12: =IF(OR($L12="",$K12=""),"",$L12-$K12) -> 61.432 | P12: =IF(OR(O12="",K12=""),"",K12*O12) | Q12: =IF(OR(O12="",L12=""),"",L12*O12)
A13: Clothing | B13: Bottoms | C13: Skirt | D13: Bolied Wool | F13: Wool Volume Skirt | I13: Drop 1 - Sep | J13: Commercial | K13: 18.655 | L13: 74 | M13: =(L13-K13)/L13 -> 0.74790541 | N13: =IF(OR($L13="",$K13=""),"",$L13-$K13) -> 55.345 | P13: =IF(OR(O13="",K13=""),"",K13*O13) | Q13: =IF(OR(O13="",L13=""),"",L13*O13)
A14: Clothing | B14: Dresses | D14: Cotton Jersey | F14: Volume Cotton Tee Dress | I14: Drop 1 - Sep | J14: Commercial | K14: 16.107 | L14: 79 | M14: =(L14-K14)/L14 -> 0.79611392 | N14: =IF(OR($L14="",$K14=""),"",$L14-$K14) -> 62.893 | P14: =IF(OR(O14="",K14=""),"",K14*O14) | Q14: =IF(OR(O14="",L14=""),"",L14*O14)
A15: Clothing | B15: Tops | C15: LS Tee | D15: Cotton Jersey | F15: Volume Cotton Tee | I15: Drop 1 - Sep | J15: Commercial | K15: 17.108 | L15: 59 | M15: =(L15-K15)/L15 -> 0.7100339 | N15: =IF(OR($L15="",$K15=""),"",$L15-$K15) -> 41.892 | P15: =IF(OR(O15="",K15=""),"",K15*O15) | Q15: =IF(OR(O15="",L15=""),"",L15*O15)
A16: Clothing | B16: Bottoms | C16: Pants | D16: Cotton Jersey | F16: Jersey Tailored Pants | I16: Drop 1 - Sep | J16: Commercial | K16: 12.6945 | L16: 69 | M16: =(L16-K16)/L16 -> 0.81602174 | N16: =IF(OR($L16="",$K16=""),"",$L16-$K16) -> 56.3055 | P16: =IF(OR(O16="",K16=""),"",K16*O16) | Q16: =IF(OR(O16="",L16=""),"",L16*O16)
A17: Clothing | B17: Outerwear | C17: Jacket | D17: Satin | F17: Satin Baloon Jackt | I17: Drop 1 - Sep | J17: Commercial | K17: 18.473 | L17: 98 | M17: =(L17-K17)/L17 -> 0.8115 | N17: =IF(OR($L17="",$K17=""),"",$L17-$K17) -> 79.527 | P17: =IF(OR(O17="",K17=""),"",K17*O17) | Q17: =IF(OR(O17="",L17=""),"",L17*O17)
A18: Clothing | B18: Bottoms | C18: Pants | D18: Satin | F18: Airy Wide Fit | I18: Drop 1 - Sep | J18: Commercial | K18: 12.467 | L18: 79 | M18: =(L18-K18)/L18 -> 0.84218987 | N18: =IF(OR($L18="",$K18=""),"",$L18-$K18) -> 66.533 | P18: =IF(OR(O18="",K18=""),"",K18*O18) | Q18: =IF(OR(O18="",L18=""),"",L18*O18)
A19: Clothing | B19: Outerwear | C19: Jacket | D19: Tailored Biker Sets | F19: Woven Biker Jacket Op1 | I19: Drop 1 - Sep | J19: Trend | K19: 27.755 | L19: 129 | M19: =(L19-K19)/L19 -> 0.78484496 | N19: =IF(OR($L19="",$K19=""),"",$L19-$K19) -> 101.245 | P19: =IF(OR(O19="",K19=""),"",K19*O19) | Q19: =IF(OR(O19="",L19=""),"",L19*O19)
A20: Clothing | B20: Outerwear | C20: Jacket | D20: Tailored Biker Sets | F20: Woven Biker Jacket Op2 | I20: Drop 1 - Sep | J20: Trend | K20: 24.479 | L20: 129 | M20: =(L20-K20)/L20 -> 0.81024031 | N20: =IF(OR($L20="",$K20=""),"",$L20-$K20) -> 104.521 | P20: =IF(OR(O20="",K20=""),"",K20*O20) | Q20: =IF(OR(O20="",L20=""),"",L20*O20)
A21: Clothing | B21: Dresses | D21: Tailored Biker Sets | F21: Front Zip Dress | I21: Drop 1 - Sep | J21: Commercial | K21: 21.203 | L21: 109 | M21: =(L21-K21)/L21 -> 0.80547706 | N21: =IF(OR($L21="",$K21=""),"",$L21-$K21) -> 87.797 | P21: =IF(OR(O21="",K21=""),"",K21*O21) | Q21: =IF(OR(O21="",L21=""),"",L21*O21)
A22: Clothing | B22: Bottoms | C22: Skirt | D22: Tailored Biker Sets | F22: Tailored Flared Skirt | I22: Drop 1 - Sep | J22: Commercial | K22: 18.018 | L22: 74 | M22: =(L22-K22)/L22 -> 0.75651351 | N22: =IF(OR($L22="",$K22=""),"",$L22-$K22) -> 55.982 | P22: =IF(OR(O22="",K22=""),"",K22*O22) | Q22: =IF(OR(O22="",L22=""),"",L22*O22)
A23: Clothing | B23: Bottoms | C23: Pants | D23: Tailored Biker Sets | F23: Relaxed Fit Trousers | I23: Drop 1 - Sep | J23: Commercial | K23: 14.469 | L23: 74 | M23: =(L23-K23)/L23 -> 0.80447297 | N23: =IF(OR($L23="",$K23=""),"",$L23-$K23) -> 59.531 | P23: =IF(OR(O23="",K23=""),"",K23*O23) | Q23: =IF(OR(O23="",L23=""),"",L23*O23)
A24: Clothing | B24: Outerwear | C24: Jacket | D24: Tailored Biker Sets | F24: Woven Biker Jacket | I24: Drop 1 - Sep | J24: Trend | K24: 18.6641 | L24: 129 | M24: =(L24-K24)/L24 -> 0.85531705 | N24: =IF(OR($L24="",$K24=""),"",$L24-$K24) -> 110.3359 | P24: =IF(OR(O24="",K24=""),"",K24*O24) | Q24: =IF(OR(O24="",L24=""),"",L24*O24)
A25: Clothing | B25: Dresses | D25: Tailored Biker Sets | F25: Front Zip Dress | I25: Drop 1 - Sep | J25: Commercial | K25: 16.8896 | L25: 109 | M25: =(L25-K25)/L25 -> 0.84504954 | N25: =IF(OR($L25="",$K25=""),"",$L25-$K25) -> 92.1104 | P25: =IF(OR(O25="",K25=""),"",K25*O25) | Q25: =IF(OR(O25="",L25=""),"",L25*O25)
A26: Clothing | B26: Bottoms | C26: Skirt | D26: Tailored Biker Sets | F26: Tailored Flared Skirt | I26: Drop 1 - Sep | J26: Commercial | K26: 13.4225 | L26: 74 | M26: =(L26-K26)/L26 -> 0.81861486 | N26: =IF(OR($L26="",$K26=""),"",$L26-$K26) -> 60.5775 | P26: =IF(OR(O26="",K26=""),"",K26*O26) | Q26: =IF(OR(O26="",L26=""),"",L26*O26)
A27: Clothing | B27: Bottoms | C27: Pants | D27: Tailored Biker Sets | F27: Relaxed Fit Trousers | I27: Drop 1 - Sep | J27: Commercial | K27: 11.3568 | L27: 74 | M27: =(L27-K27)/L27 -> 0.84652973 | N27: =IF(OR($L27="",$K27=""),"",$L27-$K27) -> 62.6432 | P27: =IF(OR(O27="",K27=""),"",K27*O27) | Q27: =IF(OR(O27="",L27=""),"",L27*O27)
A28: Clothing | B28: Outerwear | C28: Jacket | D28: Tweed | F28: Tweed Bomber Jacket | I28: Drop 1 - Sep | J28: Commercial | K28: 27.755 | L28: 129 | M28: =(L28-K28)/L28 -> 0.78484496 | N28: =IF(OR($L28="",$K28=""),"",$L28-$K28) -> 101.245 | P28: =IF(OR(O28="",K28=""),"",K28*O28) | Q28: =IF(OR(O28="",L28=""),"",L28*O28)
A29: Clothing | B29: Dresses | D29: Tweed | F29: Tweed Volume Dress | I29: Drop 1 - Sep | J29: Commercial | K29: 16.289 | L29: 109 | M29: =(L29-K29)/L29 -> 0.85055963 | N29: =IF(OR($L29="",$K29=""),"",$L29-$K29) -> 92.711 | P29: =IF(OR(O29="",K29=""),"",K29*O29) | Q29: =IF(OR(O29="",L29=""),"",L29*O29)
A30: Clothing | B30: Bottoms | C30: Skirt | D30: Tweed | F30: Tweed Skirt Opt1 | I30: Drop 1 - Sep | J30: Commercial | K30: 16.926 | L30: 74 | M30: =(L30-K30)/L30 -> 0.77127027 | N30: =IF(OR($L30="",$K30=""),"",$L30-$K30) -> 57.074 | P30: =IF(OR(O30="",K30=""),"",K30*O30) | Q30: =IF(OR(O30="",L30=""),"",L30*O30)
A31: Clothing | B31: Bottoms | C31: Skirt | D31: Tweed | F31: Tweed Skirt Opt2 | I31: Drop 1 - Sep | J31: Commercial | K31: 27.209 | L31: 74 | M31: =(L31-K31)/L31 -> 0.63231081 | N31: =IF(OR($L31="",$K31=""),"",$L31-$K31) -> 46.791 | P31: =IF(OR(O31="",K31=""),"",K31*O31) | Q31: =IF(OR(O31="",L31=""),"",L31*O31)
A32: Clothing | B32: Outerwear | C32: Jacket | D32: Tweed | F32: Tweed Bomber Jacket | I32: Drop 1 - Sep | J32: Trend | K32: 23.023 | L32: 129 | M32: =(L32-K32)/L32 -> 0.82152713 | N32: =IF(OR($L32="",$K32=""),"",$L32-$K32) -> 105.977 | P32: =IF(OR(O32="",K32=""),"",K32*O32) | Q32: =IF(OR(O32="",L32=""),"",L32*O32)
A33: Clothing | B33: Bottoms | C33: Skirt | D33: Tweed | F33: Tweed Skirt | I33: Drop 1 - Sep | J33: Trend | K33: 15.925 | L33: 74 | M33: =(L33-K33)/L33 -> 0.7847973 | N33: =IF(OR($L33="",$K33=""),"",$L33-$K33) -> 58.075 | P33: =IF(OR(O33="",K33=""),"",K33*O33) | Q33: =IF(OR(O33="",L33=""),"",L33*O33)
A34: Clothing | B34: Bottoms | C34: Skirt | D34: Tweed | F34: Tweed Skirt Opt2 | I34: Drop 1 - Sep | J34: Trend | K34: 15.925 | L34: 74 | M34: =(L34-K34)/L34 -> 0.7847973 | N34: =IF(OR($L34="",$K34=""),"",$L34-$K34) -> 58.075 | P34: =IF(OR(O34="",K34=""),"",K34*O34) | Q34: =IF(OR(O34="",L34=""),"",L34*O34)
A35: Clothing | B35: Dresses | D35: Tweed | F35: Tweed Volume Dress | I35: Drop 1 - Sep | K35: 31.85 | L35: 109 | M35: =(L35-K35)/L35 -> 0.70779817 | N35: =IF(OR($L35="",$K35=""),"",$L35-$K35) -> 77.15 | P35: =IF(OR(O35="",K35=""),"",K35*O35) | Q35: =IF(OR(O35="",L35=""),"",L35*O35)
A36: Clothing | B36: Dresses | D36: Draped Knit | F36: Draped Knit Dress | I36: Drop 1 - Sep | K36: 19.565 | L36: 109 | M36: =(L36-K36)/L36 -> 0.82050459 | N36: =IF(OR($L36="",$K36=""),"",$L36-$K36) -> 89.435 | P36: =IF(OR(O36="",K36=""),"",K36*O36) | Q36: =IF(OR(O36="",L36=""),"",L36*O36)
A37: Clothing | B37: Tops | D37: Draped Knit | F37: Draped Layered Top | I37: Drop 1 - Sep | K37: 12.649 | L37: 79 | M37: =(L37-K37)/L37 -> 0.83988608 | N37: =IF(OR($L37="",$K37=""),"",$L37-$K37) -> 66.351 | P37: =IF(OR(O37="",K37=""),"",K37*O37) | Q37: =IF(OR(O37="",L37=""),"",L37*O37)
A38: Clothing | B38: Bottoms | C38: Skirt | D38: Draped Knit | F38: Maxi Flared Skirt | I38: Drop 1 - Sep | K38: 10.92 | L38: 69 | M38: =(L38-K38)/L38 -> 0.84173913 | N38: =IF(OR($L38="",$K38=""),"",$L38-$K38) -> 58.08 | P38: =IF(OR(O38="",K38=""),"",K38*O38) | Q38: =IF(OR(O38="",L38=""),"",L38*O38)
A39: Accessories | B39: Acessories | C39: Hijab | D39: Draped Knit | F39: Knitted Hijab | I39: Drop 1 - Sep | K39: 4.6501 | L39: 29 | M39: =(L39-K39)/L39 -> 0.83965172 | N39: =IF(OR($L39="",$K39=""),"",$L39-$K39) -> 24.3499 | P39: =IF(OR(O39="",K39=""),"",K39*O39) | Q39: =IF(OR(O39="",L39=""),"",L39*O39)
A40: Clothing | B40: Outerwear | C40: Blazer | D40: Signature Tailoring | F40: Loose Fit Blazer | I40: Drop 1 - Sep | K40: 27.755 | L40: 109 | M40: =(L40-K40)/L40 -> 0.74536697 | N40: =IF(OR($L40="",$K40=""),"",$L40-$K40) -> 81.245 | P40: =IF(OR(O40="",K40=""),"",K40*O40) | Q40: =IF(OR(O40="",L40=""),"",L40*O40)
A41: Clothing | B41: Bottoms | C41: Skirt | D41: Signature Tailoring | F41: Tailored Volume Skirt | I41: Drop 1 - Sep | K41: 14.105 | L41: 74 | M41: =(L41-K41)/L41 -> 0.80939189 | N41: =IF(OR($L41="",$K41=""),"",$L41-$K41) -> 59.895 | P41: =IF(OR(O41="",K41=""),"",K41*O41) | Q41: =IF(OR(O41="",L41=""),"",L41*O41)
A42: Clothing | B42: Outerwear | C42: Poncho | D42: Signature Tailoring | F42: High Neck Asymmetric Ponch | I42: Drop 1 - Sep | K42: 15.925 | L42: 74 | M42: =(L42-K42)/L42 -> 0.7847973 | N42: =IF(OR($L42="",$K42=""),"",$L42-$K42) -> 58.075 | P42: =IF(OR(O42="",K42=""),"",K42*O42) | Q42: =IF(OR(O42="",L42=""),"",L42*O42)
A43: Clothing | B43: Outerwear | C43: Poncho | D43: Signature Tailoring | F43: High Neck Ponch | I43: Drop 1 - Sep | K43: 23.205 | L43: 74 | M43: =(L43-K43)/L43 -> 0.68641892 | N43: =IF(OR($L43="",$K43=""),"",$L43-$K43) -> 50.795 | P43: =IF(OR(O43="",K43=""),"",K43*O43) | Q43: =IF(OR(O43="",L43=""),"",L43*O43)
A44: Clothing | B44: Outerwear | C44: Poncho | D44: Signature Tailoring | F44: High Neck Asymmetric Ponch 2 add side seam | I44: Drop 1 - Sep | K44: 20.475 | L44: 74 | M44: =(L44-K44)/L44 -> 0.72331081 | N44: =IF(OR($L44="",$K44=""),"",$L44-$K44) -> 53.525 | P44: =IF(OR(O44="",K44=""),"",K44*O44) | Q44: =IF(OR(O44="",L44=""),"",L44*O44)
A45: Clothing | B45: Outerwear | C45: Poncho | D45: Signature Tailoring | F45: High Neck Asymmetric Ponch 3 keep length same for all sizes | I45: Drop 1 - Sep | K45: 16.289 | L45: 74 | M45: =(L45-K45)/L45 -> 0.77987838 | N45: =IF(OR($L45="",$K45=""),"",$L45-$K45) -> 57.711 | P45: =IF(OR(O45="",K45=""),"",K45*O45) | Q45: =IF(OR(O45="",L45=""),"",L45*O45)
A46: Clothing | B46: Outerwear | C46: Trench | D46: Trench | F46: Cape Trench - poly | I46: Drop 1 - Sep | K46: 30.667 | L46: 159 | M46: =(L46-K46)/L46 -> 0.80712579 | N46: =IF(OR($L46="",$K46=""),"",$L46-$K46) -> 128.333 | P46: =IF(OR(O46="",K46=""),"",K46*O46) | Q46: =IF(OR(O46="",L46=""),"",L46*O46)
A47: Clothing | B47: Outerwear | C47: Trench | D47: Trench | F47: Cape Trench - cotton | I47: Drop 1 - Sep | K47: 38.22 | L47: 159 | M47: =(L47-K47)/L47 -> 0.75962264 | N47: =IF(OR($L47="",$K47=""),"",$L47-$K47) -> 120.78 | P47: =IF(OR(O47="",K47=""),"",K47*O47) | Q47: =IF(OR(O47="",L47=""),"",L47*O47)
A48: Clothing | B48: Tops | D48: Twill Tailoring | F48: Draped Layered Twill Top | I48: Drop 1 - Sep | K48: 13.832 | L48: 74 | M48: =(L48-K48)/L48 -> 0.81308108 | N48: =IF(OR($L48="",$K48=""),"",$L48-$K48) -> 60.168 | P48: =IF(OR(O48="",K48=""),"",K48*O48) | Q48: =IF(OR(O48="",L48=""),"",L48*O48)
A49: Clothing | B49: Bottoms | C49: Skirt | D49: Twill Tailoring | F49: Tailored Flared Shirt | I49: Drop 1 - Sep | K49: 13.286 | L49: 79 | M49: =(L49-K49)/L49 -> 0.83182278 | N49: =IF(OR($L49="",$K49=""),"",$L49-$K49) -> 65.714 | P49: =IF(OR(O49="",K49=""),"",K49*O49) | Q49: =IF(OR(O49="",L49=""),"",L49*O49)
A50: Clothing | B50: Bottoms | C50: Skirt | D50: Twill Tailoring | F50: Maxi Flared Twill Skirt | I50: Drop 1 - Sep | K50: 10.738 | L50: 69 | M50: =(L50-K50)/L50 -> 0.84437681 | N50: =IF(OR($L50="",$K50=""),"",$L50-$K50) -> 58.262 | P50: =IF(OR(O50="",K50=""),"",K50*O50) | Q50: =IF(OR(O50="",L50=""),"",L50*O50)
A51: Clothing | B51: Bottoms | C51: Pants | D51: Twill Tailoring | F51: Straight Fit Tailored Pants | I51: Drop 1 - Sep | K51: 13.832 | L51: 74 | M51: =(L51-K51)/L51 -> 0.81308108 | N51: =IF(OR($L51="",$K51=""),"",$L51-$K51) -> 60.168 | P51: =IF(OR(O51="",K51=""),"",K51*O51) | Q51: =IF(OR(O51="",L51=""),"",L51*O51)
A52: Clothing | B52: Dresses | D52: Twill Tailoring | F52: Front Zip Dress | I52: Drop 1 - Sep | K52: 19.838 | L52: 109 | M52: =(L52-K52)/L52 -> 0.818 | N52: =IF(OR($L52="",$K52=""),"",$L52-$K52) -> 89.162 | P52: =IF(OR(O52="",K52=""),"",K52*O52) | Q52: =IF(OR(O52="",L52=""),"",L52*O52)
A53: Clothing | B53: Outerwear | C53: Jacket | D53: Windbreaker | F53: Windbreaker Jacket without lining | I53: Drop 1 - Sep | J53: Commercial | K53: 16.289 | L53: 98 | M53: =(L53-K53)/L53 -> 0.83378571 | N53: =IF(OR($L53="",$K53=""),"",$L53-$K53) -> 81.711 | P53: =IF(OR(O53="",K53=""),"",K53*O53) | Q53: =IF(OR(O53="",L53=""),"",L53*O53)
A54: Clothing | B54: Outerwear | C54: Jacket | D54: Windbreaker | F54: Windbreaker Jacket | I54: Drop 1 - Sep | J54: Commercial | K54: 20.475 | L54: 98 | M54: =(L54-K54)/L54 -> 0.79107143 | N54: =IF(OR($L54="",$K54=""),"",$L54-$K54) -> 77.525 | P54: =IF(OR(O54="",K54=""),"",K54*O54) | Q54: =IF(OR(O54="",L54=""),"",L54*O54)
A55: Clothing | B55: Bottoms | C55: Skirt | D55: Windbreaker | F55: Windbreaker Skirt without lining | I55: Drop 1 - Sep | J55: Commercial | K55: 11.648 | L55: 69 | M55: =(L55-K55)/L55 -> 0.83118841 | N55: =IF(OR($L55="",$K55=""),"",$L55-$K55) -> 57.352 | P55: =IF(OR(O55="",K55=""),"",K55*O55) | Q55: =IF(OR(O55="",L55=""),"",L55*O55)
A56: Clothing | B56: Bottoms | C56: Skirt | D56: Windbreaker | F56: Windbreaker Skirt | I56: Drop 1 - Sep | J56: Commercial | K56: 14.469 | L56: 69 | M56: =(L56-K56)/L56 -> 0.79030435 | N56: =IF(OR($L56="",$K56=""),"",$L56-$K56) -> 54.531 | P56: =IF(OR(O56="",K56=""),"",K56*O56) | Q56: =IF(OR(O56="",L56=""),"",L56*O56)
A57: Clothing | B57: Outerwear | C57: Blazer | D57: Wrap Belt | F57: Wrap Belt Blazer | I57: Drop 1 - Sep | K57: 16.562 | L57: 109 | M57: =(L57-K57)/L57 -> 0.84805505 | N57: =IF(OR($L57="",$K57=""),"",$L57-$K57) -> 92.438 | P57: =IF(OR(O57="",K57=""),"",K57*O57) | Q57: =IF(OR(O57="",L57=""),"",L57*O57)
A58: Clothing | B58: Dresses | D58: Wrap Belt | F58: Wrap Belt Dress Opt1 | I58: Drop 1 - Sep | K58: 21.6944 | L58: 129 | M58: =(L58-K58)/L58 -> 0.83182636 | N58: =IF(OR($L58="",$K58=""),"",$L58-$K58) -> 107.3056 | P58: =IF(OR(O58="",K58=""),"",K58*O58) | Q58: =IF(OR(O58="",L58=""),"",L58*O58)
A59: Clothing | B59: Dresses | D59: Wrap Belt | F59: Wrap Belt Dress Opt2 | I59: Drop 1 - Sep | K59: 21.203 | L59: 129 | M59: =(L59-K59)/L59 -> 0.83563566 | N59: =IF(OR($L59="",$K59=""),"",$L59-$K59) -> 107.797 | P59: =IF(OR(O59="",K59=""),"",K59*O59) | Q59: =IF(OR(O59="",L59=""),"",L59*O59)
A60: Clothing | B60: Bottoms | C60: Pants | D60: Wrap Belt | F60: Wide Legged Tailored Trousers Opt1 | I60: Drop 1 - Sep | K60: 11.9483 | L60: 79 | M60: =(L60-K60)/L60 -> 0.8487557 | N60: =IF(OR($L60="",$K60=""),"",$L60-$K60) -> 67.0517 | P60: =IF(OR(O60="",K60=""),"",K60*O60) | Q60: =IF(OR(O60="",L60=""),"",L60*O60)
A61: Clothing | B61: Bottoms | C61: Pants | D61: Wrap Belt | F61: Wide Legged Tailored Trousers Opt2 | I61: Drop 1 - Sep | K61: 11.8118 | L61: 79 | M61: =(L61-K61)/L61 -> 0.85048354 | N61: =IF(OR($L61="",$K61=""),"",$L61-$K61) -> 67.1882 | P61: =IF(OR(O61="",K61=""),"",K61*O61) | Q61: =IF(OR(O61="",L61=""),"",L61*O61)
A62: Headwear | B62: Scarves | C62: Premium | D62: Premium Jersey | F62: Premium Jersey Scarf | I62: Drop 1 - Sep | K62: 3.4307 | L62: 25 | M62: =(L62-K62)/L62 -> 0.862772 | N62: =IF(OR($L62="",$K62=""),"",$L62-$K62) -> 21.5693 | P62: =IF(OR(O62="",K62=""),"",K62*O62) | Q62: =IF(OR(O62="",L62=""),"",L62*O62)
A63: Headwear | B63: Scarves | C63: Premium | D63: Premium Jersey | F63: Premium Jersey Scarf | I63: Drop 1 - Sep | K63: 3.4307 | L63: 25 | M63: =(L63-K63)/L63 -> 0.862772 | N63: =IF(OR($L63="",$K63=""),"",$L63-$K63) -> 21.5693 | P63: =IF(OR(O63="",K63=""),"",K63*O63) | Q63: =IF(OR(O63="",L63=""),"",L63*O63)
A64: Headwear | B64: Scarves | C64: Premium | D64: Premium Jersey | F64: Premium Jersey Scarf | I64: Drop 1 - Sep | K64: 3.4307 | L64: 25 | M64: =(L64-K64)/L64 -> 0.862772 | N64: =IF(OR($L64="",$K64=""),"",$L64-$K64) -> 21.5693 | P64: =IF(OR(O64="",K64=""),"",K64*O64) | Q64: =IF(OR(O64="",L64=""),"",L64*O64)
A65: Headwear | B65: Scarves | C65: Premium | D65: Premium Jersey | F65: Premium Jersey Scarf | I65: Drop 1 - Sep | K65: 3.4307 | L65: 25 | M65: =(L65-K65)/L65 -> 0.862772 | N65: =IF(OR($L65="",$K65=""),"",$L65-$K65) -> 21.5693 | P65: =IF(OR(O65="",K65=""),"",K65*O65) | Q65: =IF(OR(O65="",L65=""),"",L65*O65)
A66: Headwear | B66: Scarves | C66: Premium | D66: Premium Jersey | F66: Premium Jersey Scarf | I66: Drop 1 - Sep | K66: 3.4307 | L66: 25 | M66: =(L66-K66)/L66 -> 0.862772 | N66: =IF(OR($L66="",$K66=""),"",$L66-$K66) -> 21.5693 | P66: =IF(OR(O66="",K66=""),"",K66*O66) | Q66: =IF(OR(O66="",L66=""),"",L66*O66)
A67: Headwear | B67: Scarves | C67: Premium | D67: Premium Jersey | F67: Premium Jersey Scarf | I67: Drop 1 - Sep | K67: 3.4307 | L67: 25 | M67: =(L67-K67)/L67 -> 0.862772 | N67: =IF(OR($L67="",$K67=""),"",$L67-$K67) -> 21.5693 | P67: =IF(OR(O67="",K67=""),"",K67*O67) | Q67: =IF(OR(O67="",L67=""),"",L67*O67)
A68: Headwear | B68: Scarves | C68: Premium | D68: Premium Jersey | F68: Premium Jersey Scarf | I68: Drop 1 - Sep | K68: 3.4307 | L68: 25 | M68: =(L68-K68)/L68 -> 0.862772 | N68: =IF(OR($L68="",$K68=""),"",$L68-$K68) -> 21.5693 | P68: =IF(OR(O68="",K68=""),"",K68*O68) | Q68: =IF(OR(O68="",L68=""),"",L68*O68)
A69: Headwear | B69: Scarves | C69: Premium | D69: Premium Jersey | F69: Premium Jersey Scarf | I69: Drop 1 - Sep | K69: 3.4307 | L69: 25 | M69: =(L69-K69)/L69 -> 0.862772 | N69: =IF(OR($L69="",$K69=""),"",$L69-$K69) -> 21.5693 | P69: =IF(OR(O69="",K69=""),"",K69*O69) | Q69: =IF(OR(O69="",L69=""),"",L69*O69)
A70: Headwear | B70: Scarves | C70: Premium | D70: Premium Jersey | F70: Premium Jersey Scarf | I70: Drop 1 - Sep | K70: 3.4307 | L70: 25 | M70: =(L70-K70)/L70 -> 0.862772 | N70: =IF(OR($L70="",$K70=""),"",$L70-$K70) -> 21.5693 | P70: =IF(OR(O70="",K70=""),"",K70*O70) | Q70: =IF(OR(O70="",L70=""),"",L70*O70)
A71: Headwear | B71: Scarves | C71: Premium | D71: Premium Jersey | F71: Premium Jersey Scarf | I71: Drop 1 - Sep | K71: 3.4307 | L71: 25 | M71: =(L71-K71)/L71 -> 0.862772 | N71: =IF(OR($L71="",$K71=""),"",$L71-$K71) -> 21.5693 | P71: =IF(OR(O71="",K71=""),"",K71*O71) | Q71: =IF(OR(O71="",L71=""),"",L71*O71)
... A115: Clothing | B115: Outerwear | C115: Coat | D115: Brushed Wool | F115: Brushed Wool Cocoon Coat | I115: Drop 2 - Oct | K115: 32.2504 | L115: 149 | M115: =(L115-K115)/L115 -> 0.78355436 | N115: =IF(OR($L115="",$K115=""),"",$L115-$K115) -> 116.7496 | P115: =IF(OR(O115="",K115=""),"",K115*O115) | Q115: =IF(OR(O115="",L115=""),"",L115*O115)
A116: Clothing | B116: Dresses | D116: Brushed Wool | F116: Sculpted Wool Dress | I116: Drop 2 - Oct | K116: 28.4375 | L116: 129 | M116: =(L116-K116)/L116 -> 0.77955426 | N116: =IF(OR($L116="",$K116=""),"",$L116-$K116) -> 100.5625 | P116: =IF(OR(O116="",K116=""),"",K116*O116) | Q116: =IF(OR(O116="",L116=""),"",L116*O116)
A117: Clothing | B117: Outerwear | C117: Coat | D117: Brushed Wool | F117: Brushed Wool Cocoon Coat | I117: Drop 2 - Oct | K117: 36.309 | L117: 149 | M117: =(L117-K117)/L117 -> 0.75631544 | N117: =IF(OR($L117="",$K117=""),"",$L117-$K117) -> 112.691 | P117: =IF(OR(O117="",K117=""),"",K117*O117) | Q117: =IF(OR(O117="",L117=""),"",L117*O117)
A118: Clothing | B118: Dresses | D118: Brushed Wool | F118: Sculpted Wool Dress (without lining) | I118: Drop 2 - Oct | K118: 36.3545 | L118: 129 | M118: =(L118-K118)/L118 -> 0.71818217 | N118: =IF(OR($L118="",$K118=""),"",$L118-$K118) -> 92.6455 | P118: =IF(OR(O118="",K118=""),"",K118*O118) | Q118: =IF(OR(O118="",L118=""),"",L118*O118)
A119: Clothing | B119: Outerwear | C119: Cardigan | D119: Cape Cardigan | F119: Cape Cardigan | I119: Drop 2 - Oct | K119: 23.205 | L119: 129 | M119: =(L119-K119)/L119 -> 0.82011628 | N119: =IF(OR($L119="",$K119=""),"",$L119-$K119) -> 105.795 | P119: =IF(OR(O119="",K119=""),"",K119*O119) | Q119: =IF(OR(O119="",L119=""),"",L119*O119)
A120: Clothing | B120: Outerwear | C120: Jacket | D120: Feather Knit | F120: Feather Knit Jacket | I120: Drop 2 - Oct | J120: Trend | K120: 17.108 | L120: 98 | M120: =(L120-K120)/L120 -> 0.82542857 | N120: =IF(OR($L120="",$K120=""),"",$L120-$K120) -> 80.892 | P120: =IF(OR(O120="",K120=""),"",K120*O120) | Q120: =IF(OR(O120="",L120=""),"",L120*O120)
A121: Clothing | B121: Bottoms | C121: Pants | D121: Feather Knit | F121: Feather Knit Pants | I121: Drop 2 - Oct | K121: 16.471 | L121: 79 | M121: =(L121-K121)/L121 -> 0.79150633 | N121: =IF(OR($L121="",$K121=""),"",$L121-$K121) -> 62.529 | P121: =IF(OR(O121="",K121=""),"",K121*O121) | Q121: =IF(OR(O121="",L121=""),"",L121*O121)
A122: Clothing | B122: Outerwear | C122: Jacket | D122: Feather Knit | F122: Feather Knit Jacket | I122: Drop 2 - Oct | K122: 20.02 | L122: 98 | M122: =(L122-K122)/L122 -> 0.79571429 | N122: =IF(OR($L122="",$K122=""),"",$L122-$K122) -> 77.98 | P122: =IF(OR(O122="",K122=""),"",K122*O122) | Q122: =IF(OR(O122="",L122=""),"",L122*O122)
A123: Clothing | B123: Bottoms | C123: Pants | D123: Feather Knit | F123: Feather Knit Pants | I123: Drop 2 - Oct | K123: 15.834 | L123: 79 | M123: =(L123-K123)/L123 -> 0.79956962 | N123: =IF(OR($L123="",$K123=""),"",$L123-$K123) -> 63.166 | P123: =IF(OR(O123="",K123=""),"",K123*O123) | Q123: =IF(OR(O123="",L123=""),"",L123*O123)
A124: Clothing | B124: Outerwear | C124: Cardigan | D124: Fuzzy Knit | F124: Fuzzy Knit Cardigan | I124: Drop 2 - Oct | J124: Trend | K124: 13.468 | L124: 84 | M124: =(L124-K124)/L124 -> 0.83966667 | N124: =IF(OR($L124="",$K124=""),"",$L124-$K124) -> 70.532 | P124: =IF(OR(O124="",K124=""),"",K124*O124) | Q124: =IF(OR(O124="",L124=""),"",L124*O124)
A125: Clothing | B125: Tops | D125: Fuzzy Knit | F125: Fuzzy Knit Sweater | I125: Drop 2 - Oct | J125: Trend | K125: 13.195 | L125: 89 | M125: =(L125-K125)/L125 -> 0.85174157 | N125: =IF(OR($L125="",$K125=""),"",$L125-$K125) -> 75.805 | P125: =IF(OR(O125="",K125=""),"",K125*O125) | Q125: =IF(OR(O125="",L125=""),"",L125*O125)
A126: Clothing | B126: Bottoms | C126: Pants | D126: Fuzzy Knit | F126: Fuzzy Knit Pants | I126: Drop 2 - Oct | J126: Trend | K126: 12.649 | L126: 74 | M126: =(L126-K126)/L126 -> 0.82906757 | N126: =IF(OR($L126="",$K126=""),"",$L126-$K126) -> 61.351 | P126: =IF(OR(O126="",K126=""),"",K126*O126) | Q126: =IF(OR(O126="",L126=""),"",L126*O126)
A127: Clothing | B127: Bottoms | C127: Skirt | D127: Fuzzy Knit | F127: Fuzzy Knit Skirt | I127: Drop 2 - Oct | J127: Trend | K127: 13.195 | L127: 69 | M127: =(L127-K127)/L127 -> 0.80876812 | N127: =IF(OR($L127="",$K127=""),"",$L127-$K127) -> 55.805 | P127: =IF(OR(O127="",K127=""),"",K127*O127) | Q127: =IF(OR(O127="",L127=""),"",L127*O127)
A128: Clothing | B128: Dresses | D128: Fuzzy Knit | F128: Fuzzy Knit Dress | I128: Drop 2 - Oct | J128: Trend | K128: 17.199 | L128: 99 | M128: =(L128-K128)/L128 -> 0.82627273 | N128: =IF(OR($L128="",$K128=""),"",$L128-$K128) -> 81.801 | P128: =IF(OR(O128="",K128=""),"",K128*O128) | Q128: =IF(OR(O128="",L128=""),"",L128*O128)
A129: Accessories | B129: Acessories | C129: Scarf | D129: Fuzzy Knit | F129: Fuzzy Knit Scarf | I129: Drop 2 - Oct | J129: Trend | K129: 5.915 | L129: 39 | M129: =(L129-K129)/L129 -> 0.84833333 | N129: =IF(OR($L129="",$K129=""),"",$L129-$K129) -> 33.085 | P129: =IF(OR(O129="",K129=""),"",K129*O129) | Q129: =IF(OR(O129="",L129=""),"",L129*O129)
A130: Clothing | B130: Outerwear | C130: Cape | D130: Heavy Rib Knit | F130: Funnel Neck Knit Cape | I130: Drop 2 - Oct | J130: Commercial | K130: 6.825 | L130: 69 | M130: =(L130-K130)/L130 -> 0.90108696 | N130: =IF(OR($L130="",$K130=""),"",$L130-$K130) -> 62.175 | P130: =IF(OR(O130="",K130=""),"",K130*O130) | Q130: =IF(OR(O130="",L130=""),"",L130*O130)
A131: Clothing | B131: Dresses | D131: Heavy Rib Knit | F131: Heavy Rib Knit Dress | I131: Drop 2 - Oct | J131: Commercial | K131: 16.38 | L131: 104 | M131: =(L131-K131)/L131 -> 0.8425 | N131: =IF(OR($L131="",$K131=""),"",$L131-$K131) -> 87.62 | P131: =IF(OR(O131="",K131=""),"",K131*O131) | Q131: =IF(OR(O131="",L131=""),"",L131*O131)
A132: Clothing | B132: Tops | C132: Sweater | D132: Heavy Rib Knit | F132: Heavy Rib Knit Sweater | I132: Drop 2 - Oct | J132: Commercial | K132: 11.375 | L132: 89 | M132: =(L132-K132)/L132 -> 0.87219101 | N132: =IF(OR($L132="",$K132=""),"",$L132-$K132) -> 77.625 | P132: =IF(OR(O132="",K132=""),"",K132*O132) | Q132: =IF(OR(O132="",L132=""),"",L132*O132)
A133: Clothing | B133: Bottoms | C133: Pants | D133: Heavy Rib Knit | F133: Loose Fit Knit Pants | I133: Drop 2 - Oct | J133: Commercial | K133: 11.193 | L133: 74 | M133: =(L133-K133)/L133 -> 0.84874324 | N133: =IF(OR($L133="",$K133=""),"",$L133-$K133) -> 62.807 | P133: =IF(OR(O133="",K133=""),"",K133*O133) | Q133: =IF(OR(O133="",L133=""),"",L133*O133)
A134: Clothing | B134: Outerwear | C134: Blazer | D134: Herrinbone Weave New | F134: Asymmetric Sculpted Blazer | I134: Drop 2 - Oct | K134: 20.475 | L134: 109 | M134: =(L134-K134)/L134 -> 0.81215596 | N134: =IF(OR($L134="",$K134=""),"",$L134-$K134) -> 88.525 | P134: =IF(OR(O134="",K134=""),"",K134*O134) | Q134: =IF(OR(O134="",L134=""),"",L134*O134)
A135: Clothing | B135: Dresses | D135: Herrinbone Weave New | F135: Herringbone Weave Tailored Dress | I135: Drop 2 - Oct | K135: 26.299 | L135: 129 | M135: =(L135-K135)/L135 -> 0.79613178 | N135: =IF(OR($L135="",$K135=""),"",$L135-$K135) -> 102.701 | P135: =IF(OR(O135="",K135=""),"",K135*O135) | Q135: =IF(OR(O135="",L135=""),"",L135*O135)
A136: Clothing | B136: Bottoms | C136: Pants | D136: Herrinbone Weave New | F136: Herringbone Weave Tapered Pants | I136: Drop 2 - Oct | K136: 14.469 | L136: 74 | M136: =(L136-K136)/L136 -> 0.80447297 | N136: =IF(OR($L136="",$K136=""),"",$L136-$K136) -> 59.531 | P136: =IF(OR(O136="",K136=""),"",K136*O136) | Q136: =IF(OR(O136="",L136=""),"",L136*O136)
A137: Clothing | B137: Bottoms | C137: Pants | D137: Herrinbone Weave New | F137: Herringbone Weave Flared Pants | I137: Drop 2 - Oct | K137: 14.469 | L137: 74 | M137: =(L137-K137)/L137 -> 0.80447297 | N137: =IF(OR($L137="",$K137=""),"",$L137-$K137) -> 59.531 | P137: =IF(OR(O137="",K137=""),"",K137*O137) | Q137: =IF(OR(O137="",L137=""),"",L137*O137)
A138: Clothing | B138: Outerwear | C138: Coat | D138: Puffer | F138: Puffer Wrap Coat - same padding | I138: Drop 2 - Oct | J138: Trend | K138: 34.125 | L138: 210 | M138: =(L138-K138)/L138 -> 0.8375 | N138: =IF(OR($L138="",$K138=""),"",$L138-$K138) -> 175.875 | P138: =IF(OR(O138="",K138=""),"",K138*O138) | Q138: =IF(OR(O138="",L138=""),"",L138*O138)
A139: Clothing | B139: Outerwear | C139: Coat | D139: Puffer | F139: Puffer Wrap Coat - half padding | I139: Drop 2 - Oct | J139: Trend | K139: 32.214 | L139: 210 | M139: =(L139-K139)/L139 -> 0.8466 | N139: =IF(OR($L139="",$K139=""),"",$L139-$K139) -> 177.786 | P139: =IF(OR(O139="",K139=""),"",K139*O139) | Q139: =IF(OR(O139="",L139=""),"",L139*O139)
A140: Accessories | B140: Acessories | C140: Scarf | D140: Puffer | F140: Puffer Scarf Opt 1 | I140: Drop 2 - Oct | K140: 13.286 | L140: 39 | M140: =(L140-K140)/L140 -> 0.65933333 | N140: =IF(OR($L140="",$K140=""),"",$L140-$K140) -> 25.714 | P140: =IF(OR(O140="",K140=""),"",K140*O140) | Q140: =IF(OR(O140="",L140=""),"",L140*O140)
A141: Accessories | B141: Acessories | C141: Scarf | D141: Puffer | F141: Puffer Scarf Opt 2 | I141: Drop 2 - Oct | K141: 12.649 | L141: 39 | M141: =(L141-K141)/L141 -> 0.67566667 | N141: =IF(OR($L141="",$K141=""),"",$L141-$K141) -> 26.351 | P141: =IF(OR(O141="",K141=""),"",K141*O141) | Q141: =IF(OR(O141="",L141=""),"",L141*O141)
A142: Accessories | B142: Acessories | C142: Scarf | D142: Puffer | F142: Puffer Scarf Opt 3 | I142: Drop 2 - Oct | K142: 13.195 | L142: 39 | M142: =(L142-K142)/L142 -> 0.66166667 | N142: =IF(OR($L142="",$K142=""),"",$L142-$K142) -> 25.805 | P142: =IF(OR(O142="",K142=""),"",K142*O142) | Q142: =IF(OR(O142="",L142=""),"",L142*O142)
A143: Clothing | B143: Outerwear | C143: Coat | D143: Puffer | F143: Puffer Wrap Coat Fabric Opt 1 | I143: Drop 2 - Oct | K143: 32.0775 | L143: 210 | M143: =(L143-K143)/L143 -> 0.84725 | N143: =IF(OR($L143="",$K143=""),"",$L143-$K143) -> 177.9225 | P143: =IF(OR(O143="",K143=""),"",K143*O143) | Q143: =IF(OR(O143="",L143=""),"",L143*O143)
A144: Clothing | B144: Outerwear | C144: Coat | D144: Puffer | F144: Puffer Wrap Coat Fabric Opt 2 | I144: Drop 2 - Oct | K144: 35.8085 | L144: 210 | M144: =(L144-K144)/L144 -> 0.82948333 | N144: =IF(OR($L144="",$K144=""),"",$L144-$K144) -> 174.1915 | P144: =IF(OR(O144="",K144=""),"",K144*O144) | Q144: =IF(OR(O144="",L144=""),"",L144*O144)
...

Sheet Last Season Data
B1: LAST SEASON — RAW DATA
B2: Paste last season data here. Ensure Main Category/Category/Sub Category match your current structure. Yellow = input.
A4: Drop | B4: Main Category | C4: Category | D4: Sub Category | E4: Fabric Group | F4: SKU | G4: Style Name | H4: Colour Name | I4: Colour Code | J4: Retail Price ($) | K4: Cost Price ($) | L4: Buy Qty | M4: Sales Units | N4: Sales Revenue ($) | O4: Margin %
A5: Drop 1 | B5: Headwear | C5: Scarves | D5: Premium | E5: Premium Jersey | F5: 23-2-FA23-8 | G5: Premium Jersey Scarf | H5: Chocolate | I5: 131 | J5: 25 | K5: 3.77 | L5: 3000 | M5: 2593 | N5: 61089.31 | O5: =IF(OR(N5="",N5=0),"",(N5-(K5*M5))/N5) -> 0.83997839
A6: Drop 1 | B6: Headwear | C6: Scarves | D6: Premium | E6: Premium Jersey | F6: 23-2-FA23-8 | G6: Premium Jersey Scarf | H6: Ash Brown | I6: 469 | J6: 25 | K6: 3.77 | L6: 3000 | M6: 2311 | N6: 54879.86 | O6: =IF(OR(N6="",N6=0),"",(N6-(K6*M6))/N6) -> 0.84124468
A7: Drop 1 | B7: Clothing | C7: Tops | D7: Sweater | E7: Comfy | F7: 25-2-FA25-5 | G7: Comfy Hoodie | H7: Chocolate | I7: 131 | J7: 79 | K7: 16.9 | L7: 1080 | M7: 623 | N7: 48996.43 | O7: =IF(OR(N7="",N7=0),"",(N7-(K7*M7))/N7) -> 0.78511292
A8: Drop 1 | B8: Clothing | C8: Outerwear | D8: Coat | E8: Double Wool Thick | F8: 25-1-FA25-19 | G8: Wool Blend Abaya | H8: Dark Brown | I8: 162 | J8: 139 | K8: 25 | L8: 360 | M8: 339 | N8: 46449.37 | O8: =IF(OR(N8="",N8=0),"",(N8-(K8*M8))/N8) -> 0.81754327
A9: Drop 1 | B9: Clothing | C9: Outerwear | D9: Bomber | E9: Neoprene | F9: 24-2-FA24-4 | G9: Neoprene Bomber | H9: Dark Cherry | I9: 439 | J9: 99 | K9: 19.5 | L9: 624 | M9: 455 | N9: 44753.52 | O9: =IF(OR(N9="",N9=0),"",(N9-(K9*M9))/N9) -> 0.80174744
A10: Drop 1 | B10: Clothing | C10: Outerwear | D10: Blazer | E10: Fall Tailoring | F10: 25-1-FA25-4 | G10: Tailored Oversized Blazer | H10: Dark Brown | I10: 162 | J10: 109 | K10: 17.5 | L10: 504 | M10: 386 | N10: 41770.58 | O10: =IF(OR(N10="",N10=0),"",(N10-(K10*M10))/N10) -> 0.83828331
A11: Drop 1 | B11: Headwear | C11: Scarves | D11: Liquid | E11: Liquid Jersey | F11: 24-2-SU24-6 | G11: Liquid Jersey Scarf | H11: Dark Brown | I11: 162 | J11: 25 | K11: 3.63 | L11: 1800 | M11: 1810 | N11: 41357.95 | O11: =IF(OR(N11="",N11=0),"",(N11-(K11*M11))/N11) -> 0.84113574
A12: Drop 1 | B12: Clothing | C12: Outerwear | D12: Coat | E12: Classic Soft Tailoring | F12: 25-1-FA25-11 | G12: Trench Abaya | H12: Dark Brown | I12: 162 | J12: 149 | K12: 28 | L12: 300 | M12: 274 | N12: 40695.6 | O12: =IF(OR(N12="",N12=0),"",(N12-(K12*M12))/N12) -> 0.81147839
A13: Drop 1 | B13: Clothing | C13: Outerwear | D13: Bomber | E13: Neoprene | F13: 24-2-FA24-4 | G13: Neoprene Bomber | H13: Black | I13: 100 | J13: 99 | K13: 19.5 | L13: 624 | M13: 410 | N13: 40604.97 | O13: =IF(OR(N13="",N13=0),"",(N13-(K13*M13))/N13) -> 0.80310292
A14: Drop 1 | B14: Clothing | C14: Dresses | D14: Casual | E14: Rib Knit | F14: 25-3-FA25-10 | G14: Ribbed Knit Dress | H14: Khaki | I14: 374 | J14: 129 | K14: 13.5 | L14: 528 | M14: 313 | N14: 40390.47 | O14: =IF(OR(N14="",N14=0),"",(N14-(K14*M14))/N14) -> 0.89538374
A15: Drop 1 | B15: Headwear | C15: Scarves | D15: Premium | E15: Premium Jersey | F15: 23-2-FA23-8 | G15: Premium Jersey Scarf | H15: Marron | I15: 452 | J15: 25 | K15: 3.77 | L15: 3000 | M15: 1609 | N15: 38503.2 | O15: =IF(OR(N15="",N15=0),"",(N15-(K15*M15))/N15) -> 0.84245647
A16: Drop 1 | B16: Clothing | C16: Dresses | D16: Essential | E16: Textured Jersey | F16: 23-2-FA23-12 | G16: Essential Jersey Dress Regular | H16: Dark Brown | I16: 162 | J16: 89 | K16: 10.11 | L16: 700 | M16: 422 | N16: 37041.11 | O16: =IF(OR(N16="",N16=0),"",(N16-(K16*M16))/N16) -> 0.88481933
... A561: Drop 2 | B561: Clothing | C561: Bottoms | D561: Pants | E561: Cotton | F561: 25-2-FA25-18 | G561: The Casual Pants | H561: Black | I561: 100 | J561: 69 | K561: 13.3 | L561: 0 | M561: 0 | N561: 0 | O561: =IF(OR(N561="",N561=0),"",(N561-(K561*M561))/N561)
L562: =SUM(L3:L561) -> 375718 | M562: =SUM(M3:M561) -> 75457 | N562: =SUM(N3:N561) -> 3495803.6

Sheet Sheet1
A1: Main Category | B1: Category | C1: Sub Category | D1: Total Sales U | E1: Total Rev | F1: U Mix % | G1: Sales Mix % | H1: U Buy Mix %
A2: Accessories | B2: Accessories | C2: Bags | D2: 264 | E2: 17724.92 | F2: 0.0034986814 | G2: 0.0050703421 | H2: 0.0063877696
A3: Accessories | B3: Accessories | C3: Balaclava | D3: 212 | E3: 7984.41 | F3: 0.0028095472 | G3: 0.0022839984 | H3: 0.0017300209
A4: Accessories | B4: Accessories | C4: Gloves | D4: 167 | E4: 6318 | F4: 0.002213181 | G4: 0.0018073098 | H4: 0.0017300209
A5: Accessories | B5: Accessories | C5: Hijab Pins | D5: 345 | E5: 6295.66 | F5: 0.0045721404 | G5: 0.0018009193 | H5: 0.0053231413
A6: Accessories | B6: Accessories | C6: Scarf | D6: 691 | E6: 39389.62 | F6: 0.0091575334 | G6: 0.011267687 | H6: 0.010992287
A7: Accessories | B7: Accessories | C7: Tote Bags | D7: 1409 | E7: 44310.47 | F7: 0.018672887 | G7: 0.012675332 | H7: 0.017832523
A8: Accessories | B8: Accessories Total | D8: 3088 | E8: 122023.08 | F8: 0.04092397 | G8: 0.034905588 | H8: 0.043995763
A9: Accessories Total | D9: 3088 | E9: 122023.08 | F9: 0.04092397 | G9: 0.034905588 | H9: 0.043995763
A10: Clothing | B10: Bottoms | C10: Leggings | D10: 379 | E10: 16808.41 | F10: 0.0050227282 | G10: 0.0048081677 | H10: 0.020653788
A11: Clothing | B11: Bottoms | C11: Pants | D11: 2739 | E11: 209084.69 | F11: 0.036298819 | G11: 0.059810194 | H11: 0.043724283
A12: Clothing | B12: Bottoms | C12: Skirts | D12: 1042 | E12: 84427.79 | F12: 0.013809189 | G12: 0.024151182 | H12: 0.017917694
A13: Clothing | B13: Bottoms Total | D13: 4160 | E13: 310320.89 | F13: 0.055130737 | G13: 0.088769544 | H13: 0.082295764
A14: Clothing | B14: Dresses | C14: Casual | D14: 3424 | E14: 353219.3 | F14: 0.045376837 | G14: 0.10104095 | H14: 0.066608467
A15: Clothing | B15: Dresses | C15: Essential | D15: 1452 | E15: 128725.15 | F15: 0.019242748 | G15: 0.036822764 | H15: 0.0471098
A16: Clothing | B16: Dresses | C16: Occasion | D16: 254 | E16: 30277.18 | F16: 0.0033661556 | G16: 0.0086610072 | H16: 0.0068349134
A17: Clothing | B17: Dresses Total | D17: 5130 | E17: 512221.63 | F17: 0.06798574 | G17: 0.14652472 | H17: 0.12055318
A18: Clothing | B18: Outerwear | C18: Abaya | D18: 618 | E18: 80161.29 | F18: 0.008190095 | G18: 0.022930719 | H18: 0.012243225
A19: Clothing | B19: Outerwear | C19: Blazer | D19: 717 | E19: 77868.15 | F19: 0.0095021005 | G19: 0.02227475 | H19: 0.0089428774
A20: Clothing | B20: Outerwear | C20: Bomber | D20: 1766 | E20: 184962.19 | F20: 0.023404058 | G20: 0.052909777 | H20: 0.014308604
A21: Clothing | B21: Outerwear | C21: Cape | D21: 507 | E21: 19464.95 | F21: 0.0067190585 | G21: 0.0055680903 | H21: 0.0027467409
A22: Clothing | B22: Outerwear | C22: Coat | D22: 1742 | E22: 240936.79 | F22: 0.023085996 | G22: 0.068921718 | H22: 0.023586839
A23: Clothing | B23: Outerwear | C23: Jacket | D23: 570 | E23: 53526.62 | F23: 0.0075539711 | G23: 0.015311678 | H23: 0.0063877696
A24: Clothing | B24: Outerwear | C24: Poncho | D24: 198 | E24: 12356.86 | F24: 0.002624011 | G24: 0.0035347695 | H24: 0.0016288812
A25: Clothing | B25: Outerwear Total | D25: 6118 | E25: 669276.85 | F25: 0.08107929 | G25: 0.1914515 | H25: 0.069844937
A26: Clothing | B26: Tops | C26: Cardigan | D26: 552 | E26: 48982.45 | F26: 0.0073154247 | G26: 0.014011785 | H26: 0.0053018487
A27: Clothing | B27: Tops | C27: LS Top | D27: 2116 | E27: 123510.22 | F27: 0.028042461 | G27: 0.035330995 | H27: 0.022101683
A28: Clothing | B28: Tops | C28: Shirt | D28: 473 | E28: 39192.49 | F28: 0.0062684708 | G28: 0.011211296 | H28: 0.0090706328
A29: Clothing | B29: Tops | C29: Sweater | D29: 2606 | E29: 217169.61 | F29: 0.034536226 | G29: 0.062122944 | H29: 0.037176819
A30: Clothing | B30: Tops Total | D30: 5747 | E30: 428854.77 | F30: 0.076162583 | G30: 0.12267702 | H30: 0.073650983
A31: Clothing Total | D31: 21155 | E31: 1920674.1 | F31: 0.28035835 | G31: 0.54942278 | H31: 0.34634487
A32: Headwear | B32: Scarves | C32: Bamboo | D32: 5230 | E32: 171288.54 | F32: 0.069310998 | G32: 0.04899833 | H32: 0.11900415
A33: Headwear | B33: Scarves | C33: Breathable | D33: 2723 | E33: 102172.52 | F33: 0.036086778 | G33: 0.029227191 | H33: 0.027765505
A34: Headwear | B34: Scarves | C34: Decorative | D34: 6195 | E34: 293247.3 | F34: 0.082099739 | G34: 0.083885519 | H34: 0.054296041
A35: Headwear | B35: Scarves | C35: Liquid | D35: 11742 | E35: 280896.89 | F35: 0.15561181 | G35: 0.080352595 | H35: 0.10635636
A36: Headwear | B36: Scarves | C36: Modal | D36: 569 | E36: 21141.97 | F36: 0.0075407186 | G36: 0.006047814 | H36: 0.018630995
A37: Headwear | B37: Scarves | C37: Premium | D37: 23758 | E37: 566134.71 | F37: 0.31485482 | G37: 0.16194694 | H37: 0.26683843
A38: Headwear | B38: Scarves Total | D38: 50217 | E38: 1434881.9 | F38: 0.66550486 | G38: 0.41045839 | H38: 0.59289148
A39: Headwear | B39: Underscarf | C39: Underscarf | D39: 997 | E39: 18224.45 | F39: 0.013212823 | G39: 0.0052132362 | H39: 0.016767895
A40: Headwear | B40: Underscarf Total | D40: 997 | E40: 18224.45 | F40: 0.013212823 | G40: 0.0052132362 | H40: 0.016767895
A41: Headwear Total | D41: 51214 | E41: 1453106.4 | F41: 0.67871768 | G41: 0.41567163 | H41: 0.60965937
A42: Grand Total | D42: 75457 | E42: 3495803.6 | F42: 1 | G42: 1 | H42: 1

Sheet Sign Off
A1: FW26 — MERCH PLAN SIGN OFF
A2: Proposed Plan vs Final Buy. Yellow = Final Buy inputs.
A4: OVERALL SUMMARY
B5: Proposed Plan | C5: Final Buy | D5: Variance ($) | E5: Variance (%)
A6: OTB Budget | B6: ='OTB Budget'!B5 -> 500000 | D6: =IF(C6="","",C6-B6) | E6: =IF(OR(C6="",B6=0),"",(C6-B6)/B6)
A7: Total Retail | B7: ='FW26 Styles'!Q505 -> 0 | D7: =IF(C7="","",C7-B7) | E7: =IF(OR(C7="",B7=0),"",(C7-B7)/B7)
A8: Total Cost | B8: ='FW26 Styles'!P505 -> 0 | D8: =IF(C8="","",C8-B8) | E8: =IF(OR(C8="",B8=0),"",(C8-B8)/B8)
A9: Blended Margin % | B9: ='FW26 Styles'!M505 -> 0 | D9: =IF(C9="","",C9-B9)
A10: Total Units | B10: ='FW26 Styles'!O505 -> 0 | D10: =IF(C10="","",C10-B10) | E10: =IF(OR(C10="",B10=0),"",(C10-B10)/B10)
A13: BY CATEGORY: PROPOSED vs FINAL BUY
A14: Main Category | B14: Category | C14: Sub Category | D14: Proposed Retail ($) | E14: Proposed Cost ($) | F14: Proposed Margin % | G14: Proposed Units | H14: Final Retail ($) | I14: Final Cost ($) | J14: Final Margin % | K14: Final Units
A15: Headwear | B15: Scarves | C15: Premium | D15: =SUMIFS('FW26 Styles'!Q5:Q504,'FW26 Styles'!A5:A504,A15,'FW26 Styles'!B5:B504,B15,'FW26 Styles'!C5:C504,C15) -> 0 | E15: =SUMIFS('FW26 Styles'!P5:P504,'FW26 Styles'!A5:A504,A15,'FW26 Styles'!B5:B504,B15,'FW26 Styles'!C5:C504,C15) -> 0 | F15: =IF(D15=0,"",1-(E15/D15)) | G15: =SUMIFS('FW26 Styles'!O5:O504,'FW26 Styles'!A5:A504,A15,'FW26 Styles'!B5:B504,B15,'FW26 Styles'!C5:C504,C15) -> 0 | J15: =IF(H15=0,"",1-(I15/H15))
A16: Headwear | B16: Scarves | C16: Bamboo | D16: =SUMIFS('FW26 Styles'!Q5:Q504,'FW26 Styles'!A5:A504,A16,'FW26 Styles'!B5:B504,B16,'FW26 Styles'!C5:C504,C16) -> 0 | E16: =SUMIFS('FW26 Styles'!P5:P504,'FW26 Styles'!A5:A504,A16,'FW26 Styles'!B5:B504,B16,'FW26 Styles'!C5:C504,C16) -> 0 | F16: =IF(D16=0,"",1-(E16/D16)) | G16: =SUMIFS('FW26 Styles'!O5:O504,'FW26 Styles'!A5:A504,A16,'FW26 Styles'!B5:B504,B16,'FW26 Styles'!C5:C504,C16) -> 0 | J16: =IF(H16=0,"",1-(I16/H16))
A17: Headwear | B17: Scarves | C17: Breathable | D17: =SUMIFS('FW26 Styles'!Q5:Q504,'FW26 Styles'!A5:A504,A17,'FW26 Styles'!B5:B504,B17,'FW26 Styles'!C5:C504,C17) -> 0 | E17: =SUMIFS('FW26 Styles'!P5:P504,'FW26 Styles'!A5:A504,A17,'FW26 Styles'!B5:B504,B17,'FW26 Styles'!C5:C504,C17) -> 0 | F17: =IF(D17=0,"",1-(E17/D17)) | G17: =SUMIFS('FW26 Styles'!O5:O504,'FW26 Styles'!A5:A504,A17,'FW26 Styles'!B5:B504,B17,'FW26 Styles'!C5:C504,C17) -> 0 | J17: =IF(H17=0,"",1-(I17/H17))
A18: Headwear | B18: Scarves | C18: Liquid | D18: =SUMIFS('FW26 Styles'!Q5:Q504,'FW26 Styles'!A5:A504,A18,'FW26 Styles'!B5:B504,B18,'FW26 Styles'!C5:C504,C18) -> 0 | E18: =SUMIFS('FW26 Styles'!P5:P504,'FW26 Styles'!A5:A504,A18,'FW26 Styles'!B5:B504,B18,'FW26 Styles'!C5:C504,C18) -> 0 | F18: =IF(D18=0,"",1-(E18/D18)) | G18: =SUMIFS('FW26 Styles'!O5:O504,'FW26 Styles'!A5:A504,A18,'FW26 Styles'!B5:B504,B18,'FW26 Styles'!C5:C504,C18) -> 0 | J18: =IF(H18=0,"",1-(I18/H18))
A19: Headwear | B19: Scarves | C19: Decorative | D19: =SUMIFS('FW26 Styles'!Q5:Q504,'FW26 Styles'!A5:A504,A19,'FW26 Styles'!B5:B504,B19,'FW26 Styles'!C5:C504,C19) -> 0 | E19: =SUMIFS('FW26 Styles'!P5:P504,'FW26 Styles'!A5:A504,A19,'FW26 Styles'!B5:B504,B19,'FW26 Styles'!C5:C504,C19) -> 0 | F19: =IF(D19=0,"",1-(E19/D19)) | G19: =SUMIFS('FW26 Styles'!O5:O504,'FW26 Styles'!A5:A504,A19,'FW26 Styles'!B5:B504,B19,'FW26 Styles'!C5:C504,C19) -> 0 | J19: =IF(H19=0,"",1-(I19/H19))
A20: Headwear | B20: Scarves | C20: New 1 | D20: =SUMIFS('FW26 Styles'!Q5:Q504,'FW26 Styles'!A5:A504,A20,'FW26 Styles'!B5:B504,B20,'FW26 Styles'!C5:C504,C20) -> 0 | E20: =SUMIFS('FW26 Styles'!P5:P504,'FW26 Styles'!A5:A504,A20,'FW26 Styles'!B5:B504,B20,'FW26 Styles'!C5:C504,C20) -> 0 | F20: =IF(D20=0,"",1-(E20/D20)) | G20: =SUMIFS('FW26 Styles'!O5:O504,'FW26 Styles'!A5:A504,A20,'FW26 Styles'!B5:B504,B20,'FW26 Styles'!C5:C504,C20) -> 0 | J20: =IF(H20=0,"",1-(I20/H20))
A21: Headwear | B21: Scarves | C21: New 2 | D21: =SUMIFS('FW26 Styles'!Q5:Q504,'FW26 Styles'!A5:A504,A21,'FW26 Styles'!B5:B504,B21,'FW26 Styles'!C5:C504,C21) -> 0 | E21: =SUMIFS('FW26 Styles'!P5:P504,'FW26 Styles'!A5:A504,A21,'FW26 Styles'!B5:B504,B21,'FW26 Styles'!C5:C504,C21) -> 0 | F21: =IF(D21=0,"",1-(E21/D21)) | G21: =SUMIFS('FW26 Styles'!O5:O504,'FW26 Styles'!A5:A504,A21,'FW26 Styles'!B5:B504,B21,'FW26 Styles'!C5:C504,C21) -> 0 | J21: =IF(H21=0,"",1-(I21/H21))
A22: Headwear | B22: Scarves | C22: New 3 | D22: =SUMIFS('FW26 Styles'!Q5:Q504,'FW26 Styles'!A5:A504,A22,'FW26 Styles'!B5:B504,B22,'FW26 Styles'!C5:C504,C22) -> 0 | E22: =SUMIFS('FW26 Styles'!P5:P504,'FW26 Styles'!A5:A504,A22,'FW26 Styles'!B5:B504,B22,'FW26 Styles'!C5:C504,C22) -> 0 | F22: =IF(D22=0,"",1-(E22/D22)) | G22: =SUMIFS('FW26 Styles'!O5:O504,'FW26 Styles'!A5:A504,A22,'FW26 Styles'!B5:B504,B22,'FW26 Styles'!C5:C504,C22) -> 0 | J22: =IF(H22=0,"",1-(I22/H22))
A23: Headwear | B23: Hijab | C23: Premium | D23: =SUMIFS('FW26 Styles'!Q5:Q504,'FW26 Styles'!A5:A504,A23,'FW26 Styles'!B5:B504,B23,'FW26 Styles'!C5:C504,C23) -> 0 | E23: =SUMIFS('FW26 Styles'!P5:P504,'FW26 Styles'!A5:A504,A23,'FW26 Styles'!B5:B504,B23,'FW26 Styles'!C5:C504,C23) -> 0 | F23: =IF(D23=0,"",1-(E23/D23)) | G23: =SUMIFS('FW26 Styles'!O5:O504,'FW26 Styles'!A5:A504,A23,'FW26 Styles'!B5:B504,B23,'FW26 Styles'!C5:C504,C23) -> 0 | J23: =IF(H23=0,"",1-(I23/H23))
A24: Headwear | B24: Hijab | C24: Bamboo | D24: =SUMIFS('FW26 Styles'!Q5:Q504,'FW26 Styles'!A5:A504,A24,'FW26 Styles'!B5:B504,B24,'FW26 Styles'!C5:C504,C24) -> 0 | E24: =SUMIFS('FW26 Styles'!P5:P504,'FW26 Styles'!A5:A504,A24,'FW26 Styles'!B5:B504,B24,'FW26 Styles'!C5:C504,C24) -> 0 | F24: =IF(D24=0,"",1-(E24/D24)) | G24: =SUMIFS('FW26 Styles'!O5:O504,'FW26 Styles'!A5:A504,A24,'FW26 Styles'!B5:B504,B24,'FW26 Styles'!C5:C504,C24) -> 0 | J24: =IF(H24=0,"",1-(I24/H24))
A25: Headwear | B25: Hijab | C25: Breathable | D25: =SUMIFS('FW26 Styles'!Q5:Q504,'FW26 Styles'!A5:A504,A25,'FW26 Styles'!B5:B504,B25,'FW26 Styles'!C5:C504,C25) -> 0 | E25: =SUMIFS('FW26 Styles'!P5:P504,'FW26 Styles'!A5:A504,A25,'FW26 Styles'!B5:B504,B25,'FW26 Styles'!C5:C504,C25) -> 0 | F25: =IF(D25=0,"",1-(E25/D25)) | G25: =SUMIFS('FW26 Styles'!O5:O504,'FW26 Styles'!A5:A504,A25,'FW26 Styles'!B5:B504,B25,'FW26 Styles'!C5:C504,C25) -> 0 | J25: =IF(H25=0,"",1-(I25/H25))
A26: Headwear | B26: Hijab | C26: New 1 | D26: =SUMIFS('FW26 Styles'!Q5:Q504,'FW26 Styles'!A5:A504,A26,'FW26 Styles'!B5:B504,B26,'FW26 Styles'!C5:C504,C26) -> 0 | E26: =SUMIFS('FW26 Styles'!P5:P504,'FW26 Styles'!A5:A504,A26,'FW26 Styles'!B5:B504,B26,'FW26 Styles'!C5:C504,C26) -> 0 | F26: =IF(D26=0,"",1-(E26/D26)) | G26: =SUMIFS('FW26 Styles'!O5:O504,'FW26 Styles'!A5:A504,A26,'FW26 Styles'!B5:B504,B26,'FW26 Styles'!C5:C504,C26) -> 0 | J26: =IF(H26=0,"",1-(I26/H26))
A27: Headwear | B27: Hijab | C27: New 2 | D27: =SUMIFS('FW26 Styles'!Q5:Q504,'FW26 Styles'!A5:A504,A27,'FW26 Styles'!B5:B504,B27,'FW26 Styles'!C5:C504,C27) -> 0 | E27: =SUMIFS('FW26 Styles'!P5:P504,'FW26 Styles'!A5:A504,A27,'FW26 Styles'!B5:B504,B27,'FW26 Styles'!C5:C504,C27) -> 0 | F27: =IF(D27=0,"",1-(E27/D27)) | G27: =SUMIFS('FW26 Styles'!O5:O504,'FW26 Styles'!A5:A504,A27,'FW26 Styles'!B5:B504,B27,'FW26 Styles'!C5:C504,C27) -> 0 | J27: =IF(H27=0,"",1-(I27/H27))
A28: Headwear | B28: Hijab | C28: New 3 | D28: =SUMIFS('FW26 Styles'!Q5:Q504,'FW26 Styles'!A5:A504,A28,'FW26 Styles'!B5:B504,B28,'FW26 Styles'!C5:C504,C28) -> 0 | E28: =SUMIFS('FW26 Styles'!P5:P504,'FW26 Styles'!A5:A504,A28,'FW26 Styles'!B5:B504,B28,'FW26 Styles'!C5:C504,C28) -> 0 | F28: =IF(D28=0,"",1-(E28/D28)) | G28: =SUMIFS('FW26 Styles'!O5:O504,'FW26 Styles'!A5:A504,A28,'FW26 Styles'!B5:B504,B28,'FW26 Styles'!C5:C504,C28) -> 0 | J28: =IF(H28=0,"",1-(I28/H28))
A29: Headwear | B29: Khimaar | C29: Premium | D29: =SUMIFS('FW26 Styles'!Q5:Q504,'FW26 Styles'!A5:A504,A29,'FW26 Styles'!B5:B504,B29,'FW26 Styles'!C5:C504,C29) -> 0 | E29: =SUMIFS('FW26 Styles'!P5:P504,'FW26 Styles'!A5:A504,A29,'FW26 Styles'!B5:B504,B29,'FW26 Styles'!C5:C504,C29) -> 0 | F29: =IF(D29=0,"",1-(E29/D29)) | G29: =SUMIFS('FW26 Styles'!O5:O504,'FW26 Styles'!A5:A504,A29,'FW26 Styles'!B5:B504,B29,'FW26 Styles'!C5:C504,C29) -> 0 | J29: =IF(H29=0,"",1-(I29/H29))
A30: Headwear | B30: Khimaar | C30: Bamboo | D30: =SUMIFS('FW26 Styles'!Q5:Q504,'FW26 Styles'!A5:A504,A30,'FW26 Styles'!B5:B504,B30,'FW26 Styles'!C5:C504,C30) -> 0 | E30: =SUMIFS('FW26 Styles'!P5:P504,'FW26 Styles'!A5:A504,A30,'FW26 Styles'!B5:B504,B30,'FW26 Styles'!C5:C504,C30) -> 0 | F30: =IF(D30=0,"",1-(E30/D30)) | G30: =SUMIFS('FW26 Styles'!O5:O504,'FW26 Styles'!A5:A504,A30,'FW26 Styles'!B5:B504,B30,'FW26 Styles'!C5:C504,C30) -> 0 | J30: =IF(H30=0,"",1-(I30/H30))
A31: Headwear | B31: Khimaar | C31: Breathable | D31: =SUMIFS('FW26 Styles'!Q5:Q504,'FW26 Styles'!A5:A504,A31,'FW26 Styles'!B5:B504,B31,'FW26 Styles'!C5:C504,C31) -> 0 | E31: =SUMIFS('FW26 Styles'!P5:P504,'FW26 Styles'!A5:A504,A31,'FW26 Styles'!B5:B504,B31,'FW26 Styles'!C5:C504,C31) -> 0 | F31: =IF(D31=0,"",1-(E31/D31)) | G31: =SUMIFS('FW26 Styles'!O5:O504,'FW26 Styles'!A5:A504,A31,'FW26 Styles'!B5:B504,B31,'FW26 Styles'!C5:C504,C31) -> 0 | J31: =IF(H31=0,"",1-(I31/H31))
A32: Headwear | B32: Khimaar | C32: New 1 | D32: =SUMIFS('FW26 Styles'!Q5:Q504,'FW26 Styles'!A5:A504,A32,'FW26 Styles'!B5:B504,B32,'FW26 Styles'!C5:C504,C32) -> 0 | E32: =SUMIFS('FW26 Styles'!P5:P504,'FW26 Styles'!A5:A504,A32,'FW26 Styles'!B5:B504,B32,'FW26 Styles'!C5:C504,C32) -> 0 | F32: =IF(D32=0,"",1-(E32/D32)) | G32: =SUMIFS('FW26 Styles'!O5:O504,'FW26 Styles'!A5:A504,A32,'FW26 Styles'!B5:B504,B32,'FW26 Styles'!C5:C504,C32) -> 0 | J32: =IF(H32=0,"",1-(I32/H32))
A33: Headwear | B33: Khimaar | C33: New 2 | D33: =SUMIFS('FW26 Styles'!Q5:Q504,'FW26 Styles'!A5:A504,A33,'FW26 Styles'!B5:B504,B33,'FW26 Styles'!C5:C504,C33) -> 0 | E33: =SUMIFS('FW26 Styles'!P5:P504,'FW26 Styles'!A5:A504,A33,'FW26 Styles'!B5:B504,B33,'FW26 Styles'!C5:C504,C33) -> 0 | F33: =IF(D33=0,"",1-(E33/D33)) | G33: =SUMIFS('FW26 Styles'!O5:O504,'FW26 Styles'!A5:A504,A33,'FW26 Styles'!B5:B504,B33,'FW26 Styles'!C5:C504,C33) -> 0 | J33: =IF(H33=0,"",1-(I33/H33))
A34: Headwear | B34: Khimaar | C34: New 3 | D34: =SUMIFS('FW26 Styles'!Q5:Q504,'FW26 Styles'!A5:A504,A34,'FW26 Styles'!B5:B504,B34,'FW26 Styles'!C5:C504,C34) -> 0 | E34: =SUMIFS('FW26 Styles'!P5:P504,'FW26 Styles'!A5:A504,A34,'FW26 Styles'!B5:B504,B34,'FW26 Styles'!C5:C504,C34) -> 0 | F34: =IF(D34=0,"",1-(E34/D34)) | G34: =SUMIFS('FW26 Styles'!O5:O504,'FW26 Styles'!A5:A504,A34,'FW26 Styles'!B5:B504,B34,'FW26 Styles'!C5:C504,C34) -> 0 | J34: =IF(H34=0,"",1-(I34/H34))
A35: Clothing | B35: Dresses | C35: Casual | D35: =SUMIFS('FW26 Styles'!Q5:Q504,'FW26 Styles'!A5:A504,A35,'FW26 Styles'!B5:B504,B35,'FW26 Styles'!C5:C504,C35) -> 0 | E35: =SUMIFS('FW26 Styles'!P5:P504,'FW26 Styles'!A5:A504,A35,'FW26 Styles'!B5:B504,B35,'FW26 Styles'!C5:C504,C35) -> 0 | F35: =IF(D35=0,"",1-(E35/D35)) | G35: =SUMIFS('FW26 Styles'!O5:O504,'FW26 Styles'!A5:A504,A35,'FW26 Styles'!B5:B504,B35,'FW26 Styles'!C5:C504,C35) -> 0 | J35: =IF(H35=0,"",1-(I35/H35))
A36: Clothing | B36: Dresses | C36: Occasion | D36: =SUMIFS('FW26 Styles'!Q5:Q504,'FW26 Styles'!A5:A504,A36,'FW26 Styles'!B5:B504,B36,'FW26 Styles'!C5:C504,C36) -> 0 | E36: =SUMIFS('FW26 Styles'!P5:P504,'FW26 Styles'!A5:A504,A36,'FW26 Styles'!B5:B504,B36,'FW26 Styles'!C5:C504,C36) -> 0 | F36: =IF(D36=0,"",1-(E36/D36)) | G36: =SUMIFS('FW26 Styles'!O5:O504,'FW26 Styles'!A5:A504,A36,'FW26 Styles'!B5:B504,B36,'FW26 Styles'!C5:C504,C36) -> 0 | J36: =IF(H36=0,"",1-(I36/H36))
A37: Clothing | B37: Dresses | C37: Essential | D37: =SUMIFS('FW26 Styles'!Q5:Q504,'FW26 Styles'!A5:A504,A37,'FW26 Styles'!B5:B504,B37,'FW26 Styles'!C5:C504,C37) -> 0 | E37: =SUMIFS('FW26 Styles'!P5:P504,'FW26 Styles'!A5:A504,A37,'FW26 Styles'!B5:B504,B37,'FW26 Styles'!C5:C504,C37) -> 0 | F37: =IF(D37=0,"",1-(E37/D37)) | G37: =SUMIFS('FW26 Styles'!O5:O504,'FW26 Styles'!A5:A504,A37,'FW26 Styles'!B5:B504,B37,'FW26 Styles'!C5:C504,C37) -> 0 | J37: =IF(H37=0,"",1-(I37/H37))
A38: Clothing | B38: Dresses | C38: New 1 | D38: =SUMIFS('FW26 Styles'!Q5:Q504,'FW26 Styles'!A5:A504,A38,'FW26 Styles'!B5:B504,B38,'FW26 Styles'!C5:C504,C38) -> 0 | E38: =SUMIFS('FW26 Styles'!P5:P504,'FW26 Styles'!A5:A504,A38,'FW26 Styles'!B5:B504,B38,'FW26 Styles'!C5:C504,C38) -> 0 | F38: =IF(D38=0,"",1-(E38/D38)) | G38: =SUMIFS('FW26 Styles'!O5:O504,'FW26 Styles'!A5:A504,A38,'FW26 Styles'!B5:B504,B38,'FW26 Styles'!C5:C504,C38) -> 0 | J38: =IF(H38=0,"",1-(I38/H38))
A39: Clothing | B39: Dresses | C39: New 2 | D39: =SUMIFS('FW26 Styles'!Q5:Q504,'FW26 Styles'!A5:A504,A39,'FW26 Styles'!B5:B504,B39,'FW26 Styles'!C5:C504,C39) -> 0 | E39: =SUMIFS('FW26 Styles'!P5:P504,'FW26 Styles'!A5:A504,A39,'FW26 Styles'!B5:B504,B39,'FW26 Styles'!C5:C504,C39) -> 0 | F39: =IF(D39=0,"",1-(E39/D39)) | G39: =SUMIFS('FW26 Styles'!O5:O504,'FW26 Styles'!A5:A504,A39,'FW26 Styles'!B5:B504,B39,'FW26 Styles'!C5:C504,C39) -> 0 | J39: =IF(H39=0,"",1-(I39/H39))
A40: Clothing | B40: Dresses | C40: New 3 | D40: =SUMIFS('FW26 Styles'!Q5:Q504,'FW26 Styles'!A5:A504,A40,'FW26 Styles'!B5:B504,B40,'FW26 Styles'!C5:C504,C40) -> 0 | E40: =SUMIFS('FW26 Styles'!P5:P504,'FW26 Styles'!A5:A504,A40,'FW26 Styles'!B5:B504,B40,'FW26 Styles'!C5:C504,C40) -> 0 | F40: =IF(D40=0,"",1-(E40/D40)) | G40: =SUMIFS('FW26 Styles'!O5:O504,'FW26 Styles'!A5:A504,A40,'FW26 Styles'!B5:B504,B40,'FW26 Styles'!C5:C504,C40) -> 0 | J40: =IF(H40=0,"",1-(I40/H40))
A41: Clothing | B41: Tops | C41: Blouse | D41: =SUMIFS('FW26 Styles'!Q5:Q504,'FW26 Styles'!A5:A504,A41,'FW26 Styles'!B5:B504,B41,'FW26 Styles'!C5:C504,C41) -> 0 | E41: =SUMIFS('FW26 Styles'!P5:P504,'FW26 Styles'!A5:A504,A41,'FW26 Styles'!B5:B504,B41,'FW26 Styles'!C5:C504,C41) -> 0 | F41: =IF(D41=0,"",1-(E41/D41)) | G41: =SUMIFS('FW26 Styles'!O5:O504,'FW26 Styles'!A5:A504,A41,'FW26 Styles'!B5:B504,B41,'FW26 Styles'!C5:C504,C41) -> 0 | J41: =IF(H41=0,"",1-(I41/H41))
A42: Clothing | B42: Tops | C42: LS Tops | D42: =SUMIFS('FW26 Styles'!Q5:Q504,'FW26 Styles'!A5:A504,A42,'FW26 Styles'!B5:B504,B42,'FW26 Styles'!C5:C504,C42) -> 0 | E42: =SUMIFS('FW26 Styles'!P5:P504,'FW26 Styles'!A5:A504,A42,'FW26 Styles'!B5:B504,B42,'FW26 Styles'!C5:C504,C42) -> 0 | F42: =IF(D42=0,"",1-(E42/D42)) | G42: =SUMIFS('FW26 Styles'!O5:O504,'FW26 Styles'!A5:A504,A42,'FW26 Styles'!B5:B504,B42,'FW26 Styles'!C5:C504,C42) -> 0 | J42: =IF(H42=0,"",1-(I42/H42))
A43: Clothing | B43: Tops | C43: LS Tees | D43: =SUMIFS('FW26 Styles'!Q5:Q504,'FW26 Styles'!A5:A504,A43,'FW26 Styles'!B5:B504,B43,'FW26 Styles'!C5:C504,C43) -> 0 | E43: =SUMIFS('FW26 Styles'!P5:P504,'FW26 Styles'!A5:A504,A43,'FW26 Styles'!B5:B504,B43,'FW26 Styles'!C5:C504,C43) -> 0 | F43: =IF(D43=0,"",1-(E43/D43)) | G43: =SUMIFS('FW26 Styles'!O5:O504,'FW26 Styles'!A5:A504,A43,'FW26 Styles'!B5:B504,B43,'FW26 Styles'!C5:C504,C43) -> 0 | J43: =IF(H43=0,"",1-(I43/H43))
A44: Clothing | B44: Tops | C44: Shirt | D44: =SUMIFS('FW26 Styles'!Q5:Q504,'FW26 Styles'!A5:A504,A44,'FW26 Styles'!B5:B504,B44,'FW26 Styles'!C5:C504,C44) -> 0 | E44: =SUMIFS('FW26 Styles'!P5:P504,'FW26 Styles'!A5:A504,A44,'FW26 Styles'!B5:B504,B44,'FW26 Styles'!C5:C504,C44) -> 0 | F44: =IF(D44=0,"",1-(E44/D44)) | G44: =SUMIFS('FW26 Styles'!O5:O504,'FW26 Styles'!A5:A504,A44,'FW26 Styles'!B5:B504,B44,'FW26 Styles'!C5:C504,C44) -> 0 | J44: =IF(H44=0,"",1-(I44/H44))
A45: Clothing | B45: Tops | C45: Hijab Top | D45: =SUMIFS('FW26 Styles'!Q5:Q504,'FW26 Styles'!A5:A504,A45,'FW26 Styles'!B5:B504,B45,'FW26 Styles'!C5:C504,C45) -> 0 | E45: =SUMIFS('FW26 Styles'!P5:P504,'FW26 Styles'!A5:A504,A45,'FW26 Styles'!B5:B504,B45,'FW26 Styles'!C5:C504,C45) -> 0 | F45: =IF(D45=0,"",1-(E45/D45)) | G45: =SUMIFS('FW26 Styles'!O5:O504,'FW26 Styles'!A5:A504,A45,'FW26 Styles'!B5:B504,B45,'FW26 Styles'!C5:C504,C45) -> 0 | J45: =IF(H45=0,"",1-(I45/H45))
A46: Clothing | B46: Tops | C46: Sleeveless Top | D46: =SUMIFS('FW26 Styles'!Q5:Q504,'FW26 Styles'!A5:A504,A46,'FW26 Styles'!B5:B504,B46,'FW26 Styles'!C5:C504,C46) -> 0 | E46: =SUMIFS('FW26 Styles'!P5:P504,'FW26 Styles'!A5:A504,A46,'FW26 Styles'!B5:B504,B46,'FW26 Styles'!C5:C504,C46) -> 0 | F46: =IF(D46=0,"",1-(E46/D46)) | G46: =SUMIFS('FW26 Styles'!O5:O504,'FW26 Styles'!A5:A504,A46,'FW26 Styles'!B5:B504,B46,'FW26 Styles'!C5:C504,C46) -> 0 | J46: =IF(H46=0,"",1-(I46/H46))
A47: Clothing | B47: Tops | C47: Tunic | D47: =SUMIFS('FW26 Styles'!Q5:Q504,'FW26 Styles'!A5:A504,A47,'FW26 Styles'!B5:B504,B47,'FW26 Styles'!C5:C504,C47) -> 0 | E47: =SUMIFS('FW26 Styles'!P5:P504,'FW26 Styles'!A5:A504,A47,'FW26 Styles'!B5:B504,B47,'FW26 Styles'!C5:C504,C47) -> 0 | F47: =IF(D47=0,"",1-(E47/D47)) | G47: =SUMIFS('FW26 Styles'!O5:O504,'FW26 Styles'!A5:A504,A47,'FW26 Styles'!B5:B504,B47,'FW26 Styles'!C5:C504,C47) -> 0 | J47: =IF(H47=0,"",1-(I47/H47))
A48: Clothing | B48: Tops | C48: New 1 | D48: =SUMIFS('FW26 Styles'!Q5:Q504,'FW26 Styles'!A5:A504,A48,'FW26 Styles'!B5:B504,B48,'FW26 Styles'!C5:C504,C48) -> 0 | E48: =SUMIFS('FW26 Styles'!P5:P504,'FW26 Styles'!A5:A504,A48,'FW26 Styles'!B5:B504,B48,'FW26 Styles'!C5:C504,C48) -> 0 | F48: =IF(D48=0,"",1-(E48/D48)) | G48: =SUMIFS('FW26 Styles'!O5:O504,'FW26 Styles'!A5:A504,A48,'FW26 Styles'!B5:B504,B48,'FW26 Styles'!C5:C504,C48) -> 0 | J48: =IF(H48=0,"",1-(I48/H48))
A49: Clothing | B49: Tops | C49: New 2 | D49: =SUMIFS('FW26 Styles'!Q5:Q504,'FW26 Styles'!A5:A504,A49,'FW26 Styles'!B5:B504,B49,'FW26 Styles'!C5:C504,C49) -> 0 | E49: =SUMIFS('FW26 Styles'!P5:P504,'FW26 Styles'!A5:A504,A49,'FW26 Styles'!B5:B504,B49,'FW26 Styles'!C5:C504,C49) -> 0 | F49: =IF(D49=0,"",1-(E49/D49)) | G49: =SUMIFS('FW26 Styles'!O5:O504,'FW26 Styles'!A5:A504,A49,'FW26 Styles'!B5:B504,B49,'FW26 Styles'!C5:C504,C49) -> 0 | J49: =IF(H49=0,"",1-(I49/H49))
A50: Clothing | B50: Tops | C50: New 3 | D50: =SUMIFS('FW26 Styles'!Q5:Q504,'FW26 Styles'!A5:A504,A50,'FW26 Styles'!B5:B504,B50,'FW26 Styles'!C5:C504,C50) -> 0 | E50: =SUMIFS('FW26 Styles'!P5:P504,'FW26 Styles'!A5:A504,A50,'FW26 Styles'!B5:B504,B50,'FW26 Styles'!C5:C504,C50) -> 0 | F50: =IF(D50=0,"",1-(E50/D50)) | G50: =SUMIFS('FW26 Styles'!O5:O504,'FW26 Styles'!A5:A504,A50,'FW26 Styles'!B5:B504,B50,'FW26 Styles'!C5:C504,C50) -> 0 | J50: =IF(H50=0,"",1-(I50/H50))
A51: Clothing | B51: Bottoms | C51: Pants | D51: =SUMIFS('FW26 Styles'!Q5:Q504,'FW26 Styles'!A5:A504,A51,'FW26 Styles'!B5:B504,B51,'FW26 Styles'!C5:C504,C51) -> 0 | E51: =SUMIFS('FW26 Styles'!P5:P504,'FW26 Styles'!A5:A504,A51,'FW26 Styles'!B5:B504,B51,'FW26 Styles'!C5:C504,C51) -> 0 | F51: =IF(D51=0,"",1-(E51/D51)) | G51: =SUMIFS('FW26 Styles'!O5:O504,'FW26 Styles'!A5:A504,A51,'FW26 Styles'!B5:B504,B51,'FW26 Styles'!C5:C504,C51) -> 0 | J51: =IF(H51=0,"",1-(I51/H51))
A52: Clothing | B52: Bottoms | C52: Skirts | D52: =SUMIFS('FW26 Styles'!Q5:Q504,'FW26 Styles'!A5:A504,A52,'FW26 Styles'!B5:B504,B52,'FW26 Styles'!C5:C504,C52) -> 0 | E52: =SUMIFS('FW26 Styles'!P5:P504,'FW26 Styles'!A5:A504,A52,'FW26 Styles'!B5:B504,B52,'FW26 Styles'!C5:C504,C52) -> 0 | F52: =IF(D52=0,"",1-(E52/D52)) | G52: =SUMIFS('FW26 Styles'!O5:O504,'FW26 Styles'!A5:A504,A52,'FW26 Styles'!B5:B504,B52,'FW26 Styles'!C5:C504,C52) -> 0 | J52: =IF(H52=0,"",1-(I52/H52))
A53: Clothing | B53: Bottoms | C53: Legging | D53: =SUMIFS('FW26 Styles'!Q5:Q504,'FW26 Styles'!A5:A504,A53,'FW26 Styles'!B5:B504,B53,'FW26 Styles'!C5:C504,C53) -> 0 | E53: =SUMIFS('FW26 Styles'!P5:P504,'FW26 Styles'!A5:A504,A53,'FW26 Styles'!B5:B504,B53,'FW26 Styles'!C5:C504,C53) -> 0 | F53: =IF(D53=0,"",1-(E53/D53)) | G53: =SUMIFS('FW26 Styles'!O5:O504,'FW26 Styles'!A5:A504,A53,'FW26 Styles'!B5:B504,B53,'FW26 Styles'!C5:C504,C53) -> 0 | J53: =IF(H53=0,"",1-(I53/H53))
A54: Clothing | B54: Bottoms | C54: New 1 | D54: =SUMIFS('FW26 Styles'!Q5:Q504,'FW26 Styles'!A5:A504,A54,'FW26 Styles'!B5:B504,B54,'FW26 Styles'!C5:C504,C54) -> 0 | E54: =SUMIFS('FW26 Styles'!P5:P504,'FW26 Styles'!A5:A504,A54,'FW26 Styles'!B5:B504,B54,'FW26 Styles'!C5:C504,C54) -> 0 | F54: =IF(D54=0,"",1-(E54/D54)) | G54: =SUMIFS('FW26 Styles'!O5:O504,'FW26 Styles'!A5:A504,A54,'FW26 Styles'!B5:B504,B54,'FW26 Styles'!C5:C504,C54) -> 0 | J54: =IF(H54=0,"",1-(I54/H54))
A55: Clothing | B55: Bottoms | C55: New 2 | D55: =SUMIFS('FW26 Styles'!Q5:Q504,'FW26 Styles'!A5:A504,A55,'FW26 Styles'!B5:B504,B55,'FW26 Styles'!C5:C504,C55) -> 0 | E55: =SUMIFS('FW26 Styles'!P5:P504,'FW26 Styles'!A5:A504,A55,'FW26 Styles'!B5:B504,B55,'FW26 Styles'!C5:C504,C55) -> 0 | F55: =IF(D55=0,"",1-(E55/D55)) | G55: =SUMIFS('FW26 Styles'!O5:O504,'FW26 Styles'!A5:A504,A55,'FW26 Styles'!B5:B504,B55,'FW26 Styles'!C5:C504,C55) -> 0 | J55: =IF(H55=0,"",1-(I55/H55))
A56: Clothing | B56: Bottoms | C56: New 3 | D56: =SUMIFS('FW26 Styles'!Q5:Q504,'FW26 Styles'!A5:A504,A56,'FW26 Styles'!B5:B504,B56,'FW26 Styles'!C5:C504,C56) -> 0 | E56: =SUMIFS('FW26 Styles'!P5:P504,'FW26 Styles'!A5:A504,A56,'FW26 Styles'!B5:B504,B56,'FW26 Styles'!C5:C504,C56) -> 0 | F56: =IF(D56=0,"",1-(E56/D56)) | G56: =SUMIFS('FW26 Styles'!O5:O504,'FW26 Styles'!A5:A504,A56,'FW26 Styles'!B5:B504,B56,'FW26 Styles'!C5:C504,C56) -> 0 | J56: =IF(H56=0,"",1-(I56/H56))
A57: Clothing | B57: Outerwear | C57: Abaya | D57: =SUMIFS('FW26 Styles'!Q5:Q504,'FW26 Styles'!A5:A504,A57,'FW26 Styles'!B5:B504,B57,'FW26 Styles'!C5:C504,C57) -> 0 | E57: =SUMIFS('FW26 Styles'!P5:P504,'FW26 Styles'!A5:A504,A57,'FW26 Styles'!B5:B504,B57,'FW26 Styles'!C5:C504,C57) -> 0 | F57: =IF(D57=0,"",1-(E57/D57)) | G57: =SUMIFS('FW26 Styles'!O5:O504,'FW26 Styles'!A5:A504,A57,'FW26 Styles'!B5:B504,B57,'FW26 Styles'!C5:C504,C57) -> 0 | J57: =IF(H57=0,"",1-(I57/H57))
A58: Clothing | B58: Outerwear | C58: Jacket | D58: =SUMIFS('FW26 Styles'!Q5:Q504,'FW26 Styles'!A5:A504,A58,'FW26 Styles'!B5:B504,B58,'FW26 Styles'!C5:C504,C58) -> 0 | E58: =SUMIFS('FW26 Styles'!P5:P504,'FW26 Styles'!A5:A504,A58,'FW26 Styles'!B5:B504,B58,'FW26 Styles'!C5:C504,C58) -> 0 | F58: =IF(D58=0,"",1-(E58/D58)) | G58: =SUMIFS('FW26 Styles'!O5:O504,'FW26 Styles'!A5:A504,A58,'FW26 Styles'!B5:B504,B58,'FW26 Styles'!C5:C504,C58) -> 0 | J58: =IF(H58=0,"",1-(I58/H58))
A59: Clothing | B59: Outerwear | C59: Coat | D59: =SUMIFS('FW26 Styles'!Q5:Q504,'FW26 Styles'!A5:A504,A59,'FW26 Styles'!B5:B504,B59,'FW26 Styles'!C5:C504,C59) -> 0 | E59: =SUMIFS('FW26 Styles'!P5:P504,'FW26 Styles'!A5:A504,A59,'FW26 Styles'!B5:B504,B59,'FW26 Styles'!C5:C504,C59) -> 0 | F59: =IF(D59=0,"",1-(E59/D59)) | G59: =SUMIFS('FW26 Styles'!O5:O504,'FW26 Styles'!A5:A504,A59,'FW26 Styles'!B5:B504,B59,'FW26 Styles'!C5:C504,C59) -> 0 | J59: =IF(H59=0,"",1-(I59/H59))
A60: Clothing | B60: Outerwear | C60: Bomber | D60: =SUMIFS('FW26 Styles'!Q5:Q504,'FW26 Styles'!A5:A504,A60,'FW26 Styles'!B5:B504,B60,'FW26 Styles'!C5:C504,C60) -> 0 | E60: =SUMIFS('FW26 Styles'!P5:P504,'FW26 Styles'!A5:A504,A60,'FW26 Styles'!B5:B504,B60,'FW26 Styles'!C5:C504,C60) -> 0 | F60: =IF(D60=0,"",1-(E60/D60)) | G60: =SUMIFS('FW26 Styles'!O5:O504,'FW26 Styles'!A5:A504,A60,'FW26 Styles'!B5:B504,B60,'FW26 Styles'!C5:C504,C60) -> 0 | J60: =IF(H60=0,"",1-(I60/H60))
A61: Clothing | B61: Outerwear | C61: Poncho | D61: =SUMIFS('FW26 Styles'!Q5:Q504,'FW26 Styles'!A5:A504,A61,'FW26 Styles'!B5:B504,B61,'FW26 Styles'!C5:C504,C61) -> 0 | E61: =SUMIFS('FW26 Styles'!P5:P504,'FW26 Styles'!A5:A504,A61,'FW26 Styles'!B5:B504,B61,'FW26 Styles'!C5:C504,C61) -> 0 | F61: =IF(D61=0,"",1-(E61/D61)) | G61: =SUMIFS('FW26 Styles'!O5:O504,'FW26 Styles'!A5:A504,A61,'FW26 Styles'!B5:B504,B61,'FW26 Styles'!C5:C504,C61) -> 0 | J61: =IF(H61=0,"",1-(I61/H61))
A62: Clothing | B62: Outerwear | C62: New 1 | D62: =SUMIFS('FW26 Styles'!Q5:Q504,'FW26 Styles'!A5:A504,A62,'FW26 Styles'!B5:B504,B62,'FW26 Styles'!C5:C504,C62) -> 0 | E62: =SUMIFS('FW26 Styles'!P5:P504,'FW26 Styles'!A5:A504,A62,'FW26 Styles'!B5:B504,B62,'FW26 Styles'!C5:C504,C62) -> 0 | F62: =IF(D62=0,"",1-(E62/D62)) | G62: =SUMIFS('FW26 Styles'!O5:O504,'FW26 Styles'!A5:A504,A62,'FW26 Styles'!B5:B504,B62,'FW26 Styles'!C5:C504,C62) -> 0 | J62: =IF(H62=0,"",1-(I62/H62))
A63: Clothing | B63: Outerwear | C63: New 2 | D63: =SUMIFS('FW26 Styles'!Q5:Q504,'FW26 Styles'!A5:A504,A63,'FW26 Styles'!B5:B504,B63,'FW26 Styles'!C5:C504,C63) -> 0 | E63: =SUMIFS('FW26 Styles'!P5:P504,'FW26 Styles'!A5:A504,A63,'FW26 Styles'!B5:B504,B63,'FW26 Styles'!C5:C504,C63) -> 0 | F63: =IF(D63=0,"",1-(E63/D63)) | G63: =SUMIFS('FW26 Styles'!O5:O504,'FW26 Styles'!A5:A504,A63,'FW26 Styles'!B5:B504,B63,'FW26 Styles'!C5:C504,C63) -> 0 | J63: =IF(H63=0,"",1-(I63/H63))
A64: Clothing | B64: Outerwear | C64: New 3 | D64: =SUMIFS('FW26 Styles'!Q5:Q504,'FW26 Styles'!A5:A504,A64,'FW26 Styles'!B5:B504,B64,'FW26 Styles'!C5:C504,C64) -> 0 | E64: =SUMIFS('FW26 Styles'!P5:P504,'FW26 Styles'!A5:A504,A64,'FW26 Styles'!B5:B504,B64,'FW26 Styles'!C5:C504,C64) -> 0 | F64: =IF(D64=0,"",1-(E64/D64)) | G64: =SUMIFS('FW26 Styles'!O5:O504,'FW26 Styles'!A5:A504,A64,'FW26 Styles'!B5:B504,B64,'FW26 Styles'!C5:C504,C64) -> 0 | J64: =IF(H64=0,"",1-(I64/H64))
A65: Accessories | B65: Accessories | C65: Sunglasses | D65: =SUMIFS('FW26 Styles'!Q5:Q504,'FW26 Styles'!A5:A504,A65,'FW26 Styles'!B5:B504,B65,'FW26 Styles'!C5:C504,C65) -> 0 | E65: =SUMIFS('FW26 Styles'!P5:P504,'FW26 Styles'!A5:A504,A65,'FW26 Styles'!B5:B504,B65,'FW26 Styles'!C5:C504,C65) -> 0 | F65: =IF(D65=0,"",1-(E65/D65)) | G65: =SUMIFS('FW26 Styles'!O5:O504,'FW26 Styles'!A5:A504,A65,'FW26 Styles'!B5:B504,B65,'FW26 Styles'!C5:C504,C65) -> 0 | J65: =IF(H65=0,"",1-(I65/H65))
A66: Accessories | B66: Accessories | C66: Bags | D66: =SUMIFS('FW26 Styles'!Q5:Q504,'FW26 Styles'!A5:A504,A66,'FW26 Styles'!B5:B504,B66,'FW26 Styles'!C5:C504,C66) -> 0 | E66: =SUMIFS('FW26 Styles'!P5:P504,'FW26 Styles'!A5:A504,A66,'FW26 Styles'!B5:B504,B66,'FW26 Styles'!C5:C504,C66) -> 0 | F66: =IF(D66=0,"",1-(E66/D66)) | G66: =SUMIFS('FW26 Styles'!O5:O504,'FW26 Styles'!A5:A504,A66,'FW26 Styles'!B5:B504,B66,'FW26 Styles'!C5:C504,C66) -> 0 | J66: =IF(H66=0,"",1-(I66/H66))
A67: Accessories | B67: Accessories | C67: Tote Bags | D67: =SUMIFS('FW26 Styles'!Q5:Q504,'FW26 Styles'!A5:A504,A67,'FW26 Styles'!B5:B504,B67,'FW26 Styles'!C5:C504,C67) -> 0 | E67: =SUMIFS('FW26 Styles'!P5:P504,'FW26 Styles'!A5:A504,A67,'FW26 Styles'!B5:B504,B67,'FW26 Styles'!C5:C504,C67) -> 0 | F67: =IF(D67=0,"",1-(E67/D67)) | G67: =SUMIFS('FW26 Styles'!O5:O504,'FW26 Styles'!A5:A504,A67,'FW26 Styles'!B5:B504,B67,'FW26 Styles'!C5:C504,C67) -> 0 | J67: =IF(H67=0,"",1-(I67/H67))
A68: Accessories | B68: Accessories | C68: Misc | D68: =SUMIFS('FW26 Styles'!Q5:Q504,'FW26 Styles'!A5:A504,A68,'FW26 Styles'!B5:B504,B68,'FW26 Styles'!C5:C504,C68) -> 0 | E68: =SUMIFS('FW26 Styles'!P5:P504,'FW26 Styles'!A5:A504,A68,'FW26 Styles'!B5:B504,B68,'FW26 Styles'!C5:C504,C68) -> 0 | F68: =IF(D68=0,"",1-(E68/D68)) | G68: =SUMIFS('FW26 Styles'!O5:O504,'FW26 Styles'!A5:A504,A68,'FW26 Styles'!B5:B504,B68,'FW26 Styles'!C5:C504,C68) -> 0 | J68: =IF(H68=0,"",1-(I68/H68))
A69: Accessories | B69: Accessories | C69: Scarves | D69: =SUMIFS('FW26 Styles'!Q5:Q504,'FW26 Styles'!A5:A504,A69,'FW26 Styles'!B5:B504,B69,'FW26 Styles'!C5:C504,C69) -> 0 | E69: =SUMIFS('FW26 Styles'!P5:P504,'FW26 Styles'!A5:A504,A69,'FW26 Styles'!B5:B504,B69,'FW26 Styles'!C5:C504,C69) -> 0 | F69: =IF(D69=0,"",1-(E69/D69)) | G69: =SUMIFS('FW26 Styles'!O5:O504,'FW26 Styles'!A5:A504,A69,'FW26 Styles'!B5:B504,B69,'FW26 Styles'!C5:C504,C69) -> 0 | J69: =IF(H69=0,"",1-(I69/H69))
A70: Accessories | B70: Accessories | C70: Gloves | D70: =SUMIFS('FW26 Styles'!Q5:Q504,'FW26 Styles'!A5:A504,A70,'FW26 Styles'!B5:B504,B70,'FW26 Styles'!C5:C504,C70) -> 0 | E70: =SUMIFS('FW26 Styles'!P5:P504,'FW26 Styles'!A5:A504,A70,'FW26 Styles'!B5:B504,B70,'FW26 Styles'!C5:C504,C70) -> 0 | F70: =IF(D70=0,"",1-(E70/D70)) | G70: =SUMIFS('FW26 Styles'!O5:O504,'FW26 Styles'!A5:A504,A70,'FW26 Styles'!B5:B504,B70,'FW26 Styles'!C5:C504,C70) -> 0 | J70: =IF(H70=0,"",1-(I70/H70))
A71: Accessories | B71: Accessories | C71: Balaclava | D71: =SUMIFS('FW26 Styles'!Q5:Q504,'FW26 Styles'!A5:A504,A71,'FW26 Styles'!B5:B504,B71,'FW26 Styles'!C5:C504,C71) -> 0 | E71: =SUMIFS('FW26 Styles'!P5:P504,'FW26 Styles'!A5:A504,A71,'FW26 Styles'!B5:B504,B71,'FW26 Styles'!C5:C504,C71) -> 0 | F71: =IF(D71=0,"",1-(E71/D71)) | G71: =SUMIFS('FW26 Styles'!O5:O504,'FW26 Styles'!A5:A504,A71,'FW26 Styles'!B5:B504,B71,'FW26 Styles'!C5:C504,C71) -> 0 | J71: =IF(H71=0,"",1-(I71/H71))
A72: Accessories | B72: Accessories | C72: Keyring | D72: =SUMIFS('FW26 Styles'!Q5:Q504,'FW26 Styles'!A5:A504,A72,'FW26 Styles'!B5:B504,B72,'FW26 Styles'!C5:C504,C72) -> 0 | E72: =SUMIFS('FW26 Styles'!P5:P504,'FW26 Styles'!A5:A504,A72,'FW26 Styles'!B5:B504,B72,'FW26 Styles'!C5:C504,C72) -> 0 | F72: =IF(D72=0,"",1-(E72/D72)) | G72: =SUMIFS('FW26 Styles'!O5:O504,'FW26 Styles'!A5:A504,A72,'FW26 Styles'!B5:B504,B72,'FW26 Styles'!C5:C504,C72) -> 0 | J72: =IF(H72=0,"",1-(I72/H72))
A73: Accessories | B73: Accessories | C73: New 1 | D73: =SUMIFS('FW26 Styles'!Q5:Q504,'FW26 Styles'!A5:A504,A73,'FW26 Styles'!B5:B504,B73,'FW26 Styles'!C5:C504,C73) -> 0 | E73: =SUMIFS('FW26 Styles'!P5:P504,'FW26 Styles'!A5:A504,A73,'FW26 Styles'!B5:B504,B73,'FW26 Styles'!C5:C504,C73) -> 0 | F73: =IF(D73=0,"",1-(E73/D73)) | G73: =SUMIFS('FW26 Styles'!O5:O504,'FW26 Styles'!A5:A504,A73,'FW26 Styles'!B5:B504,B73,'FW26 Styles'!C5:C504,C73) -> 0 | J73: =IF(H73=0,"",1-(I73/H73))
A74: Accessories | B74: Accessories | C74: New 2 | D74: =SUMIFS('FW26 Styles'!Q5:Q504,'FW26 Styles'!A5:A504,A74,'FW26 Styles'!B5:B504,B74,'FW26 Styles'!C5:C504,C74) -> 0 | E74: =SUMIFS('FW26 Styles'!P5:P504,'FW26 Styles'!A5:A504,A74,'FW26 Styles'!B5:B504,B74,'FW26 Styles'!C5:C504,C74) -> 0 | F74: =IF(D74=0,"",1-(E74/D74)) | G74: =SUMIFS('FW26 Styles'!O5:O504,'FW26 Styles'!A5:A504,A74,'FW26 Styles'!B5:B504,B74,'FW26 Styles'!C5:C504,C74) -> 0 | J74: =IF(H74=0,"",1-(I74/H74))
A75: Accessories | B75: Accessories | C75: New 3 | D75: =SUMIFS('FW26 Styles'!Q5:Q504,'FW26 Styles'!A5:A504,A75,'FW26 Styles'!B5:B504,B75,'FW26 Styles'!C5:C504,C75) -> 0 | E75: =SUMIFS('FW26 Styles'!P5:P504,'FW26 Styles'!A5:A504,A75,'FW26 Styles'!B5:B504,B75,'FW26 Styles'!C5:C504,C75) -> 0 | F75: =IF(D75=0,"",1-(E75/D75)) | G75: =SUMIFS('FW26 Styles'!O5:O504,'FW26 Styles'!A5:A504,A75,'FW26 Styles'!B5:B504,B75,'FW26 Styles'!C5:C504,C75) -> 0 | J75: =IF(H75=0,"",1-(I75/H75))
A76: TOTAL | D76: =SUM(D15:D75) -> 0 | E76: =SUM(E15:E75) -> 0 | F76: =IF(D76=0,"",1-(E76/D76)) | G76: =SUM(G15:G75) -> 0 | H76: =SUM(H15:H75) -> 0 | I76: =SUM(I15:I75) -> 0 | J76: =IF(H76=0,"",1-(I76/H76)) | K76: =SUM(K15:K75) -> 0
A79: VARIANCE (FINAL vs PROPOSED)
A80: Main Category | B80: Category | C80: Sub Category | D80: Retail Var ($) | E80: Cost Var ($) | F80: Margin Var (pp) | G80: Units Var
A81: Headwear | B81: Scarves | C81: Premium | D81: =H15-D15 -> 0 | E81: =I15-E15 -> 0 | F81: =IF(OR(J15="",F15=""),"",J15-F15) | G81: =K15-G15 -> 0
A82: Headwear | B82: Scarves | C82: Bamboo | D82: =H16-D16 -> 0 | E82: =I16-E16 -> 0 | F82: =IF(OR(J16="",F16=""),"",J16-F16) | G82: =K16-G16 -> 0
A83: Headwear | B83: Scarves | C83: Breathable | D83: =H17-D17 -> 0 | E83: =I17-E17 -> 0 | F83: =IF(OR(J17="",F17=""),"",J17-F17) | G83: =K17-G17 -> 0
A84: Headwear | B84: Scarves | C84: Liquid | D84: =H18-D18 -> 0 | E84: =I18-E18 -> 0 | F84: =IF(OR(J18="",F18=""),"",J18-F18) | G84: =K18-G18 -> 0
A85: Headwear | B85: Scarves | C85: Decorative | D85: =H19-D19 -> 0 | E85: =I19-E19 -> 0 | F85: =IF(OR(J19="",F19=""),"",J19-F19) | G85: =K19-G19 -> 0
A86: Headwear | B86: Scarves | C86: New 1 | D86: =H20-D20 -> 0 | E86: =I20-E20 -> 0 | F86: =IF(OR(J20="",F20=""),"",J20-F20) | G86: =K20-G20 -> 0
A87: Headwear | B87: Scarves | C87: New 2 | D87: =H21-D21 -> 0 | E87: =I21-E21 -> 0 | F87: =IF(OR(J21="",F21=""),"",J21-F21) | G87: =K21-G21 -> 0
A88: Headwear | B88: Scarves | C88: New 3 | D88: =H22-D22 -> 0 | E88: =I22-E22 -> 0 | F88: =IF(OR(J22="",F22=""),"",J22-F22) | G88: =K22-G22 -> 0
A89: Headwear | B89: Hijab | C89: Premium | D89: =H23-D23 -> 0 | E89: =I23-E23 -> 0 | F89: =IF(OR(J23="",F23=""),"",J23-F23) | G89: =K23-G23 -> 0
A90: Headwear | B90: Hijab | C90: Bamboo | D90: =H24-D24 -> 0 | E90: =I24-E24 -> 0 | F90: =IF(OR(J24="",F24=""),"",J24-F24) | G90: =K24-G24 -> 0
A91: Headwear | B91: Hijab | C91: Breathable | D91: =H25-D25 -> 0 | E91: =I25-E25 -> 0 | F91: =IF(OR(J25="",F25=""),"",J25-F25) | G91: =K25-G25 -> 0
A92: Headwear | B92: Hijab | C92: New 1 | D92: =H26-D26 -> 0 | E92: =I26-E26 -> 0 | F92: =IF(OR(J26="",F26=""),"",J26-F26) | G92: =K26-G26 -> 0
... A141: Accessories | B141: Accessories | C141: New 3 | D141: =H75-D75 -> 0 | E141: =I75-E75 -> 0 | F141: =IF(OR(J75="",F75=""),"",J75-F75) | G141: =K75-G75 -> 0
A145: APPROVALS
A146: Role | B146: Name | C146: Date | D146: Signature / Approval
A147: Merchandiser
A148: Buyer
A149: Head of Buying
A150: Finance
